Workbook

Sheet Dash
A1: Signal | C1: Value | E1: Days | K1: Ticker Description | L1: Last %Change | M1: Ticker | N1: TOS Ticker | O1: HE OL | P1: TrTn OL | Q1: MQ | R1: QQ | S1: Last | T1: A_TrendValue | U1: A_TradeValue | V1: %BRR | X1: Low | Y1: High | Z1: Invest | AB1: Main Date | AC1: Data Refresh Dates | AF1: Data Dates | AG1: Imported Date | AH1: Incl Date Range | AJ1: Investments | AK1: Amount | AM1: Desc | AN1: Desc Date | AO1: TD Import Date Time | AP1: TL Import Date | AQ1: TW Import Date | AR1: TD Import Date | AS1: TO Import Date
A2: Holiday? | C2: =_xlfn.MINIFS(Data!$O:$O,Data!$O:$O,">" & Dash!$AB$2) -> 46167 | E2: =_xlfn.DAYS(C2,Dash!$AB$2) -> 25 | K2: VIX | L2: =_xlfn.XLOOKUP(M2,MA!C:C,MA!H:H,"") | M2: ^VIX | N2: VIX | O2: =_xlfn.XLOOKUP(M2,MA!C:C,MA!VP:VP,"") | P2: =_xlfn.XLOOKUP(M2,MA!C:C,MA!VQ:VQ,"") | S2: =_xlfn.XLOOKUP(M2,MA!C:C,MA!D:D,"") | T2: =_xlfn.XLOOKUP(M2,MA!C:C,MA!K:K,"") | U2: =_xlfn.XLOOKUP(M2,MA!C:C,MA!L:L,"") | V2: =(T2-S2)*100/(T2-U2) -> #VALUE! | X2: 19 | Y2: 30 | Z2: =IF(S2<=X2,"Y",IF(S2>=Y2,"N","W")) -> N | AB2: 46142 | AC2: Today | AF2: RR | AG2: =MAX(RR!D:D) -> 46141 | AJ2: Total | AK2: 200000 | AM2: Today | AN2: =Dash!$AB$2 -> 46142 | AO2: =_xlfn.MAXIFS(TD!B:B,TD!B:B,"<=" & AN2) -> 46141.688 | AP2: =_xlfn.MAXIFS(TL!B:B,TL!B:B,"<=" & AN2) -> 46141.688 | AQ2: =_xlfn.MAXIFS(TW!B:B,TW!B:B,"<=" & AN2) -> 46141.688 | AR2: =INT(AO2) -> 46141 | AS2: =_xlfn.MAXIFS(TO!B:B,TO!B:B,"<=" & AN2) -> 46139.688
A3: Incl Eco Days | C3: =$AB$2+7 -> 46149 | E3: =_xlfn.DAYS(C3,Dash!$AB$2) -> 7 | K3: CBOE VIX VOLATILITY INDEX | L3: =_xlfn.XLOOKUP(M3,MA!C:C,MA!H:H,"") | M3: ^VVIX | N3: VVIX | O3: =_xlfn.XLOOKUP(M3,MA!C:C,MA!VP:VP,"") | P3: =_xlfn.XLOOKUP(M3,MA!C:C,MA!VQ:VQ,"") | S3: =_xlfn.XLOOKUP(M3,MA!C:C,MA!D:D,"") | T3: =_xlfn.XLOOKUP(M3,MA!C:C,MA!K:K,"") | U3: =_xlfn.XLOOKUP(M3,MA!C:C,MA!L:L,"") | V3: =(T3-S3)*100/(T3-U3) -> #VALUE! | X3: 100 | Y3: 150 | Z3: =IF(S3<=X3,"Y",IF(S3>=Y3,"N","W")) -> N | AC3: Overwrite Main date | AF3: CAll | AG3: =MAX(call!C:C) -> 46141 | AH3: =EDATE($AB$2, -1) -> 46111 | AJ3: PS | AK3: 400000 | AM3: Day Ago | AN3: =WORKDAY(AN2,-1) -> 46141 | AO3: =_xlfn.MAXIFS(TD!B:B,TD!B:B,"<=" & AN3) -> 0 | AP3: =_xlfn.MAXIFS(TL!B:B,TL!B:B,"<=" & AN3) -> 0 | AQ3: =_xlfn.MAXIFS(TW!B:B,TW!B:B,"<=" & AN3) -> 0 | AR3: =INT(AO3) -> 0 | AS3: =_xlfn.MAXIFS(TO!B:B,TO!B:B,"<=" & AN3) -> 46139.688
A4: Econ.Ind 1 | B4: 1 | C4: {=INDEX(_xlfn._xlws.SORT(_xlfn._xlws.FILTER(Data!$C:$H, (Data!$L:$L="Y"),""),3),B4)} -> Fed Blackout Period | D4: 46130 | E4: -12 | F4: BULLISH | G4: 46130 | H4: 46189 | K4: CBOE RUSSell 2000 VOLATILITY IN | L4: =_xlfn.XLOOKUP(M4,MA!C:C,MA!H:H,"") | M4: ^RVX | N4: RVX | O4: =_xlfn.XLOOKUP(M4,MA!C:C,MA!VP:VP,"") | P4: =_xlfn.XLOOKUP(M4,MA!C:C,MA!VQ:VQ,"") | S4: =_xlfn.XLOOKUP(M4,MA!C:C,MA!D:D,"") | T4: =_xlfn.XLOOKUP(M4,MA!C:C,MA!K:K,"") | U4: =_xlfn.XLOOKUP(M4,MA!C:C,MA!L:L,"") | V4: =(T4-S4)*100/(T4-U4) -> #VALUE! | X4: 22 | Y4: 40 | Z4: =IF(S4<=X4,"Y",IF(S4>=Y4,"N","W")) -> N | AB4: =IF(AB18>=AB14,"Y","N") -> Y | AC4: After close TOS Export used? | AF4: ETF | AG4: =MAX(etf!C:C) -> 46019 | AH4: =EDATE($AB$2, -1) -> 46111 | AJ4: SSS | AK4: 100000 | AM4: 3 Days Ago | AN4: =WORKDAY(AN2,-3) -> 46139 | AO4: =_xlfn.MAXIFS(TD!B:B,TD!B:B,"<=" & AN4) -> 0 | AP4: =_xlfn.MAXIFS(TL!B:B,TL!B:B,"<=" & AN4) -> 0 | AQ4: =_xlfn.MAXIFS(TW!B:B,TW!B:B,"<=" & AN4) -> 0 | AR4: =INT(AO4) -> 0 | AS4: =_xlfn.MAXIFS(TO!B:B,TO!B:B,"<=" & AN4) -> 0
A5: Econ.Ind 2 | B5: 2 | C5: {=INDEX(_xlfn._xlws.SORT(_xlfn._xlws.FILTER(Data!$C:$H, (Data!$L:$L="Y"),""),3),B5)} -> Month end marking - 3 days before - Buy CAlls | D5: 46142 | E5: -3 | F5: BULLISH | G5: 46139 | H5: 46142 | K5: Nasdaq-100 vol Index (out $ opts) | L5: =_xlfn.XLOOKUP(M5,MA!C:C,MA!H:H,"") | M5: ^VXN | N5: VXN:CGI | O5: =_xlfn.XLOOKUP(M5,MA!C:C,MA!VP:VP,"") | P5: =_xlfn.XLOOKUP(M5,MA!C:C,MA!VQ:VQ,"") | S5: =_xlfn.XLOOKUP(M5,MA!C:C,MA!D:D,"") | T5: =_xlfn.XLOOKUP(M5,MA!C:C,MA!K:K,"") | U5: =_xlfn.XLOOKUP(M5,MA!C:C,MA!L:L,"") | V5: =(T5-S5)*100/(T5-U5) -> #VALUE! | X5: 22 | Y5: 32 | Z5: =IF(S5<=X5,"Y",IF(S5>=Y5,"N","W")) -> N | AB5: =IF(AB22>=AB14,"Y","N") -> Y | AC5: After close Y Export used? | AF5: PS | AG5: =MAX(psRk!A:A) -> 46146 | AJ5: My | AK5: 20000 | AM5: Wk Ago | AN5: =WORKDAY(AN2,-5) -> 46135 | AO5: =_xlfn.MAXIFS(TD!B:B,TD!B:B,"<=" & AN5) -> 0 | AP5: =_xlfn.MAXIFS(TL!B:B,TL!B:B,"<=" & AN5) -> 0 | AQ5: =_xlfn.MAXIFS(TW!B:B,TW!B:B,"<=" & AN5) -> 0 | AR5: =INT(AO5) -> 0 | AS5: =_xlfn.MAXIFS(TO!B:B,TO!B:B,"<=" & AN5) -> 0
A6: Econ.Ind 3 | B6: 3 | C6: {=INDEX(_xlfn._xlws.SORT(_xlfn._xlws.FILTER(Data!$C:$H, (Data!$L:$L="Y"),""),3),B6)} -> Month end marking - 3 days after - Buy Puts (Crypto) | D6: 46142 | E6: -2 | F6: BEARISH | G6: 46140 | H6: 46147 | K6: CBOE Gold Volatitity Index | L6: =_xlfn.XLOOKUP(M6,MA!C:C,MA!H:H,"") | M6: ^GVZ | N6: GVZ:CGI | O6: =_xlfn.XLOOKUP(M6,MA!C:C,MA!VP:VP,"") | P6: =_xlfn.XLOOKUP(M6,MA!C:C,MA!VQ:VQ,"") | S6: =_xlfn.XLOOKUP(M6,MA!C:C,MA!D:D,"") | T6: =_xlfn.XLOOKUP(M6,MA!C:C,MA!K:K,"") | U6: =_xlfn.XLOOKUP(M6,MA!C:C,MA!L:L,"") | V6: =(T6-S6)*100/(T6-U6) -> #VALUE! | X6: 26 | Y6: 32 | Z6: =IF(S6<=X6,"Y",IF(S6>=Y6,"N","W")) -> N | AB6: Y | AC6: Use latest Y export | AF6: SSS | AG6: =MAX(ssH!B:B) -> 46140 | AH6: =EDATE($AB$2, -1) -> 46111 | AM6: 3 Wks Ago | AN6: =WORKDAY(AN2,-5*3) -> 46121 | AO6: =_xlfn.MAXIFS(TD!B:B,TD!B:B,"<=" & AN6) -> 0 | AP6: =_xlfn.MAXIFS(TL!B:B,TL!B:B,"<=" & AN6) -> 0 | AQ6: =_xlfn.MAXIFS(TW!B:B,TW!B:B,"<=" & AN6) -> 0 | AR6: =INT(AO6) -> 0 | AS6: =_xlfn.MAXIFS(TO!B:B,TO!B:B,"<=" & AN6) -> 0
A7: Econ.Ind 4 | B7: 4 | C7: {=INDEX(_xlfn._xlws.SORT(_xlfn._xlws.FILTER(Data!$C:$H, (Data!$L:$L="Y"),""),3),B7)} -> Personal Consumption Expenditures - PCE | D7: 46142 | E7: -1 | F7: 0 | G7: 46141 | H7: 46141 | K7: CBOE Crude Oil Volatility Index | L7: =_xlfn.XLOOKUP(M7,MA!C:C,MA!H:H,"") | M7: ^OVX | N7: OVX:CGI | O7: =_xlfn.XLOOKUP(M7,MA!C:C,MA!VP:VP,"") | P7: =_xlfn.XLOOKUP(M7,MA!C:C,MA!VQ:VQ,"") | S7: =_xlfn.XLOOKUP(M7,MA!C:C,MA!D:D,"") | T7: =_xlfn.XLOOKUP(M7,MA!C:C,MA!K:K,"") | U7: =_xlfn.XLOOKUP(M7,MA!C:C,MA!L:L,"") | V7: =(T7-S7)*100/(T7-U7) -> #VALUE! | X7: 30 | Y7: 50 | Z7: =IF(S7<=X7,"Y",IF(S7>=Y7,"N","W")) -> N | AB7: N | AC7: Use Previous Close Date | AF7: II | AH7: =EDATE($AB$2, -1) -> 46111 | AM7: Month Ago | AN7: =WORKDAY(AN2,-5*4) -> 46114 | AO7: =_xlfn.MAXIFS(TD!B:B,TD!B:B,"<=" & AN7) -> 0 | AP7: =_xlfn.MAXIFS(TL!B:B,TL!B:B,"<=" & AN7) -> 0 | AQ7: =_xlfn.MAXIFS(TW!B:B,TW!B:B,"<=" & AN7) -> 0 | AR7: =INT(AO7) -> 0 | AS7: =_xlfn.MAXIFS(TO!B:B,TO!B:B,"<=" & AN7) -> 0
A8: Econ.Ind 5 | B8: 5 | C8: {=INDEX(_xlfn._xlws.SORT(_xlfn._xlws.FILTER(Data!$C:$H, (Data!$L:$L="Y"),""),3),B8)} -> Gross domestic product - GDP | D8: 46142 | E8: -1 | F8: 0 | G8: 46141 | H8: 46141 | K8: ICE BofAML MOVE Index | L8: =_xlfn.XLOOKUP(M8,MA!C:C,MA!H:H,"") | M8: ^MOVE | N8: MOVE:GIF | O8: =_xlfn.XLOOKUP(M8,MA!C:C,MA!VP:VP,"") | P8: =_xlfn.XLOOKUP(M8,MA!C:C,MA!VQ:VQ,"") | S8: =_xlfn.XLOOKUP(M8,MA!C:C,MA!D:D,"") | T8: =_xlfn.XLOOKUP(M8,MA!C:C,MA!K:K,"") | U8: =_xlfn.XLOOKUP(M8,MA!C:C,MA!L:L,"") | V8: =(T8-S8)*100/(T8-U8) -> #VALUE! | X8: 100 | Y8: 120 | Z8: =IF(S8<=X8,"Y",IF(S8>=Y8,"N","W")) -> N | AB8: 46141 | AC8: Overwrite Market Close Date | AM8: 2 Month Ago | AN8: =WORKDAY(AN2,-5*4*2) -> 46086 | AO8: =_xlfn.MAXIFS(TD!B:B,TD!B:B,"<=" & AN8) -> 0 | AP8: =_xlfn.MAXIFS(TL!B:B,TL!B:B,"<=" & AN8) -> 0 | AQ8: =_xlfn.MAXIFS(TW!B:B,TW!B:B,"<=" & AN8) -> 0 | AR8: =INT(AO8) -> 0 | AS8: =_xlfn.MAXIFS(TO!B:B,TO!B:B,"<=" & AN8) -> 0
A9: Econ.Ind 6 | B9: 6 | C9: {=INDEX(_xlfn._xlws.SORT(_xlfn._xlws.FILTER(Data!$C:$H, (Data!$L:$L="Y"),""),3),B9)} -> Pending Home Sales | D9: 46142 | E9: -1 | F9: 0 | G9: 46141 | H9: 46141 | K9: DJIA VOLATILITY | L9: =_xlfn.XLOOKUP(M9,MA!C:C,MA!H:H,"") | M9: ^VXD | N9: VXD | O9: =_xlfn.XLOOKUP(M9,MA!C:C,MA!VP:VP,"") | P9: =_xlfn.XLOOKUP(M9,MA!C:C,MA!VQ:VQ,"") | S9: =_xlfn.XLOOKUP(M9,MA!C:C,MA!D:D,"") | T9: =_xlfn.XLOOKUP(M9,MA!C:C,MA!K:K,"") | U9: =_xlfn.XLOOKUP(M9,MA!C:C,MA!L:L,"") | V9: =(T9-S9)*100/(T9-U9) -> #VALUE! | X9: 20 | Y9: 30 | Z9: =IF(S9<=X9,"Y",IF(S9>=Y9,"N","W")) -> N | AB9: =IF(AND(WORKDAY(Dash!$AB$2-1,1,Data!$O$2:$O$31)=Dash!$AB$2, OR(Dash!$AB$2<TODAY(),HOUR(NOW())>=16)), Dash!$AB$2, WORKDAY(Dash!$AB$2,-1,Data!$O$2:$O$31)) -> 46142 | AC9: Calculated Market Close Date
A10: Econ.Ind 7 | B10: 7 | C10: {=INDEX(_xlfn._xlws.SORT(_xlfn._xlws.FILTER(Data!$C:$H, (Data!$L:$L="Y"),""),3),B10)} -> Nonfarm payrolls | D10: 46143 | E10: 0 | F10: BEARISH | G10: 46142 | H10: 46142 | O10: =_xlfn.XLOOKUP(M10,MA!C:C,MA!VP:VP,"") -> 0 | P10: =_xlfn.XLOOKUP(M10,MA!C:C,MA!VQ:VQ,"") -> 0 | AB10: =WORKDAY(AB9,-1,Data!$O$2:$O$31) -> 46141 | AC10: Prev Close Date
A11: Econ.Ind 8 | B11: 8 | C11: {=INDEX(_xlfn._xlws.SORT(_xlfn._xlws.FILTER(Data!$C:$H, (Data!$L:$L="Y"),""),3),B11)} -> ISM Mfg | D11: 46145 | E11: 1 | F11: 0 | G11: 46143 | H11: 46143 | K11: S&P500 | L11: =_xlfn.XLOOKUP(M11,MA!C:C,MA!H:H,"") | M11: ^SPX | N11: SPX | O11: =_xlfn.XLOOKUP(M11,MA!C:C,MA!VP:VP,"") | P11: =_xlfn.XLOOKUP(M11,MA!C:C,MA!VQ:VQ,"") | Q11: =_xlfn.XLOOKUP(M11,MA!C:C,MA!IG:IG,"") | R11: =_xlfn.XLOOKUP(M11,MA!C:C,MA!IS:IS,"") | S11: =_xlfn.XLOOKUP(M11,MA!C:C,MA!D:D,"") | T11: =_xlfn.XLOOKUP(M11,MA!C:C,MA!K:K,"") | U11: =_xlfn.XLOOKUP(M11,MA!C:C,MA!L:L,"") | V11: =(T11-S11)*100/(T11-U11) -> #VALUE! | Z11: {=_xlfn.IFS(AND(O11>0,P11>=0),"Y",AND(O11<0,P11<=0),"N",AND(O11>0),"W",AND(O11=0,P11>0),"W",TRUE,"")} -> Y | AB11: =AB10 + TIME(16,0,0) -> 46141.667 | AC11: Prev Close End Date and Time
A12: Econ.Ind 9 | B12: 9 | C12: {=INDEX(_xlfn._xlws.SORT(_xlfn._xlws.FILTER(Data!$C:$H, (Data!$L:$L="Y"),""),3),B12)} -> ISM Svcs | D12: 46146 | E12: 1 | F12: 0 | G12: 46143 | H12: 46143 | K12: Nasdaq | L12: =_xlfn.XLOOKUP(M12,MA!C:C,MA!H:H,"") | M12: ^IXIC | N12: $COMP | O12: =_xlfn.XLOOKUP(M12,MA!C:C,MA!VP:VP,"") | P12: =_xlfn.XLOOKUP(M12,MA!C:C,MA!VQ:VQ,"") | Q12: =_xlfn.XLOOKUP(M12,MA!C:C,MA!IG:IG,"") | R12: =_xlfn.XLOOKUP(M12,MA!C:C,MA!IS:IS,"") | S12: =_xlfn.XLOOKUP(M12,MA!C:C,MA!D:D,"") | T12: =_xlfn.XLOOKUP(M12,MA!C:C,MA!K:K,"") | U12: =_xlfn.XLOOKUP(M12,MA!C:C,MA!L:L,"") | V12: =(T12-S12)*100/(T12-U12) -> #VALUE! | Z12: {=_xlfn.IFS(AND(O12>0,P12>=0),"Y",AND(O12<0,P12<=0),"N",AND(O12>0),"W",AND(O12=0,P12>0),"W",TRUE,"")} -> Y | AB12: =IF($AB$8<>"",$AB$8,IF(AB7="N",AB9,AB10)) -> 46141 | AC12: Using Date as Market Close
A13: Econ.Ind 10 | B13: 10 | C13: {=INDEX(_xlfn._xlws.SORT(_xlfn._xlws.FILTER(Data!$C:$H, (Data!$L:$L="Y"),""),3),B13)} -> Monthly options exp - 2 weeks before (Bullish) | D13: 46157 | E13: 1 | F13: BULLISH | G13: 46143 | H13: 46157 | K13: RusSell 2000 | L13: =_xlfn.XLOOKUP(M13,MA!C:C,MA!H:H,"") | M13: ^RUT | N13: RUT | O13: =_xlfn.XLOOKUP(M13,MA!C:C,MA!VP:VP,"") | P13: =_xlfn.XLOOKUP(M13,MA!C:C,MA!VQ:VQ,"") | Q13: =_xlfn.XLOOKUP(M13,MA!C:C,MA!IG:IG,"") | R13: =_xlfn.XLOOKUP(M13,MA!C:C,MA!IS:IS,"") | S13: =_xlfn.XLOOKUP(M13,MA!C:C,MA!D:D,"") | T13: =_xlfn.XLOOKUP(M13,MA!C:C,MA!K:K,"") | U13: =_xlfn.XLOOKUP(M13,MA!C:C,MA!L:L,"") | V13: =(T13-S13)*100/(T13-U13) -> #VALUE! | Z13: {=_xlfn.IFS(AND(O13>0,P13>=0),"Y",AND(O13<0,P13<=0),"N",AND(O13>0),"W",AND(O13=0,P13>0),"W",TRUE,"")} -> Y | AB13: =AB12 + TIME(9,30,0) -> 46141.396 | AC13: Market Close Start Date and Time
A14: Econ.Ind 11 | B14: 11 | C14: {=INDEX(_xlfn._xlws.SORT(_xlfn._xlws.FILTER(Data!$C:$H, (Data!$L:$L="Y"),""),3),B14)} -> ADP payrolls | D14: 46148 | E14: 5 | F14: BEARISH | G14: 46147 | H14: 46147 | K14: High Yield | L14: =_xlfn.XLOOKUP(M14,MA!C:C,MA!H:H,"") | M14: HYG | N14: HYG | O14: =_xlfn.XLOOKUP(M14,MA!C:C,MA!VP:VP,"") | P14: =_xlfn.XLOOKUP(M14,MA!C:C,MA!VQ:VQ,"") | Q14: =_xlfn.XLOOKUP(M14,MA!C:C,MA!IG:IG,"") | R14: =_xlfn.XLOOKUP(M14,MA!C:C,MA!IS:IS,"") | S14: =_xlfn.XLOOKUP(M14,MA!C:C,MA!D:D,"") | T14: =_xlfn.XLOOKUP(M14,MA!C:C,MA!K:K,"") | U14: =_xlfn.XLOOKUP(M14,MA!C:C,MA!L:L,"") | V14: =(T14-S14)*100/(T14-U14) -> #VALUE! | Z14: {=_xlfn.IFS(AND(O14>0,P14>=0),"Y",AND(O14<0,P14<=0),"N",AND(O14>0),"W",AND(O14=0,P14>0),"W",TRUE,"")} -> Y | AB14: =AB12 + TIME(16,0,0) -> 46141.667 | AC14: Market Close End Date and Time
A15: Econ.Ind 12 | B15: 12 | C15: {=INDEX(_xlfn._xlws.SORT(_xlfn._xlws.FILTER(Data!$C:$H, (Data!$L:$L="Y"),""),3),B15)} -> New Home Sales | D15: 46148 | E15: 5 | F15: 0 | G15: 46147 | H15: 46147 | K15: Investment Grade Corporate Bond ETF | L15: =_xlfn.XLOOKUP(M15,MA!C:C,MA!H:H,"") | M15: LQD | N15: LQD | O15: =_xlfn.XLOOKUP(M15,MA!C:C,MA!VP:VP,"") | P15: =_xlfn.XLOOKUP(M15,MA!C:C,MA!VQ:VQ,"") | Q15: =_xlfn.XLOOKUP(M15,MA!C:C,MA!IG:IG,"") | R15: =_xlfn.XLOOKUP(M15,MA!C:C,MA!IS:IS,"") | S15: =_xlfn.XLOOKUP(M15,MA!C:C,MA!D:D,"") | T15: =_xlfn.XLOOKUP(M15,MA!C:C,MA!K:K,"") | U15: =_xlfn.XLOOKUP(M15,MA!C:C,MA!L:L,"") | V15: =(T15-S15)*100/(T15-U15) -> #VALUE! | Z15: {=_xlfn.IFS(AND(O15>0,P15>=0),"Y",AND(O15<0,P15<=0),"N",AND(O15>0),"W",AND(O15=0,P15>0),"W",TRUE,"")} -> Y | AB15: =WORKDAY(Dash!$AB$12,1,Data!$O$2:$O$31) -> 46142 | AC15: Next Close Date
A16: Econ.Ind 13 | B16: 13 | C16: {=INDEX(_xlfn._xlws.SORT(_xlfn._xlws.FILTER(Data!$C:$H, (Data!$L:$L="Y"),""),3),B16)} -> U.S. Michigan Consumer Sentiment (2 Fridy of M) | D16: 46150 | E16: 7 | F16: BEARISH | G16: 46149 | H16: 46149 | O16: =_xlfn.XLOOKUP(M16,MA!C:C,MA!VP:VP,"") -> 0 | P16: =_xlfn.XLOOKUP(M16,MA!C:C,MA!VQ:VQ,"") -> 0 | Q16: =_xlfn.XLOOKUP(M16,MA!C:C,MA!IG:IG,"") -> 0 | R16: =_xlfn.XLOOKUP(M16,MA!C:C,MA!IS:IS,"") -> 0 | AB16: =AB15 + TIME(9,30,0) -> 46142.396 | AC16: Next Close Start Date and Time
K17: 30-Year U.S. Treasury Yield | L17: =_xlfn.XLOOKUP(M17,MA!C:C,MA!H:H,"") | M17: ^TYX | N17: TYX:CGI | O17: =_xlfn.XLOOKUP(M17,MA!C:C,MA!VP:VP,"") | P17: =_xlfn.XLOOKUP(M17,MA!C:C,MA!VQ:VQ,"") | Q17: =_xlfn.XLOOKUP(M17,MA!C:C,MA!IG:IG,"") | R17: =_xlfn.XLOOKUP(M17,MA!C:C,MA!IS:IS,"") | S17: =_xlfn.XLOOKUP(M17,MA!C:C,MA!D:D,0)/10 -> 0 | T17: =_xlfn.XLOOKUP(M17,MA!C:C,MA!K:K,"") | U17: =_xlfn.XLOOKUP(M17,MA!C:C,MA!L:L,"") | V17: =(S17-U17)*100/(T17-U17) -> #VALUE! | Z17: {=_xlfn.IFS(O17>0,"Y",O17<0,"N",TRUE,"")} -> Y | AB17: =AB15 + TIME(16,0,0) -> 46142.667 | AC17: Next Close End Date and Time
K18: 10-Year U.S. Treasury Yield | L18: =_xlfn.XLOOKUP(M18,MA!C:C,MA!H:H,"") | M18: ^TNX | N18: TNX:CGI | O18: =_xlfn.XLOOKUP(M18,MA!C:C,MA!VP:VP,"") | P18: =_xlfn.XLOOKUP(M18,MA!C:C,MA!VQ:VQ,"") | Q18: =_xlfn.XLOOKUP(M18,MA!C:C,MA!IG:IG,"") | R18: =_xlfn.XLOOKUP(M18,MA!C:C,MA!IS:IS,"") | S18: =_xlfn.XLOOKUP(M18,MA!C:C,MA!D:D,0)/10 -> 0 | T18: =_xlfn.XLOOKUP(M18,MA!C:C,MA!K:K,"") | U18: =_xlfn.XLOOKUP(M18,MA!C:C,MA!L:L,"") | V18: =(S18-U18)*100/(T18-U18) -> #VALUE! | Z18: {=_xlfn.IFS(O18>0,"Y",O18<0,"N",TRUE,"")} -> Y | AB18: =_xlfn.MAXIFS(TW!B:B,TW!B:B,"<=" & AB16) -> 46141.688 | AC18: TOS Weekly export Date
K19: 2-Year U.S. Treasury Yield | L19: =_xlfn.XLOOKUP(MA!#REF!&M19,Y!$D:$D,Y!$M:$M) -> #REF! | M19: 2YY=F | N19: DGS2:FRED | O19: =_xlfn.XLOOKUP(M19,MA!C:C,MA!VP:VP,"") | P19: =_xlfn.XLOOKUP(M19,MA!C:C,MA!VQ:VQ,"") | Q19: =_xlfn.XLOOKUP(M19,MA!C:C,MA!IG:IG,"") | R19: =_xlfn.XLOOKUP(M19,MA!C:C,MA!IS:IS,"") | S19: =_xlfn.XLOOKUP($AB$23&M19,Y!$D:$D,Y!$K:$K) -> #N/A | T19: =_xlfn.XLOOKUP(N19,RR!F:F,RR!I:I) -> #N/A | U19: =_xlfn.XLOOKUP(N19,RR!F:F,RR!J:J) -> #N/A | V19: =(S19-U19)*100/(T19-U19) -> #N/A | Z19: {=_xlfn.IFS(O19>0,"Y",O19<0,"N",TRUE,"")} -> Y | AB19: =_xlfn.MAXIFS(TD!B:B,TD!B:B,">=" & AB14,TD!B:B,"<=" & AB16) -> 46141.688 | AC19: TOS Daily export Date
B20: Ticker | C20: Earnings Days | F20: HE OL | G20: TrTn OL | O20: =_xlfn.XLOOKUP(M20,MA!C:C,MA!VP:VP,"") -> 0 | P20: =_xlfn.XLOOKUP(M20,MA!C:C,MA!VQ:VQ,"") -> 0 | Q20: =_xlfn.XLOOKUP(M20,MA!C:C,MA!IG:IG,"") -> 0 | R20: =_xlfn.XLOOKUP(M20,MA!C:C,MA!IS:IS,"") -> 0 | AB20: =_xlfn.MAXIFS(TO!B:B,TO!B:B,">=" & AN5,TO!B:B,"<=" & AB16) -> 46139.688 | AC20: TOS Other export Date
B21: {=_xlfn._xlws.SORT(_xlfn._xlws.FILTER(MA!JA2:JB179,(MA!JB2:JB179>=0)*(MA!JB2:JB179<7)*(MA!UY2:UY179=1)),2,1)} -> #VALUE! | F21: =IF(B21<>"",_xlfn.XLOOKUP(B21,MA!C:C,MA!VP:VP,""),"") -> #VALUE! | G21: =IF(B21<>"",_xlfn.XLOOKUP(B21,MA!C:C,MA!VQ:VQ,""),"") -> #VALUE! | K21: US Dollar | L21: =_xlfn.XLOOKUP(M21,MA!C:C,MA!H:H,"") | M21: ^NYICDX | N21: $DXY | O21: =_xlfn.XLOOKUP(M21,MA!C:C,MA!VP:VP,"") | P21: =_xlfn.XLOOKUP(M21,MA!C:C,MA!VQ:VQ,"") | Q21: =_xlfn.XLOOKUP(M21,MA!C:C,MA!IG:IG,"") | R21: =_xlfn.XLOOKUP(M21,MA!C:C,MA!IS:IS,"") | S21: =_xlfn.XLOOKUP(M21,MA!C:C,MA!D:D,"") | T21: =_xlfn.XLOOKUP(M21,MA!C:C,MA!K:K,"") | U21: =_xlfn.XLOOKUP(M21,MA!C:C,MA!L:L,"") | V21: =(T21-S21)*100/(T21-U21) -> #VALUE! | X21: 100 | Y21: 105 | Z21: {=_xlfn.IFS(AND(O21>0,P21>=0),"Y",AND(O21<0,P21<=0),"N",AND(O21>0),"W",AND(O21=0,P21>0),"W",TRUE,"")} -> Y | AB21: =_xlfn.MAXIFS(TL!B:B,TL!B:B,">=" & AB13,TL!B:B,"<=" & AB17) -> 46141.688 | AC21: TOS Latest export Date
F22: =IF(B22<>"",_xlfn.XLOOKUP(B22,MA!C:C,MA!VP:VP,""),"") | G22: =IF(B22<>"",_xlfn.XLOOKUP(B22,MA!C:C,MA!VQ:VQ,""),"") | K22: Euro to U.S. Dollar | L22: =_xlfn.XLOOKUP(M22,MA!C:C,MA!H:H,"") | M22: EURUSD=X | N22: /6E | O22: =_xlfn.XLOOKUP(M22,MA!C:C,MA!VP:VP,"") | P22: =_xlfn.XLOOKUP(M22,MA!C:C,MA!VQ:VQ,"") | Q22: =_xlfn.XLOOKUP(M22,MA!C:C,MA!IG:IG,"") | R22: =_xlfn.XLOOKUP(M22,MA!C:C,MA!IS:IS,"") | S22: =_xlfn.XLOOKUP(M22,MA!C:C,MA!D:D,"") | T22: =_xlfn.XLOOKUP(M22,MA!C:C,MA!K:K,"") | U22: =_xlfn.XLOOKUP(M22,MA!C:C,MA!L:L,"") | V22: =(T22-S22)*100/(T22-U22) -> #VALUE! | Z22: {=_xlfn.IFS(AND(O22>0,P22>=0),"Y",AND(O22<0,P22<=0),"N",AND(O22>0),"W",AND(O22=0,P22>0),"W",TRUE,"")} -> Y | AB22: =_xlfn.MAXIFS(Y!B:B,Y!B:B,">=" & AB14,Y!B:B,"<=" & AB16) -> 46141.688 | AC22: Y Market Close export Date
F23: =IF(B23<>"",_xlfn.XLOOKUP(B23,MA!C:C,MA!VP:VP,""),"") | G23: =IF(B23<>"",_xlfn.XLOOKUP(B23,MA!C:C,MA!VQ:VQ,""),"") | K23: U.S. Dollar to Japanese Yen | L23: =_xlfn.XLOOKUP(M23,MA!C:C,MA!H:H,"") | M23: JPYUSD=X | N23: /6J | O23: =_xlfn.XLOOKUP(M23,MA!C:C,MA!VP:VP,"") | P23: =_xlfn.XLOOKUP(M23,MA!C:C,MA!VQ:VQ,"") | Q23: =_xlfn.XLOOKUP(M23,MA!C:C,MA!IG:IG,"") | R23: =_xlfn.XLOOKUP(M23,MA!C:C,MA!IS:IS,"") | S23: =_xlfn.XLOOKUP(M23,MA!C:C,MA!D:D,"") | T23: =_xlfn.XLOOKUP(M23,MA!C:C,MA!K:K,"") | U23: =_xlfn.XLOOKUP(M23,MA!C:C,MA!L:L,"") | V23: =(T23-S23)*100/(T23-U23) -> #VALUE! | Z23: {=_xlfn.IFS(AND(O23>0,P23>=0),"Y",AND(O23<0,P23<=0),"N",AND(O23>0),"W",AND(O23=0,P23>0),"W",TRUE,"")} -> Y | AB23: =_xlfn.MAXIFS(Y!B:B,Y!B:B,">=" & AB11,Y!B:B,"<=" & AB17) -> 46141.688 | AC23: Y Latest export Date
F24: =IF(B24<>"",_xlfn.XLOOKUP(B24,MA!C:C,MA!VP:VP,""),"") | G24: =IF(B24<>"",_xlfn.XLOOKUP(B24,MA!C:C,MA!VQ:VQ,""),"") | K24: British Pound to U.S. Dollar | L24: =_xlfn.XLOOKUP(M24,MA!C:C,MA!H:H,"") | M24: GBPUSD=X | N24: /6B | O24: =_xlfn.XLOOKUP(M24,MA!C:C,MA!VP:VP,"") | P24: =_xlfn.XLOOKUP(M24,MA!C:C,MA!VQ:VQ,"") | Q24: =_xlfn.XLOOKUP(M24,MA!C:C,MA!IG:IG,"") | R24: =_xlfn.XLOOKUP(M24,MA!C:C,MA!IS:IS,"") | S24: =_xlfn.XLOOKUP(M24,MA!C:C,MA!D:D,"") | T24: =_xlfn.XLOOKUP(M24,MA!C:C,MA!K:K,"") | U24: =_xlfn.XLOOKUP(M24,MA!C:C,MA!L:L,"") | V24: =(T24-S24)*100/(T24-U24) -> #VALUE! | Z24: {=_xlfn.IFS(AND(O24>0,P24>=0),"Y",AND(O24<0,P24<=0),"N",AND(O24>0),"W",AND(O24=0,P24>0),"W",TRUE,"")} -> Y | AB24: =IF($AB$23>$AB$21,"Y","N") -> N | AC24: Latest Y or TOS (N)
F25: =IF(B25<>"",_xlfn.XLOOKUP(B25,MA!C:C,MA!VP:VP,""),"") | G25: =IF(B25<>"",_xlfn.XLOOKUP(B25,MA!C:C,MA!VQ:VQ,""),"") | K25: Canadian Dollar to U.S. Dollar | L25: =_xlfn.XLOOKUP(M25,MA!C:C,MA!H:H,"") | M25: CADUSD=X | N25: /6C | O25: =_xlfn.XLOOKUP(M25,MA!C:C,MA!VP:VP,"") | P25: =_xlfn.XLOOKUP(M25,MA!C:C,MA!VQ:VQ,"") | Q25: =_xlfn.XLOOKUP(M25,MA!C:C,MA!IG:IG,"") | R25: =_xlfn.XLOOKUP(M25,MA!C:C,MA!IS:IS,"") | S25: =_xlfn.XLOOKUP(M25,MA!C:C,MA!D:D,"") | T25: =_xlfn.XLOOKUP(M25,MA!C:C,MA!K:K,"") | U25: =_xlfn.XLOOKUP(M25,MA!C:C,MA!L:L,"") | V25: =(T25-S25)*100/(T25-U25) -> #VALUE! | Z25: {=_xlfn.IFS(AND(O25>0,P25>=0),"Y",AND(O25<0,P25<=0),"N",AND(O25>0),"W",AND(O25=0,P25>0),"W",TRUE,"")} -> Y | AB25: =IF($AB$21>$AB$19,"Y","N") -> N | AC25: Latest TOSL (Y) or TOSD(W) (N)
F26: =IF(B26<>"",_xlfn.XLOOKUP(B26,MA!C:C,MA!VP:VP,""),"") | G26: =IF(B26<>"",_xlfn.XLOOKUP(B26,MA!C:C,MA!VQ:VQ,""),"") | K26: German DAX Composite | L26: =_xlfn.XLOOKUP(M26,MA!C:C,MA!H:H,"") | M26: ^GDAXI | N26: GDAXI:DE | O26: =_xlfn.XLOOKUP(M26,MA!C:C,MA!VP:VP,"") | P26: =_xlfn.XLOOKUP(M26,MA!C:C,MA!VQ:VQ,"") | Q26: =_xlfn.XLOOKUP(M26,MA!C:C,MA!IG:IG,"") | R26: =_xlfn.XLOOKUP(M26,MA!C:C,MA!IS:IS,"") | S26: =_xlfn.XLOOKUP(M26,MA!C:C,MA!D:D,"") | T26: =_xlfn.XLOOKUP(M26,MA!C:C,MA!K:K,"") | U26: =_xlfn.XLOOKUP(M26,MA!C:C,MA!L:L,"") | V26: =(T26-S26)*100/(T26-U26) -> #VALUE! | Z26: {=_xlfn.IFS(AND(O26>0,P26>=0),"Y",AND(O26<0,P26<=0),"N",AND(O26>0),"W",AND(O26=0,P26>0),"W",TRUE,"")} -> Y
F27: =IF(B27<>"",_xlfn.XLOOKUP(B27,MA!C:C,MA!VP:VP,""),"") | G27: =IF(B27<>"",_xlfn.XLOOKUP(B27,MA!C:C,MA!VQ:VQ,""),"") | K27: Nikkei 225 Index | L27: =_xlfn.XLOOKUP(M27,MA!C:C,MA!H:H,"") | M27: ^N225 | N27: N225:JP | O27: =_xlfn.XLOOKUP(M27,MA!C:C,MA!VP:VP,"") | P27: =_xlfn.XLOOKUP(M27,MA!C:C,MA!VQ:VQ,"") | Q27: =_xlfn.XLOOKUP(M27,MA!C:C,MA!IG:IG,"") | R27: =_xlfn.XLOOKUP(M27,MA!C:C,MA!IS:IS,"") | S27: =_xlfn.XLOOKUP(M27,MA!C:C,MA!D:D,"") | T27: =_xlfn.XLOOKUP(M27,MA!C:C,MA!K:K,"") | U27: =_xlfn.XLOOKUP(M27,MA!C:C,MA!L:L,"") | V27: =(T27-S27)*100/(T27-U27) -> #VALUE! | Z27: {=_xlfn.IFS(AND(O27>0,P27>=0),"Y",AND(O27<0,P27<=0),"N",AND(O27>0),"W",AND(O27=0,P27>0),"W",TRUE,"")} -> Y | AB27: =_xlfn.XLOOKUP("Y",HQds!$D$2:$D$25,HQds!$E$2:$E$25) -> Quad 2 | AC27: Monthly Quad
F28: =IF(B28<>"",_xlfn.XLOOKUP(B28,MA!C:C,MA!VP:VP,""),"") | G28: =IF(B28<>"",_xlfn.XLOOKUP(B28,MA!C:C,MA!VQ:VQ,""),"") | K28: Sectors | O28: =_xlfn.XLOOKUP(M28,MA!C:C,MA!VP:VP,"") -> 0 | P28: =_xlfn.XLOOKUP(M28,MA!C:C,MA!VQ:VQ,"") -> 0 | Q28: =_xlfn.XLOOKUP(M28,MA!C:C,MA!IG:IG,"") -> 0 | R28: =_xlfn.XLOOKUP(M28,MA!C:C,MA!IS:IS,"") -> 0 | AB28: =_xlfn.XLOOKUP("Y",HQds!$L$2:$L$25,HQds!$M$2:$M$25) -> Quad 3 | AC28: Quarterly Quad
F29: =IF(B29<>"",_xlfn.XLOOKUP(B29,MA!C:C,MA!VP:VP,""),"") | G29: =IF(B29<>"",_xlfn.XLOOKUP(B29,MA!C:C,MA!VQ:VQ,""),"") | K29: Communication Services | L29: =_xlfn.XLOOKUP(M29,MA!C:C,MA!H:H,"") | M29: XLC | N29: XLC | O29: =_xlfn.XLOOKUP(M29,MA!C:C,MA!VP:VP,"") | P29: =_xlfn.XLOOKUP(M29,MA!C:C,MA!VQ:VQ,"") | Q29: =_xlfn.XLOOKUP(M29,MA!C:C,MA!IG:IG,"") | R29: =_xlfn.XLOOKUP(M29,MA!C:C,MA!IS:IS,"") | S29: =_xlfn.XLOOKUP(M29,MA!C:C,MA!D:D,"") | T29: =_xlfn.XLOOKUP(M29,MA!C:C,MA!K:K,"") | U29: =_xlfn.XLOOKUP(M29,MA!C:C,MA!L:L,"") | V29: =(T29-S29)*100/(T29-U29) -> #VALUE! | Z29: {=_xlfn.IFS(SUM(O29:R29)=0,"",AND(O29:R29>=0),"Y",AND(O29:R29<=0),"N",TRUE,"W")}
F30: =IF(B30<>"",_xlfn.XLOOKUP(B30,MA!C:C,MA!VP:VP,""),"") | G30: =IF(B30<>"",_xlfn.XLOOKUP(B30,MA!C:C,MA!VQ:VQ,""),"") | K30: Consumer Discretionary | L30: =_xlfn.XLOOKUP(M30,MA!C:C,MA!H:H,"") | M30: XLY | N30: XLY | O30: =_xlfn.XLOOKUP(M30,MA!C:C,MA!VP:VP,"") | P30: =_xlfn.XLOOKUP(M30,MA!C:C,MA!VQ:VQ,"") | Q30: =_xlfn.XLOOKUP(M30,MA!C:C,MA!IG:IG,"") | R30: =_xlfn.XLOOKUP(M30,MA!C:C,MA!IS:IS,"") | S30: =_xlfn.XLOOKUP(M30,MA!C:C,MA!D:D,"") | T30: =_xlfn.XLOOKUP(M30,MA!C:C,MA!K:K,"") | U30: =_xlfn.XLOOKUP(M30,MA!C:C,MA!L:L,"") | V30: =(T30-S30)*100/(T30-U30) -> #VALUE! | Z30: {=_xlfn.IFS(SUM(O30:R30)=0,"",AND(O30:R30>=0),"Y",AND(O30:R30<=0),"N",TRUE,"W")} | AB30: {=REPLACE(LEFT(CELL("filename",A1),FIND("]",CELL("filename",A1))-1),1,FIND("[",CELL("filename",A1)),"")} -> Tickers 2026-04-30.xlsx | AC30: Filename
F31: =IF(B31<>"",_xlfn.XLOOKUP(B31,MA!C:C,MA!VP:VP,""),"") | G31: =IF(B31<>"",_xlfn.XLOOKUP(B31,MA!C:C,MA!VQ:VQ,""),"") | K31: Consumer Staples | L31: =_xlfn.XLOOKUP(M31,MA!C:C,MA!H:H,"") | M31: XLP | N31: XLP | O31: =_xlfn.XLOOKUP(M31,MA!C:C,MA!VP:VP,"") | P31: =_xlfn.XLOOKUP(M31,MA!C:C,MA!VQ:VQ,"") | Q31: =_xlfn.XLOOKUP(M31,MA!C:C,MA!IG:IG,"") | R31: =_xlfn.XLOOKUP(M31,MA!C:C,MA!IS:IS,"") | S31: =_xlfn.XLOOKUP(M31,MA!C:C,MA!D:D,"") | T31: =_xlfn.XLOOKUP(M31,MA!C:C,MA!K:K,"") | U31: =_xlfn.XLOOKUP(M31,MA!C:C,MA!L:L,"") | V31: =(T31-S31)*100/(T31-U31) -> #VALUE! | Z31: {=_xlfn.IFS(SUM(O31:R31)=0,"",AND(O31:R31>=0),"Y",AND(O31:R31<=0),"N",TRUE,"W")} | AB31: =DATEVALUE(MID(AB30,FIND(" ",AB30)+1,10)) -> 46142 | AC31: Filedate
F32: =IF(B32<>"",_xlfn.XLOOKUP(B32,MA!C:C,MA!VP:VP,""),"") | G32: =IF(B32<>"",_xlfn.XLOOKUP(B32,MA!C:C,MA!VQ:VQ,""),"") | K32: Energy | L32: =_xlfn.XLOOKUP(M32,MA!C:C,MA!H:H,"") | M32: XLE | N32: XLE | O32: =_xlfn.XLOOKUP(M32,MA!C:C,MA!VP:VP,"") | P32: =_xlfn.XLOOKUP(M32,MA!C:C,MA!VQ:VQ,"") | Q32: =_xlfn.XLOOKUP(M32,MA!C:C,MA!IG:IG,"") | R32: =_xlfn.XLOOKUP(M32,MA!C:C,MA!IS:IS,"") | S32: =_xlfn.XLOOKUP(M32,MA!C:C,MA!D:D,"") | T32: =_xlfn.XLOOKUP(M32,MA!C:C,MA!K:K,"") | U32: =_xlfn.XLOOKUP(M32,MA!C:C,MA!L:L,"") | V32: =(T32-S32)*100/(T32-U32) -> #VALUE! | Z32: {=_xlfn.IFS(SUM(O32:R32)=0,"",AND(O32:R32>=0),"Y",AND(O32:R32<=0),"N",TRUE,"W")}
F33: =IF(B33<>"",_xlfn.XLOOKUP(B33,MA!C:C,MA!VP:VP,""),"") | G33: =IF(B33<>"",_xlfn.XLOOKUP(B33,MA!C:C,MA!VQ:VQ,""),"") | K33: Financials | L33: =_xlfn.XLOOKUP(M33,MA!C:C,MA!H:H,"") | M33: XLF | N33: XLF | O33: =_xlfn.XLOOKUP(M33,MA!C:C,MA!VP:VP,"") | P33: =_xlfn.XLOOKUP(M33,MA!C:C,MA!VQ:VQ,"") | Q33: =_xlfn.XLOOKUP(M33,MA!C:C,MA!IG:IG,"") | R33: =_xlfn.XLOOKUP(M33,MA!C:C,MA!IS:IS,"") | S33: =_xlfn.XLOOKUP(M33,MA!C:C,MA!D:D,"") | T33: =_xlfn.XLOOKUP(M33,MA!C:C,MA!K:K,"") | U33: =_xlfn.XLOOKUP(M33,MA!C:C,MA!L:L,"") | V33: =(T33-S33)*100/(T33-U33) -> #VALUE! | Z33: {=_xlfn.IFS(SUM(O33:R33)=0,"",AND(O33:R33>=0),"Y",AND(O33:R33<=0),"N",TRUE,"W")} | AB33: 2.59 | AC33: Dec CPI
F34: =IF(B34<>"",_xlfn.XLOOKUP(B34,MA!C:C,MA!VP:VP,""),"") | G34: =IF(B34<>"",_xlfn.XLOOKUP(B34,MA!C:C,MA!VQ:VQ,""),"") | K34: Health Care | L34: =_xlfn.XLOOKUP(M34,MA!C:C,MA!H:H,"") | M34: XLV | N34: XLV | O34: =_xlfn.XLOOKUP(M34,MA!C:C,MA!VP:VP,"") | P34: =_xlfn.XLOOKUP(M34,MA!C:C,MA!VQ:VQ,"") | Q34: =_xlfn.XLOOKUP(M34,MA!C:C,MA!IG:IG,"") | R34: =_xlfn.XLOOKUP(M34,MA!C:C,MA!IS:IS,"") | S34: =_xlfn.XLOOKUP(M34,MA!C:C,MA!D:D,"") | T34: =_xlfn.XLOOKUP(M34,MA!C:C,MA!K:K,"") | U34: =_xlfn.XLOOKUP(M34,MA!C:C,MA!L:L,"") | V34: =(T34-S34)*100/(T34-U34) -> #VALUE! | Z34: {=_xlfn.IFS(SUM(O34:R34)=0,"",AND(O34:R34>=0),"Y",AND(O34:R34<=0),"N",TRUE,"W")}
F35: =IF(B35<>"",_xlfn.XLOOKUP(B35,MA!C:C,MA!VP:VP,""),"") | G35: =IF(B35<>"",_xlfn.XLOOKUP(B35,MA!C:C,MA!VQ:VQ,""),"") | K35: Industrials | L35: =_xlfn.XLOOKUP(M35,MA!C:C,MA!H:H,"") | M35: XLI | N35: XLI | O35: =_xlfn.XLOOKUP(M35,MA!C:C,MA!VP:VP,"") | P35: =_xlfn.XLOOKUP(M35,MA!C:C,MA!VQ:VQ,"") | Q35: =_xlfn.XLOOKUP(M35,MA!C:C,MA!IG:IG,"") | R35: =_xlfn.XLOOKUP(M35,MA!C:C,MA!IS:IS,"") | S35: =_xlfn.XLOOKUP(M35,MA!C:C,MA!D:D,"") | T35: =_xlfn.XLOOKUP(M35,MA!C:C,MA!K:K,"") | U35: =_xlfn.XLOOKUP(M35,MA!C:C,MA!L:L,"") | V35: =(T35-S35)*100/(T35-U35) -> #VALUE! | Z35: {=_xlfn.IFS(SUM(O35:R35)=0,"",AND(O35:R35>=0),"Y",AND(O35:R35<=0),"N",TRUE,"W")}
F36: =IF(B36<>"",_xlfn.XLOOKUP(B36,MA!C:C,MA!VP:VP,""),"") | G36: =IF(B36<>"",_xlfn.XLOOKUP(B36,MA!C:C,MA!VQ:VQ,""),"") | K36: Information Technology | L36: =_xlfn.XLOOKUP(M36,MA!C:C,MA!H:H,"") | M36: XLK | N36: XLK | O36: =_xlfn.XLOOKUP(M36,MA!C:C,MA!VP:VP,"") | P36: =_xlfn.XLOOKUP(M36,MA!C:C,MA!VQ:VQ,"") | Q36: =_xlfn.XLOOKUP(M36,MA!C:C,MA!IG:IG,"") | R36: =_xlfn.XLOOKUP(M36,MA!C:C,MA!IS:IS,"") | S36: =_xlfn.XLOOKUP(M36,MA!C:C,MA!D:D,"") | T36: =_xlfn.XLOOKUP(M36,MA!C:C,MA!K:K,"") | U36: =_xlfn.XLOOKUP(M36,MA!C:C,MA!L:L,"") | V36: =(T36-S36)*100/(T36-U36) -> #VALUE! | Z36: {=_xlfn.IFS(SUM(O36:R36)=0,"",AND(O36:R36>=0),"Y",AND(O36:R36<=0),"N",TRUE,"W")}
F37: =IF(B37<>"",_xlfn.XLOOKUP(B37,MA!C:C,MA!VP:VP,""),"") | G37: =IF(B37<>"",_xlfn.XLOOKUP(B37,MA!C:C,MA!VQ:VQ,""),"") | K37: Materials | L37: =_xlfn.XLOOKUP(M37,MA!C:C,MA!H:H,"") | M37: XLB | N37: XLB | O37: =_xlfn.XLOOKUP(M37,MA!C:C,MA!VP:VP,"") | P37: =_xlfn.XLOOKUP(M37,MA!C:C,MA!VQ:VQ,"") | Q37: =_xlfn.XLOOKUP(M37,MA!C:C,MA!IG:IG,"") | R37: =_xlfn.XLOOKUP(M37,MA!C:C,MA!IS:IS,"") | S37: =_xlfn.XLOOKUP(M37,MA!C:C,MA!D:D,"") | T37: =_xlfn.XLOOKUP(M37,MA!C:C,MA!K:K,"") | U37: =_xlfn.XLOOKUP(M37,MA!C:C,MA!L:L,"") | V37: =(T37-S37)*100/(T37-U37) -> #VALUE! | Z37: {=_xlfn.IFS(SUM(O37:R37)=0,"",AND(O37:R37>=0),"Y",AND(O37:R37<=0),"N",TRUE,"W")}
F38: =IF(B38<>"",_xlfn.XLOOKUP(B38,MA!C:C,MA!VP:VP,""),"") | G38: =IF(B38<>"",_xlfn.XLOOKUP(B38,MA!C:C,MA!VQ:VQ,""),"") | K38: Real Estate | L38: =_xlfn.XLOOKUP(M38,MA!C:C,MA!H:H,"") | M38: XLRE | N38: XLRE | O38: =_xlfn.XLOOKUP(M38,MA!C:C,MA!VP:VP,"") | P38: =_xlfn.XLOOKUP(M38,MA!C:C,MA!VQ:VQ,"") | Q38: =_xlfn.XLOOKUP(M38,MA!C:C,MA!IG:IG,"") | R38: =_xlfn.XLOOKUP(M38,MA!C:C,MA!IS:IS,"") | S38: =_xlfn.XLOOKUP(M38,MA!C:C,MA!D:D,"") | T38: =_xlfn.XLOOKUP(M38,MA!C:C,MA!K:K,"") | U38: =_xlfn.XLOOKUP(M38,MA!C:C,MA!L:L,"") | V38: =(T38-S38)*100/(T38-U38) -> #VALUE! | Z38: {=_xlfn.IFS(SUM(O38:R38)=0,"",AND(O38:R38>=0),"Y",AND(O38:R38<=0),"N",TRUE,"W")}
F39: =IF(B39<>"",_xlfn.XLOOKUP(B39,MA!C:C,MA!VP:VP,""),"") | G39: =IF(B39<>"",_xlfn.XLOOKUP(B39,MA!C:C,MA!VQ:VQ,""),"") | K39: Utilities | L39: =_xlfn.XLOOKUP(M39,MA!C:C,MA!H:H,"") | M39: XLU | N39: XLU | O39: =_xlfn.XLOOKUP(M39,MA!C:C,MA!VP:VP,"") | P39: =_xlfn.XLOOKUP(M39,MA!C:C,MA!VQ:VQ,"") | Q39: =_xlfn.XLOOKUP(M39,MA!C:C,MA!IG:IG,"") | R39: =_xlfn.XLOOKUP(M39,MA!C:C,MA!IS:IS,"") | S39: =_xlfn.XLOOKUP(M39,MA!C:C,MA!D:D,"") | T39: =_xlfn.XLOOKUP(M39,MA!C:C,MA!K:K,"") | U39: =_xlfn.XLOOKUP(M39,MA!C:C,MA!L:L,"") | V39: =(T39-S39)*100/(T39-U39) -> #VALUE! | Z39: {=_xlfn.IFS(SUM(O39:R39)=0,"",AND(O39:R39>=0),"Y",AND(O39:R39<=0),"N",TRUE,"W")}
F40: =IF(B40<>"",_xlfn.XLOOKUP(B40,MA!C:C,MA!VP:VP,""),"") | G40: =IF(B40<>"",_xlfn.XLOOKUP(B40,MA!C:C,MA!VQ:VQ,""),"") | K40: Commodities | O40: =_xlfn.XLOOKUP(M40,MA!C:C,MA!VP:VP,"") -> 0 | P40: =_xlfn.XLOOKUP(M40,MA!C:C,MA!VQ:VQ,"") -> 0 | Q40: =_xlfn.XLOOKUP(M40,MA!C:C,MA!IG:IG,"") -> 0 | R40: =_xlfn.XLOOKUP(M40,MA!C:C,MA!IS:IS,"") -> 0
F41: =IF(B41<>"",_xlfn.XLOOKUP(B41,MA!C:C,MA!VP:VP,""),"") | G41: =IF(B41<>"",_xlfn.XLOOKUP(B41,MA!C:C,MA!VQ:VQ,""),"") | K41: Light Crude Oil Continuous Contract | L41: =_xlfn.XLOOKUP(M41,MA!C:C,MA!H:H,"") | M41: CL=F | N41: /CL | O41: =_xlfn.XLOOKUP(M41,MA!C:C,MA!VP:VP,"") | P41: =_xlfn.XLOOKUP(M41,MA!C:C,MA!VQ:VQ,"") | Q41: =_xlfn.XLOOKUP(M41,MA!C:C,MA!IG:IG,"") | R41: =_xlfn.XLOOKUP(M41,MA!C:C,MA!IS:IS,"") | S41: =_xlfn.XLOOKUP(M41,MA!C:C,MA!D:D,"") | T41: =_xlfn.XLOOKUP(M41,MA!C:C,MA!K:K,"") | U41: =_xlfn.XLOOKUP(M41,MA!C:C,MA!L:L,"") | V41: =(T41-S41)*100/(T41-U41) -> #VALUE! | Z41: {=_xlfn.IFS(SUM(O41:R41)=0,"",AND(O41:R41>=0),"Y",AND(O41:R41<=0),"N",TRUE,"W")}
F42: =IF(B42<>"",_xlfn.XLOOKUP(B42,MA!C:C,MA!VP:VP,""),"") | G42: =IF(B42<>"",_xlfn.XLOOKUP(B42,MA!C:C,MA!VQ:VQ,""),"") | K42: Brent Crude Oil Continuous Contract | L42: =_xlfn.XLOOKUP(M42,MA!C:C,MA!H:H,"") | M42: BZ=F | N42: /BZ | O42: =_xlfn.XLOOKUP(M42,MA!C:C,MA!VP:VP,"") | P42: =_xlfn.XLOOKUP(M42,MA!C:C,MA!VQ:VQ,"") | Q42: =_xlfn.XLOOKUP(M42,MA!C:C,MA!IG:IG,"") | R42: =_xlfn.XLOOKUP(M42,MA!C:C,MA!IS:IS,"") | S42: =_xlfn.XLOOKUP(M42,MA!C:C,MA!D:D,"") | T42: =_xlfn.XLOOKUP(M42,MA!C:C,MA!K:K,"") | U42: =_xlfn.XLOOKUP(M42,MA!C:C,MA!L:L,"") | V42: =(T42-S42)*100/(T42-U42) -> #VALUE! | Z42: {=_xlfn.IFS(SUM(O42:R42)=0,"",AND(O42:R42>=0),"Y",AND(O42:R42<=0),"N",TRUE,"W")}
F43: =IF(B43<>"",_xlfn.XLOOKUP(B43,MA!C:C,MA!VP:VP,""),"") | G43: =IF(B43<>"",_xlfn.XLOOKUP(B43,MA!C:C,MA!VQ:VQ,""),"") | K43: Natural Gas Continuous Contract | L43: =_xlfn.XLOOKUP(M43,MA!C:C,MA!H:H,"") | M43: NG=F | N43: /NG | O43: =_xlfn.XLOOKUP(M43,MA!C:C,MA!VP:VP,"") | P43: =_xlfn.XLOOKUP(M43,MA!C:C,MA!VQ:VQ,"") | Q43: =_xlfn.XLOOKUP(M43,MA!C:C,MA!IG:IG,"") | R43: =_xlfn.XLOOKUP(M43,MA!C:C,MA!IS:IS,"") | S43: =_xlfn.XLOOKUP(M43,MA!C:C,MA!D:D,"") | T43: =_xlfn.XLOOKUP(M43,MA!C:C,MA!K:K,"") | U43: =_xlfn.XLOOKUP(M43,MA!C:C,MA!L:L,"") | V43: =(T43-S43)*100/(T43-U43) -> #VALUE! | Z43: {=_xlfn.IFS(SUM(O43:R43)=0,"",AND(O43:R43>=0),"Y",AND(O43:R43<=0),"N",TRUE,"W")}
F44: =IF(B44<>"",_xlfn.XLOOKUP(B44,MA!C:C,MA!VP:VP,""),"") | G44: =IF(B44<>"",_xlfn.XLOOKUP(B44,MA!C:C,MA!VQ:VQ,""),"") | K44: Gold Spot Price | L44: =_xlfn.XLOOKUP(M44,MA!C:C,MA!H:H,"") | M44: GC=F | N44: /GC | O44: =_xlfn.XLOOKUP(M44,MA!C:C,MA!VP:VP,"") | P44: =_xlfn.XLOOKUP(M44,MA!C:C,MA!VQ:VQ,"") | Q44: =_xlfn.XLOOKUP(M44,MA!C:C,MA!IG:IG,"") | R44: =_xlfn.XLOOKUP(M44,MA!C:C,MA!IS:IS,"") | S44: =_xlfn.XLOOKUP(M44,MA!C:C,MA!D:D,"") | T44: =_xlfn.XLOOKUP(M44,MA!C:C,MA!K:K,"") | U44: =_xlfn.XLOOKUP(M44,MA!C:C,MA!L:L,"") | V44: =(T44-S44)*100/(T44-U44) -> #VALUE! | Z44: {=_xlfn.IFS(SUM(O44:R44)=0,"",AND(O44:R44>=0),"Y",AND(O44:R44<=0),"N",TRUE,"W")}
F45: =IF(B45<>"",_xlfn.XLOOKUP(B45,MA!C:C,MA!VP:VP,""),"") | G45: =IF(B45<>"",_xlfn.XLOOKUP(B45,MA!C:C,MA!VQ:VQ,""),"") | K45: Copper Continuous Contract | L45: =_xlfn.XLOOKUP(M45,MA!C:C,MA!H:H,"") | M45: HG=F | N45: /HG | O45: =_xlfn.XLOOKUP(M45,MA!C:C,MA!VP:VP,"") | P45: =_xlfn.XLOOKUP(M45,MA!C:C,MA!VQ:VQ,"") | Q45: =_xlfn.XLOOKUP(M45,MA!C:C,MA!IG:IG,"") | R45: =_xlfn.XLOOKUP(M45,MA!C:C,MA!IS:IS,"") | S45: =_xlfn.XLOOKUP(M45,MA!C:C,MA!D:D,"") | T45: =_xlfn.XLOOKUP(M45,MA!C:C,MA!K:K,"") | U45: =_xlfn.XLOOKUP(M45,MA!C:C,MA!L:L,"") | V45: =(T45-S45)*100/(T45-U45) -> #VALUE! | Z45: {=_xlfn.IFS(SUM(O45:R45)=0,"",AND(O45:R45>=0),"Y",AND(O45:R45<=0),"N",TRUE,"W")}
F46: =IF(B46<>"",_xlfn.XLOOKUP(B46,MA!C:C,MA!VP:VP,""),"") | G46: =IF(B46<>"",_xlfn.XLOOKUP(B46,MA!C:C,MA!VQ:VQ,""),"") | K46: Silver Spot Price | L46: =_xlfn.XLOOKUP(M46,MA!C:C,MA!H:H,"") | M46: SI=F | N46: /SI | O46: =_xlfn.XLOOKUP(M46,MA!C:C,MA!VP:VP,"") | P46: =_xlfn.XLOOKUP(M46,MA!C:C,MA!VQ:VQ,"") | Q46: =_xlfn.XLOOKUP(M46,MA!C:C,MA!IG:IG,"") | R46: =_xlfn.XLOOKUP(M46,MA!C:C,MA!IS:IS,"") | S46: =_xlfn.XLOOKUP(M46,MA!C:C,MA!D:D,"") | T46: =_xlfn.XLOOKUP(M46,MA!C:C,MA!K:K,"") | U46: =_xlfn.XLOOKUP(M46,MA!C:C,MA!L:L,"") | V46: =(T46-S46)*100/(T46-U46) -> #VALUE! | Z46: {=_xlfn.IFS(SUM(O46:R46)=0,"",AND(O46:R46>=0),"Y",AND(O46:R46<=0),"N",TRUE,"W")}
F47: =IF(B47<>"",_xlfn.XLOOKUP(B47,MA!C:C,MA!VP:VP,""),"") | G47: =IF(B47<>"",_xlfn.XLOOKUP(B47,MA!C:C,MA!VQ:VQ,""),"") | K47: abrdn Physical Platinum Shares ETF | L47: =_xlfn.XLOOKUP(M47,MA!C:C,MA!H:H,"") | M47: PPLT | N47: PPLT | O47: =_xlfn.XLOOKUP(M47,MA!C:C,MA!VP:VP,"") | P47: =_xlfn.XLOOKUP(M47,MA!C:C,MA!VQ:VQ,"") | Q47: =_xlfn.XLOOKUP(M47,MA!C:C,MA!IG:IG,"") | R47: =_xlfn.XLOOKUP(M47,MA!C:C,MA!IS:IS,"") | S47: =_xlfn.XLOOKUP(M47,MA!C:C,MA!D:D,"") | T47: =_xlfn.XLOOKUP(M47,MA!C:C,MA!K:K,"") | U47: =_xlfn.XLOOKUP(M47,MA!C:C,MA!L:L,"") | V47: =(T47-S47)*100/(T47-U47) -> #VALUE! | Z47: {=_xlfn.IFS(SUM(O47:R47)=0,"",AND(O47:R47>=0),"Y",AND(O47:R47<=0),"N",TRUE,"W")}
F48: =IF(B48<>"",_xlfn.XLOOKUP(B48,MA!C:C,MA!VP:VP,""),"") | G48: =IF(B48<>"",_xlfn.XLOOKUP(B48,MA!C:C,MA!VQ:VQ,""),"") | K48: Stocks | O48: =_xlfn.XLOOKUP(M48,MA!C:C,MA!VP:VP,"") -> 0 | P48: =_xlfn.XLOOKUP(M48,MA!C:C,MA!VQ:VQ,"") -> 0 | Q48: =_xlfn.XLOOKUP(M48,MA!C:C,MA!IG:IG,"") -> 0 | R48: =_xlfn.XLOOKUP(M48,MA!C:C,MA!IS:IS,"") -> 0
F49: =IF(B49<>"",_xlfn.XLOOKUP(B49,MA!C:C,MA!VP:VP,""),"") | G49: =IF(B49<>"",_xlfn.XLOOKUP(B49,MA!C:C,MA!VQ:VQ,""),"") | K49: MICROSOFT CORP. | L49: =_xlfn.XLOOKUP(M49,MA!C:C,MA!H:H,"") | M49: MSFT | N49: MSFT | O49: =_xlfn.XLOOKUP(M49,MA!C:C,MA!VP:VP,"") | P49: =_xlfn.XLOOKUP(M49,MA!C:C,MA!VQ:VQ,"") | Q49: =_xlfn.XLOOKUP(M49,MA!C:C,MA!IG:IG,"") | R49: =_xlfn.XLOOKUP(M49,MA!C:C,MA!IS:IS,"") | S49: =_xlfn.XLOOKUP(M49,MA!C:C,MA!D:D,"") | T49: =_xlfn.XLOOKUP(M49,MA!C:C,MA!K:K,"") | U49: =_xlfn.XLOOKUP(M49,MA!C:C,MA!L:L,"") | V49: =(T49-S49)*100/(T49-U49) -> #VALUE! | Z49: {=_xlfn.IFS(SUM(O49:R49)=0,"",AND(O49:R49>=0),"Y",AND(O49:R49<=0),"N",TRUE,"W")}
F50: =IF(B50<>"",_xlfn.XLOOKUP(B50,MA!C:C,MA!VP:VP,""),"") | G50: =IF(B50<>"",_xlfn.XLOOKUP(B50,MA!C:C,MA!VQ:VQ,""),"") | K50: APPLE INC. | L50: =_xlfn.XLOOKUP(M50,MA!C:C,MA!H:H,"") | M50: AAPL | N50: AAPL | O50: =_xlfn.XLOOKUP(M50,MA!C:C,MA!VP:VP,"") | P50: =_xlfn.XLOOKUP(M50,MA!C:C,MA!VQ:VQ,"") | Q50: =_xlfn.XLOOKUP(M50,MA!C:C,MA!IG:IG,"") | R50: =_xlfn.XLOOKUP(M50,MA!C:C,MA!IS:IS,"") | S50: =_xlfn.XLOOKUP(M50,MA!C:C,MA!D:D,"") | T50: =_xlfn.XLOOKUP(M50,MA!C:C,MA!K:K,"") | U50: =_xlfn.XLOOKUP(M50,MA!C:C,MA!L:L,"") | V50: =(T50-S50)*100/(T50-U50) -> #VALUE! | Z50: {=_xlfn.IFS(SUM(O50:R50)=0,"",AND(O50:R50>=0),"Y",AND(O50:R50<=0),"N",TRUE,"W")}
F51: =IF(B51<>"",_xlfn.XLOOKUP(B51,MA!C:C,MA!VP:VP,""),"") | G51: =IF(B51<>"",_xlfn.XLOOKUP(B51,MA!C:C,MA!VQ:VQ,""),"") | K51: AMAZON INC. | L51: =_xlfn.XLOOKUP(M51,MA!C:C,MA!H:H,"") | M51: AMZN | N51: AMZN | O51: =_xlfn.XLOOKUP(M51,MA!C:C,MA!VP:VP,"") | P51: =_xlfn.XLOOKUP(M51,MA!C:C,MA!VQ:VQ,"") | Q51: =_xlfn.XLOOKUP(M51,MA!C:C,MA!IG:IG,"") | R51: =_xlfn.XLOOKUP(M51,MA!C:C,MA!IS:IS,"") | S51: =_xlfn.XLOOKUP(M51,MA!C:C,MA!D:D,"") | T51: =_xlfn.XLOOKUP(M51,MA!C:C,MA!K:K,"") | U51: =_xlfn.XLOOKUP(M51,MA!C:C,MA!L:L,"") | V51: =(T51-S51)*100/(T51-U51) -> #VALUE! | Z51: {=_xlfn.IFS(SUM(O51:R51)=0,"",AND(O51:R51>=0),"Y",AND(O51:R51<=0),"N",TRUE,"W")}
F52: =IF(B52<>"",_xlfn.XLOOKUP(B52,MA!C:C,MA!VP:VP,""),"") | G52: =IF(B52<>"",_xlfn.XLOOKUP(B52,MA!C:C,MA!VQ:VQ,""),"") | K52: META PLATFORMS INC. | L52: =_xlfn.XLOOKUP(M52,MA!C:C,MA!H:H,"") | M52: META | N52: META | O52: =_xlfn.XLOOKUP(M52,MA!C:C,MA!VP:VP,"") | P52: =_xlfn.XLOOKUP(M52,MA!C:C,MA!VQ:VQ,"") | Q52: =_xlfn.XLOOKUP(M52,MA!C:C,MA!IG:IG,"") | R52: =_xlfn.XLOOKUP(M52,MA!C:C,MA!IS:IS,"") | S52: =_xlfn.XLOOKUP(M52,MA!C:C,MA!D:D,"") | T52: =_xlfn.XLOOKUP(M52,MA!C:C,MA!K:K,"") | U52: =_xlfn.XLOOKUP(M52,MA!C:C,MA!L:L,"") | V52: =(T52-S52)*100/(T52-U52) -> #VALUE! | Z52: {=_xlfn.IFS(SUM(O52:R52)=0,"",AND(O52:R52>=0),"Y",AND(O52:R52<=0),"N",TRUE,"W")}
F53: =IF(B53<>"",_xlfn.XLOOKUP(B53,MA!C:C,MA!VP:VP,""),"") | G53: =IF(B53<>"",_xlfn.XLOOKUP(B53,MA!C:C,MA!VQ:VQ,""),"") | K53: ALPHABET INC. | L53: =_xlfn.XLOOKUP(M53,MA!C:C,MA!H:H,"") | M53: GOOGL | N53: GOOGL | O53: =_xlfn.XLOOKUP(M53,MA!C:C,MA!VP:VP,"") | P53: =_xlfn.XLOOKUP(M53,MA!C:C,MA!VQ:VQ,"") | Q53: =_xlfn.XLOOKUP(M53,MA!C:C,MA!IG:IG,"") | R53: =_xlfn.XLOOKUP(M53,MA!C:C,MA!IS:IS,"") | S53: =_xlfn.XLOOKUP(M53,MA!C:C,MA!D:D,"") | T53: =_xlfn.XLOOKUP(M53,MA!C:C,MA!K:K,"") | U53: =_xlfn.XLOOKUP(M53,MA!C:C,MA!L:L,"") | V53: =(T53-S53)*100/(T53-U53) -> #VALUE! | Z53: {=_xlfn.IFS(SUM(O53:R53)=0,"",AND(O53:R53>=0),"Y",AND(O53:R53<=0),"N",TRUE,"W")}
F54: =IF(B54<>"",_xlfn.XLOOKUP(B54,MA!C:C,MA!VP:VP,""),"") | G54: =IF(B54<>"",_xlfn.XLOOKUP(B54,MA!C:C,MA!VQ:VQ,""),"") | K54: NETFLIX INC. | L54: =_xlfn.XLOOKUP(M54,MA!C:C,MA!H:H,"") | M54: NFLX | N54: NFLX | O54: =_xlfn.XLOOKUP(M54,MA!C:C,MA!VP:VP,"") | P54: =_xlfn.XLOOKUP(M54,MA!C:C,MA!VQ:VQ,"") | Q54: =_xlfn.XLOOKUP(M54,MA!C:C,MA!IG:IG,"") | R54: =_xlfn.XLOOKUP(M54,MA!C:C,MA!IS:IS,"") | S54: =_xlfn.XLOOKUP(M54,MA!C:C,MA!D:D,"") | T54: =_xlfn.XLOOKUP(M54,MA!C:C,MA!K:K,"") | U54: =_xlfn.XLOOKUP(M54,MA!C:C,MA!L:L,"") | V54: =(T54-S54)*100/(T54-U54) -> #VALUE! | Z54: {=_xlfn.IFS(SUM(O54:R54)=0,"",AND(O54:R54>=0),"Y",AND(O54:R54<=0),"N",TRUE,"W")}
F55: =IF(B55<>"",_xlfn.XLOOKUP(B55,MA!C:C,MA!VP:VP,""),"") | G55: =IF(B55<>"",_xlfn.XLOOKUP(B55,MA!C:C,MA!VQ:VQ,""),"") | K55: TESLA INC. | L55: =_xlfn.XLOOKUP(M55,MA!C:C,MA!H:H,"") | M55: TSLA | N55: TSLA | O55: =_xlfn.XLOOKUP(M55,MA!C:C,MA!VP:VP,"") | P55: =_xlfn.XLOOKUP(M55,MA!C:C,MA!VQ:VQ,"") | Q55: =_xlfn.XLOOKUP(M55,MA!C:C,MA!IG:IG,"") | R55: =_xlfn.XLOOKUP(M55,MA!C:C,MA!IS:IS,"") | S55: =_xlfn.XLOOKUP(M55,MA!C:C,MA!D:D,"") | T55: =_xlfn.XLOOKUP(M55,MA!C:C,MA!K:K,"") | U55: =_xlfn.XLOOKUP(M55,MA!C:C,MA!L:L,"") | V55: =(T55-S55)*100/(T55-U55) -> #VALUE! | Z55: {=_xlfn.IFS(SUM(O55:R55)=0,"",AND(O55:R55>=0),"Y",AND(O55:R55<=0),"N",TRUE,"W")}
F56: =IF(B56<>"",_xlfn.XLOOKUP(B56,MA!C:C,MA!VP:VP,""),"") | G56: =IF(B56<>"",_xlfn.XLOOKUP(B56,MA!C:C,MA!VQ:VQ,""),"") | K56: NVIDIA CORPORATION | L56: =_xlfn.XLOOKUP(M56,MA!C:C,MA!H:H,"") | M56: NVDA | N56: NVDA | O56: =_xlfn.XLOOKUP(M56,MA!C:C,MA!VP:VP,"") | P56: =_xlfn.XLOOKUP(M56,MA!C:C,MA!VQ:VQ,"") | Q56: =_xlfn.XLOOKUP(M56,MA!C:C,MA!IG:IG,"") | R56: =_xlfn.XLOOKUP(M56,MA!C:C,MA!IS:IS,"") | S56: =_xlfn.XLOOKUP(M56,MA!C:C,MA!D:D,"") | T56: =_xlfn.XLOOKUP(M56,MA!C:C,MA!K:K,"") | U56: =_xlfn.XLOOKUP(M56,MA!C:C,MA!L:L,"") | V56: =(T56-S56)*100/(T56-U56) -> #VALUE! | Z56: {=_xlfn.IFS(SUM(O56:R56)=0,"",AND(O56:R56>=0),"Y",AND(O56:R56<=0),"N",TRUE,"W")}
F57: =IF(B57<>"",_xlfn.XLOOKUP(B57,MA!C:C,MA!VP:VP,""),"") | G57: =IF(B57<>"",_xlfn.XLOOKUP(B57,MA!C:C,MA!VQ:VQ,""),"") | K57: ORACLE CORPORATION | L57: =_xlfn.XLOOKUP(M57,MA!C:C,MA!H:H,"") | M57: ORCL | N57: ORCL | O57: =_xlfn.XLOOKUP(M57,MA!C:C,MA!VP:VP,"") | P57: =_xlfn.XLOOKUP(M57,MA!C:C,MA!VQ:VQ,"") | Q57: =_xlfn.XLOOKUP(M57,MA!C:C,MA!IG:IG,"") | R57: =_xlfn.XLOOKUP(M57,MA!C:C,MA!IS:IS,"") | S57: =_xlfn.XLOOKUP(M57,MA!C:C,MA!D:D,"") | T57: =_xlfn.XLOOKUP(M57,MA!C:C,MA!K:K,"") | U57: =_xlfn.XLOOKUP(M57,MA!C:C,MA!L:L,"") | V57: =(T57-S57)*100/(T57-U57) -> #VALUE! | Z57: {=_xlfn.IFS(SUM(O57:R57)=0,"",AND(O57:R57>=0),"Y",AND(O57:R57<=0),"N",TRUE,"W")}
F58: =IF(B58<>"",_xlfn.XLOOKUP(B58,MA!C:C,MA!VP:VP,""),"") | G58: =IF(B58<>"",_xlfn.XLOOKUP(B58,MA!C:C,MA!VQ:VQ,""),"") | K58: BITCOIN SPOT PRICE | L58: =_xlfn.XLOOKUP(M58,MA!C:C,MA!H:H,"") | M58: BTC-USD | N58: /BTC | O58: =_xlfn.XLOOKUP(M58,MA!C:C,MA!VP:VP,"") | P58: =_xlfn.XLOOKUP(M58,MA!C:C,MA!VQ:VQ,"") | Q58: =_xlfn.XLOOKUP(M58,MA!C:C,MA!IG:IG,"") | R58: =_xlfn.XLOOKUP(M58,MA!C:C,MA!IS:IS,"") | S58: =_xlfn.XLOOKUP(M58,MA!C:C,MA!D:D,"") | T58: =_xlfn.XLOOKUP(M58,MA!C:C,MA!K:K,"") | U58: =_xlfn.XLOOKUP(M58,MA!C:C,MA!L:L,"") | V58: =(T58-S58)*100/(T58-U58) -> #VALUE! | Z58: {=_xlfn.IFS(SUM(O58:R58)=0,"",AND(O58:R58>=0),"Y",AND(O58:R58<=0),"N",TRUE,"W")}
F59: =IF(B59<>"",_xlfn.XLOOKUP(B59,MA!C:C,MA!VP:VP,""),"") | G59: =IF(B59<>"",_xlfn.XLOOKUP(B59,MA!C:C,MA!VQ:VQ,""),"") | K59: Aerospace & Defense ETF | L59: =_xlfn.XLOOKUP(M59,MA!C:C,MA!H:H,"") | M59: ITA | N59: ITA | O59: =_xlfn.XLOOKUP(M59,MA!C:C,MA!VP:VP,"") | P59: =_xlfn.XLOOKUP(M59,MA!C:C,MA!VQ:VQ,"") | Q59: =_xlfn.XLOOKUP(M59,MA!C:C,MA!IG:IG,"") | R59: =_xlfn.XLOOKUP(M59,MA!C:C,MA!IS:IS,"") | S59: =_xlfn.XLOOKUP(M59,MA!C:C,MA!D:D,"") | T59: =_xlfn.XLOOKUP(M59,MA!C:C,MA!K:K,"") | U59: =_xlfn.XLOOKUP(M59,MA!C:C,MA!L:L,"") | V59: =(T59-S59)*100/(T59-U59) -> #VALUE! | Z59: {=_xlfn.IFS(SUM(O59:R59)=0,"",AND(O59:R59>=0),"Y",AND(O59:R59<=0),"N",TRUE,"W")}
F60: =IF(B60<>"",_xlfn.XLOOKUP(B60,MA!C:C,MA!VP:VP,""),"") | G60: =IF(B60<>"",_xlfn.XLOOKUP(B60,MA!C:C,MA!VQ:VQ,""),"") | K60: Simplify Healthcare ETF | L60: =_xlfn.XLOOKUP(M60,MA!C:C,MA!H:H,"") | M60: PINK | N60: PINK | O60: =_xlfn.XLOOKUP(M60,MA!C:C,MA!VP:VP,"") | P60: =_xlfn.XLOOKUP(M60,MA!C:C,MA!VQ:VQ,"") | Q60: =_xlfn.XLOOKUP(M60,MA!C:C,MA!IG:IG,"") | R60: =_xlfn.XLOOKUP(M60,MA!C:C,MA!IS:IS,"") | S60: =_xlfn.XLOOKUP(M60,MA!C:C,MA!D:D,"") | T60: =_xlfn.XLOOKUP(M60,MA!C:C,MA!K:K,"") | U60: =_xlfn.XLOOKUP(M60,MA!C:C,MA!L:L,"") | V60: =(T60-S60)*100/(T60-U60) -> #VALUE! | Z60: {=_xlfn.IFS(SUM(O60:R60)=0,"",AND(O60:R60>=0),"Y",AND(O60:R60<=0),"N",TRUE,"W")}
... F70: =IF(B70<>"",_xlfn.XLOOKUP(B70,MA!C:C,MA!VP:VP,""),"") | G70: =IF(B70<>"",_xlfn.XLOOKUP(B70,MA!C:C,MA!VQ:VQ,""),"") | K70: Consumer Discretionary Select Sector SPDR Fund | L70: =_xlfn.XLOOKUP(M70,MA!C:C,MA!H:H,"") | M70: XLY | N70: XLY | O70: =_xlfn.XLOOKUP(M70,MA!C:C,MA!VP:VP,"") | P70: =_xlfn.XLOOKUP(M70,MA!C:C,MA!VQ:VQ,"") | Q70: =_xlfn.XLOOKUP(M70,MA!C:C,MA!IG:IG,"") | R70: =_xlfn.XLOOKUP(M70,MA!C:C,MA!IS:IS,"") | S70: =_xlfn.XLOOKUP(M70,MA!C:C,MA!D:D,"") | T70: =_xlfn.XLOOKUP(M70,MA!C:C,MA!K:K,"") | U70: =_xlfn.XLOOKUP(M70,MA!C:C,MA!L:L,"") | V70: =(T70-S70)*100/(T70-U70) -> #VALUE! | Z70: {=_xlfn.IFS(SUM(O70:R70)=0,"",AND(O70:R70>=0),"Y",AND(O70:R70<=0),"N",TRUE,"W")}
F71: =IF(B71<>"",_xlfn.XLOOKUP(B71,MA!C:C,MA!VP:VP,""),"") | G71: =IF(B71<>"",_xlfn.XLOOKUP(B71,MA!C:C,MA!VQ:VQ,""),"")
F72: =IF(B72<>"",_xlfn.XLOOKUP(B72,MA!C:C,MA!VP:VP,""),"") | G72: =IF(B72<>"",_xlfn.XLOOKUP(B72,MA!C:C,MA!VQ:VQ,""),"")
F73: =IF(B73<>"",_xlfn.XLOOKUP(B73,MA!C:C,MA!VP:VP,""),"") | G73: =IF(B73<>"",_xlfn.XLOOKUP(B73,MA!C:C,MA!VQ:VQ,""),"")
F74: =IF(B74<>"",_xlfn.XLOOKUP(B74,MA!C:C,MA!VP:VP,""),"") | G74: =IF(B74<>"",_xlfn.XLOOKUP(B74,MA!C:C,MA!VQ:VQ,""),"")
F75: =IF(B75<>"",_xlfn.XLOOKUP(B75,MA!C:C,MA!VP:VP,""),"") | G75: =IF(B75<>"",_xlfn.XLOOKUP(B75,MA!C:C,MA!VQ:VQ,""),"")
F76: =IF(B76<>"",_xlfn.XLOOKUP(B76,MA!C:C,MA!VP:VP,""),"") | G76: =IF(B76<>"",_xlfn.XLOOKUP(B76,MA!C:C,MA!VQ:VQ,""),"")
F77: =IF(B77<>"",_xlfn.XLOOKUP(B77,MA!C:C,MA!VP:VP,""),"") | G77: =IF(B77<>"",_xlfn.XLOOKUP(B77,MA!C:C,MA!VQ:VQ,""),"")
F78: =IF(B78<>"",_xlfn.XLOOKUP(B78,MA!C:C,MA!VP:VP,""),"") | G78: =IF(B78<>"",_xlfn.XLOOKUP(B78,MA!C:C,MA!VQ:VQ,""),"")
F79: =IF(B79<>"",_xlfn.XLOOKUP(B79,MA!C:C,MA!VP:VP,""),"") | G79: =IF(B79<>"",_xlfn.XLOOKUP(B79,MA!C:C,MA!VQ:VQ,""),"")
F80: =IF(B80<>"",_xlfn.XLOOKUP(B80,MA!C:C,MA!VP:VP,""),"") | G80: =IF(B80<>"",_xlfn.XLOOKUP(B80,MA!C:C,MA!VQ:VQ,""),"")
F81: =IF(B81<>"",_xlfn.XLOOKUP(B81,MA!C:C,MA!VP:VP,""),"") | G81: =IF(B81<>"",_xlfn.XLOOKUP(B81,MA!C:C,MA!VQ:VQ,""),"")
F82: =IF(B82<>"",_xlfn.XLOOKUP(B82,MA!C:C,MA!VP:VP,""),"") | G82: =IF(B82<>"",_xlfn.XLOOKUP(B82,MA!C:C,MA!VQ:VQ,""),"")
... F262: =IF(B262<>"",_xlfn.XLOOKUP(B262,MA!C:C,MA!VP:VP,""),"") | G262: =IF(B262<>"",_xlfn.XLOOKUP(B262,MA!C:C,MA!VQ:VQ,""),"")

Sheet My

Sheet Y
A1: DateSymbol | B1: DateTime | C1: Sym | D1: DateSymbolTime | E1: Date | F1: Sequence | G1: Export Date | H1: Export Time | I1: Symbol | J1: Company Name | K1: Last Price | L1: Change | M1: Change (%) | N1: Open | O1: High | P1: Low | Q1: Short Ratio | R1: Float | S1: Shares Out
A2: =IF(I2="","",E2&I2) -> 46141ZM | B2: =E2 + TIME(LEFT(TEXT(F2,"0000"),2),RIGHT(TEXT(F2,"0000"),2),0) -> 46141.688 | C2: =IF(ISNUMBER(SEARCH("[",I2)),LEFT(I2,FIND("[",I2)-1),I2) -> ZM | D2: =IF(I2="","",B2&C2) -> 46141.6875ZM | E2: =G2 -> 46141 | F2: =H2 -> 1630 | G2: 46141 | H2: 1630 | I2: ZM | J2: Zoom Communications, Inc. | K2: 95.76 | L2: 4.62 | M2: 0.0507 | N2: 91.54 | O2: 96.51 | P2: 91.02 | Q2: 1.7 | R2: 260.232M | S2: 265.97M
A3: =IF(I3="","",E3&I3) -> 46141ZS | B3: =E3 + TIME(LEFT(TEXT(F3,"0000"),2),RIGHT(TEXT(F3,"0000"),2),0) -> 46141.688 | C3: =IF(ISNUMBER(SEARCH("[",I3)),LEFT(I3,FIND("[",I3)-1),I3) -> ZS | D3: =IF(I3="","",B3&C3) -> 46141.6875ZS | E3: =G3 -> 46141 | F3: =H3 -> 1630 | G3: 46141 | H3: 1630 | I3: ZS | J3: Zscaler, Inc. | K3: 134.73 | L3: -1.34 | M3: -0.0098 | N3: 135.12 | O3: 135.71 | P3: 131.76 | Q3: 3.53 | R3: 104.215M | S3: 160.791M

Sheet TL
A1: DateSymbol | B1: DateTime | C1: Sym | D1: DateSymbolTime | E1: Date | F1: Sequence | G1: Vlm | H1: ImpVolatility | I1: Export Date | J1: Export Time | K1: Symbol | L1: Last | M1: Net Chng | N1: %Change | O1: Open | P1: High | Q1: Low | R1: Volume | S1: RSI | T1: ImpVolatility
A2: =IF(K2="","",E2&K2) -> 46141ZM | B2: =E2 + TIME(LEFT(TEXT(F2,"0000"),2),RIGHT(TEXT(F2,"0000"),2),0) -> 46141.688 | C2: =IF(ISNUMBER(SEARCH("[",K2)),LEFT(K2,FIND("[",K2)-1),K2) -> ZM | D2: =IF(K2="","",B2&C2) -> 46141.6875ZM | E2: =I2 -> 46141 | F2: =J2 -> 1630 | G2: =IF(OR(K2="",R2="<empty>",F2<930),"",IF(F2<1600, R2*390/((INT(F2/100)*60 + MOD(F2,100)) - 570),R2)) -> 6815835 | H2: =IF(J2="","",IF(T2="NaN",0,T2)) -> 0.59 | I2: 46141 | J2: 1630 | K2: ZM | L2: 95.76 | M2: 4.62 | N2: 0.0507 | O2: 91.685 | P2: 96.51 | Q2: 91.02 | R2: 6815835 | S2: 69.17 | T2: 0.59
A3: =IF(K3="","",E3&K3) -> 46141ZS | B3: =E3 + TIME(LEFT(TEXT(F3,"0000"),2),RIGHT(TEXT(F3,"0000"),2),0) -> 46141.688 | C3: =IF(ISNUMBER(SEARCH("[",K3)),LEFT(K3,FIND("[",K3)-1),K3) -> ZS | D3: =IF(K3="","",B3&C3) -> 46141.6875ZS | E3: =I3 -> 46141 | F3: =J3 -> 1630 | G3: =IF(OR(K3="",R3="<empty>",F3<930),"",IF(F3<1600, R3*390/((INT(F3/100)*60 + MOD(F3,100)) - 570),R3)) -> 1339176 | H3: =IF(J3="","",IF(T3="NaN",0,T3)) -> 0.76 | I3: 46141 | J3: 1630 | K3: ZS | L3: 134.73 | M3: -1.34 | N3: -0.0098 | O3: 135.12 | P3: 135.715 | Q3: 131.74 | R3: 1339176 | S3: 46.06 | T3: 0.76

Sheet TD
A1: DateSymbol | B1: DateTime | C1: Sym | D1: DateSymbolTime | E1: Date1 | F1: Sequence | G1: DSKey | H1: DS Sequence | I1: BB_Bot_15d | J1: BB_Bot_7d | K1: BB_Bot_3d | L1: BB_Bot_Prev | M1: BB_Top_15d | N1: BB_Top_7d | O1: BB_Top_3d | P1: BB_Top_Prev | Q1: IVPercentile | R1: HVPercentile | S1: RangeCompression | T1: D_RSI | U1: D_RSI3 | V1: D_RSI7 | W1: D_RSIDirection | X1: D_HV | Y1: D_HV3 | Z1: D_HV7 | AA1: D_HVDirection | AB1: D_IV | AC1: D_IV3 | AD1: D_IV7 | AE1: D_IVDirection | AF1: D_IVP3 | AG1: D_IVP7 | AH1: D_IVPDirection | AI1: D_IVPMax10 | AJ1: D_IV_to_HV | AK1: D_Vlt_RuleCode | AL1: D_Vlt_Caution | AM1: Export Date | AN1: Export Time | AO1: Symbol | AP1: Last | AQ1: Net Chng | AR1: %Change | AS1: Open | AT1: High | AU1: Low | AV1: RSI | AW1: HistoricalVolatility | AX1: ImpVolatility | AY1: A_TrendValue | AZ1: A_TradeValue | BA1: A_BB_Bottom | BB1: A_BB_Top | BC1: A_BB_Streak | BD1: A_BBHighLow | BE1: A_BBHighLowDays | BF1: A_IVPercentile | BG1: A_HVPercentile | BH1: A_BB_Top_Slope | BI1: A_BB_Bot_Slope
A2: =IF(AO2="","",E2&AO2) -> 46141ZM | B2: =E2 + TIME(LEFT(TEXT(F2,"0000"),2),RIGHT(TEXT(F2,"0000"),2),0) -> 46141.688 | C2: =IF(ISNUMBER(SEARCH("[",AO2)),LEFT(AO2,FIND("[",AO2)-1),AO2) -> ZM | D2: =IF(AO2="","",B2&C2) -> 46141.6875ZM | E2: =AM2 -> 46141 | F2: =AN2 -> 1630 | G2: =H2&C2 -> 1ZM | H2: =1 -> 1 | I2: {=_xlfn.XLOOKUP((H2-15)&C2, G$1:G1, BA$1:BA1, 0, 0, -1)} -> 0 | J2: {=_xlfn.XLOOKUP((H2-7)&C2, G$1:G1, BA$1:BA1, 0, 0, -1)} -> 0 | K2: {=_xlfn.XLOOKUP((H2-3)&C2,G$1:G1,BA$1:BA1,0,0,-1)} -> 0 | L2: {=_xlfn.XLOOKUP(C2, C$1:C1, BA$1:BA1, 0, 0, -1)} -> 0 | M2: {=_xlfn.XLOOKUP((H2-15)&C2,G$1:G1,BB$1:BB1,0,0,-1)} -> 0 | N2: {=_xlfn.XLOOKUP((H2-7)&C2,G$1:G1,BB$1:BB1,0,0,-1)} -> 0 | O2: {=_xlfn.XLOOKUP((H2-3)&C2, G$1:G1, BB$1:BB1, 0, 0, -1)} -> 0 | P2: {=_xlfn.XLOOKUP(C2, C$1:C1, BB$1:BB1, 0, 0, -1)} -> 0 | Q2: =IF(AO2="","",IF(BF2="NaN",0,BF2)) -> 96.4 | R2: =IF(AO2="","",IF(BG2="NaN",0,BG2)) -> 74.1 | S2: {=(MAX(_xlfn.TAKE(_xlfn._xlws.FILTER($AT$2:$AT2, $C$2:$C2=$C2), -10)) - MIN(_xlfn.TAKE(_xlfn._xlws.FILTER($AU$2:$AU2, $C$2:$C2=$C2), -10)))/AP2} -> 0.057330827 | T2: =AV2 -> 69.17 | U2: {=AVERAGE(_xlfn.TAKE(_xlfn._xlws.FILTER(AV$2:AV2, C$2:C2=C2), -3))} -> 69.17 | V2: {=AVERAGE(_xlfn.TAKE(_xlfn._xlws.FILTER(AV$2:AV2, C$2:C2=C2), -7))} -> 69.17 | W2: {=_xlfn.IFS(OR(U2=0, V2=0), 0, (U2-V2) > 1, 1, (U2-V2) < -1, -1, TRUE, 0)} -> 0 | X2: =AW2 -> 0.46 | Y2: {=AVERAGE(_xlfn.TAKE(_xlfn._xlws.FILTER(AW$2:AW2, C$2:C2=C2), -3))} -> 0.46 | Z2: {=AVERAGE(_xlfn.TAKE(_xlfn._xlws.FILTER(AW$2:AW2, C$2:C2=C2), -7))} -> 0.46 | AA2: {=_xlfn.IFS(OR(Y2=0, Z2=0), 0, (Y2-Z2)/Z2 > 0.03, 1, (Y2-Z2)/Z2 < -0.03, -1, TRUE, 0)} -> 0 | AB2: =IF(AN2="","",IF(AX2="NaN",0,AX2)) -> 0.59 | AC2: {=AVERAGE(_xlfn.TAKE(_xlfn._xlws.FILTER(AB$2:AB2, C$2:C2=C2), -3))} -> 0.59 | AD2: {=AVERAGE(_xlfn.TAKE(_xlfn._xlws.FILTER(AB$2:AB2, $C$2:$C2=$C2), -7))} -> 0.59 | AE2: {=_xlfn.IFS(OR(AC2=0, AD2=0), 0, (AC2-AD2)/AD2 > 0.03, 1, (AC2-AD2)/AD2 < -0.03, -1, TRUE, 0)} -> 0 | AF2: {=AVERAGE(_xlfn.TAKE(_xlfn._xlws.FILTER($Q$2:$Q2, $C$2:$C2=$C2), -3))} -> 96.4 | AG2: {=AVERAGE(_xlfn.TAKE(_xlfn._xlws.FILTER($Q$2:$Q2, $C$2:$C2=$C2), -7))} -> 96.4 | AH2: {=_xlfn.IFS(OR(AF2=0, AG2=0), 0, (AF2-AG2) > 1, 1, (AF2-AG2) < -1, -1, TRUE, 0)} -> 0 | AI2: {=MAX(_xlfn.TAKE(_xlfn._xlws.FILTER($Q$2:$Q2, $C$2:$C2=$C2), -10))} -> 96.4 | AJ2: =IF(X2=0,0,AB2/X2) -> 1.2826087 | AK2: {=_xlfn.IFS( OR(Q2=0,X2=0,AB2=0),"", AND(Q2>90,W2<=0,OR((X2/Z2)>1.25,(Y2/Z2)>1.1,(AC2/AD2)>1.1)),1, AND(Q2>60,AJ2>2,AE2<0),2, AND(Q2<60,AA2<0,AE2>0,W2<0),3, AND(Q2>40,(Y2/Z2)>1.25,AA2<=0),4, AND(Q2>25,AA2<0,AE2<0,W2<0),5, AND(Q2<50,AA2<0,AE2<=0,W2<=0),6, AND(Q2<10,R2<=10,AH2<=0,S2<0.03),7, AND(Q2>60,AI2>=80,(AI2-Q2)>10,W2>0,AE2<0),8, AND(Q2<25,AA2>0,AE2>0,W2>0,AH2>0),9, AND(Q2<60,W2>0,AA2>=0,AE2>=0,T2>U2,T2>V2),10, TRUE,"" )} | AL2: {=_xlfn.IFS( OR(Q2=0,X2=0,AB2=0),"", Q2 > 90, "IVPXtrm", X2 / Z2 > 1.25, "HV1Spke", Y2 / Z2 > 1.25, "HV3Spke", AB2 / AD2 > 1.25, "IV1Spke", AC2 / AD2 > 1.25, "IV3Spke", AJ2 > 2, "HiIV2HV", AND(S2 < 0.03, X2 / Z2 > 1.25), "IVExpn", TRUE,"" )} -> IVPXtrm | AM2: 46141 | AN2: 1630 | AO2: ZM | AP2: 95.76 | AQ2: 4.62 | AR2: 0.0507 | AS2: 91.685 | AT2: 96.51 | AU2: 91.02 | AV2: 69.17 | AW2: 0.46 | AX2: 0.59 | AY2: 87.19 | AZ2: 77.02 | BA2: 83.77 | BB2: 98.86 | BC2: 8213.01 | BD2: 9651.01 | BE2: 6.14 | BF2: 96.4 | BG2: 74.1 | BH2: 9.2 | BI2: 6.8
A3: =IF(AO3="","",E3&AO3) -> 46141ZS | B3: =E3 + TIME(LEFT(TEXT(F3,"0000"),2),RIGHT(TEXT(F3,"0000"),2),0) -> 46141.688 | C3: =IF(ISNUMBER(SEARCH("[",AO3)),LEFT(AO3,FIND("[",AO3)-1),AO3) -> ZS | D3: =IF(AO3="","",B3&C3) -> 46141.6875ZS | E3: =AM3 -> 46141 | F3: =AN3 -> 1630 | G3: =H3&C3 -> 1ZS | H3: =1 -> 1 | I3: {=_xlfn.XLOOKUP((H3-15)&C3, G$1:G2, BA$1:BA2, 0, 0, -1)} -> 0 | J3: {=_xlfn.XLOOKUP((H3-7)&C3, G$1:G2, BA$1:BA2, 0, 0, -1)} -> 0 | K3: {=_xlfn.XLOOKUP((H3-3)&C3,G$1:G2,BA$1:BA2,0,0,-1)} -> 0 | L3: {=_xlfn.XLOOKUP(C3, C$1:C2, BA$1:BA2, 0, 0, -1)} -> 0 | M3: {=_xlfn.XLOOKUP((H3-15)&C3,G$1:G2,BB$1:BB2,0,0,-1)} -> 0 | N3: {=_xlfn.XLOOKUP((H3-7)&C3,G$1:G2,BB$1:BB2,0,0,-1)} -> 0 | O3: {=_xlfn.XLOOKUP((H3-3)&C3, G$1:G2, BB$1:BB2, 0, 0, -1)} -> 0 | P3: {=_xlfn.XLOOKUP(C3, C$1:C2, BB$1:BB2, 0, 0, -1)} -> 0 | Q3: =IF(AO3="","",IF(BF3="NaN",0,BF3)) -> 97.3 | R3: =IF(AO3="","",IF(BG3="NaN",0,BG3)) -> 86.3 | S3: {=(MAX(_xlfn.TAKE(_xlfn._xlws.FILTER($AT$2:$AT3, $C$2:$C3=$C3), -10)) - MIN(_xlfn.TAKE(_xlfn._xlws.FILTER($AU$2:$AU3, $C$2:$C3=$C3), -10)))/AP3} -> 0.029503451 | T3: =AV3 -> 46.06 | U3: {=AVERAGE(_xlfn.TAKE(_xlfn._xlws.FILTER(AV$2:AV3, C$2:C3=C3), -3))} -> 46.06 | V3: {=AVERAGE(_xlfn.TAKE(_xlfn._xlws.FILTER(AV$2:AV3, C$2:C3=C3), -7))} -> 46.06 | W3: {=_xlfn.IFS(OR(U3=0, V3=0), 0, (U3-V3) > 1, 1, (U3-V3) < -1, -1, TRUE, 0)} -> 0 | X3: =AW3 -> 0.65 | Y3: {=AVERAGE(_xlfn.TAKE(_xlfn._xlws.FILTER(AW$2:AW3, C$2:C3=C3), -3))} -> 0.65 | Z3: {=AVERAGE(_xlfn.TAKE(_xlfn._xlws.FILTER(AW$2:AW3, C$2:C3=C3), -7))} -> 0.65 | AA3: {=_xlfn.IFS(OR(Y3=0, Z3=0), 0, (Y3-Z3)/Z3 > 0.03, 1, (Y3-Z3)/Z3 < -0.03, -1, TRUE, 0)} -> 0 | AB3: =IF(AN3="","",IF(AX3="NaN",0,AX3)) -> 0.76 | AC3: {=AVERAGE(_xlfn.TAKE(_xlfn._xlws.FILTER(AB$2:AB3, C$2:C3=C3), -3))} -> 0.76 | AD3: {=AVERAGE(_xlfn.TAKE(_xlfn._xlws.FILTER(AB$2:AB3, $C$2:$C3=$C3), -7))} -> 0.76 | AE3: {=_xlfn.IFS(OR(AC3=0, AD3=0), 0, (AC3-AD3)/AD3 > 0.03, 1, (AC3-AD3)/AD3 < -0.03, -1, TRUE, 0)} -> 0 | AF3: {=AVERAGE(_xlfn.TAKE(_xlfn._xlws.FILTER($Q$2:$Q3, $C$2:$C3=$C3), -3))} -> 97.3 | AG3: {=AVERAGE(_xlfn.TAKE(_xlfn._xlws.FILTER($Q$2:$Q3, $C$2:$C3=$C3), -7))} -> 97.3 | AH3: {=_xlfn.IFS(OR(AF3=0, AG3=0), 0, (AF3-AG3) > 1, 1, (AF3-AG3) < -1, -1, TRUE, 0)} -> 0 | AI3: {=MAX(_xlfn.TAKE(_xlfn._xlws.FILTER($Q$2:$Q3, $C$2:$C3=$C3), -10))} -> 97.3 | AJ3: =IF(X3=0,0,AB3/X3) -> 1.1692308 | AK3: {=_xlfn.IFS( OR(Q3=0,X3=0,AB3=0),"", AND(Q3>90,W3<=0,OR((X3/Z3)>1.25,(Y3/Z3)>1.1,(AC3/AD3)>1.1)),1, AND(Q3>60,AJ3>2,AE3<0),2, AND(Q3<60,AA3<0,AE3>0,W3<0),3, AND(Q3>40,(Y3/Z3)>1.25,AA3<=0),4, AND(Q3>25,AA3<0,AE3<0,W3<0),5, AND(Q3<50,AA3<0,AE3<=0,W3<=0),6, AND(Q3<10,R3<=10,AH3<=0,S3<0.03),7, AND(Q3>60,AI3>=80,(AI3-Q3)>10,W3>0,AE3<0),8, AND(Q3<25,AA3>0,AE3>0,W3>0,AH3>0),9, AND(Q3<60,W3>0,AA3>=0,AE3>=0,T3>U3,T3>V3),10, TRUE,"" )} | AL3: {=_xlfn.IFS( OR(Q3=0,X3=0,AB3=0),"", Q3 > 90, "IVPXtrm", X3 / Z3 > 1.25, "HV1Spke", Y3 / Z3 > 1.25, "HV3Spke", AB3 / AD3 > 1.25, "IV1Spke", AC3 / AD3 > 1.25, "IV3Spke", AJ3 > 2, "HiIV2HV", AND(S3 < 0.03, X3 / Z3 > 1.25), "IVExpn", TRUE,"" )} -> IVPXtrm | AM3: 46141 | AN3: 1630 | AO3: ZS | AP3: 134.73 | AQ3: -1.34 | AR3: -0.0098 | AS3: 135.12 | AT3: 135.715 | AU3: 131.74 | AV3: 46.06 | AW3: 0.65 | AX3: 0.76 | AY3: 162.94 | AZ3: 114.63 | BA3: 120.88 | BB3: 148.55 | BC3: 3211.06 | BD3: 14472.07 | BE3: 7.13 | BF3: 97.3 | BG3: 86.3 | BH3: -0.1 | BI3: 0

Sheet TW
A1: DateSymbol | B1: DateTime | C1: Sym | D1: DateSymbolTime | E1: Date1 | F1: Sequence | G1: FCF | H1: 20 DMA | I1: 50 DMA | J1: 200 DMA | K1: W_Vlm | L1: Avg Vlm (10day) | M1: Avg Vlm (3m) | N1: VlmRateOfChange | O1: W_Vlm_Expn_Ratio | P1: W_Prior-DayVlmExpnRatio | Q1: %Change | R1: Last Price | S1: W_Price_WkAgo | T1: W_%Change_Wk | U1: W_Vlm_RuleDesc | V1: A_MACD_BRR | W1: A_MACDH_D_BRR | X1: EarningsDays | Y1: Export Date | Z1: Export Time | AA1: Symbol | AB1: Last | AC1: %Change | AD1: Sector | AE1: Beta | AF1: StandardDeviation | AG1: Free Cash Flow Per Share - Current (Annual) | AH1: 52High | AI1: 52Low | AJ1: SimpleMovingAvg | AK1: SimpleMovingAvg | AL1: SimpleMovingAvg | AM1: A_MACDays_Streak | AN1: A_MACD_BRR1 | AO1: A_MACDH_D_BRR1 | AP1: Volume | AQ1: A_VolumeSpike | AR1: VolumeAvg | AS1: VolumeAvg | AT1: VolumeRateOfChange | AU1: A_Perf2M | AV1: A_Perf2Wk | AW1: A_Perf3D | AX1: A_3mnHigh | AY1: A_3mnLow | AZ1: A_3mnHighLow | BA1: A_3wkHighLow | BB1: A_EarningsDays | BC1: Market Cap
A2: =IF(AA2="","",E2&AA2) -> 46141ZM | B2: =E2 + TIME(LEFT(TEXT(F2,"0000"),2),RIGHT(TEXT(F2,"0000"),2),0) -> 46141.688 | C2: =IF(ISNUMBER(SEARCH("[",AA2)),LEFT(AA2,FIND("[",AA2)-1),AA2) -> ZM | D2: =IF(AA2="","",B2&C2) -> 46141.6875ZM | E2: =Y2 -> 46141 | F2: =Z2 -> 1630 | G2: =IF(AA2="","",IF(AG2="<empty>","",AG2)) -> 6.4 | H2: =IF(Z2="","",IF(AJ2="NaN",0,AJ2)) -> 86.92 | I2: =IF(AA2="","",IF(AK2="NaN",0,AK2)) -> 82.11 | J2: =IF(AA2="","",IF(AL2="NaN",0,AL2)) -> 82.69 | K2: =IF(AA2="","",IF(AP2="<empty>",0,AP2)) -> 6815835 | L2: =IF(AA2="","",IF(AR2="NaN",0,AR2)) -> 4431087.3 | M2: =IF(AA2="","",IF(AS2="NaN",0,AS2)) -> 4379189.9 | N2: =IF(AA2="","",IF(AT2="NaN",0,AT2)) -> 38.55 | O2: =IFERROR(K2/L2,0) -> 1.5381857 | P2: {=_xlfn.IFNA(_xlfn.XLOOKUP(C2, C$1:C1, O$1:O1, "", 0, -1), "")} | Q2: =AC2 -> 0.0507 | R2: =IF(E2<Dash!$AQ$5, C2, "") | S2: {=_xlfn.XLOOKUP(C2, R$1:R1, AB$1:AB1, 0, 0, -1)} -> 0 | T2: =IF(OR(AB2=0,S2=0),0,(AB2-S2)*100/S2) -> 0 | U2: {=_xlfn.IFS( AND(T2>12,O2>=2.8,N2>=120),1, AND(O2>=1.5,ABS(Q2)<0.003),2, AND(N2>=60,K2<L2,L2<=M2),3, AND(O2>=2.8,N2>=150),4, AND(L2<=1.05*M2,O2<1),5, AND(N2>=40,K2<L2,L2<=M2),6, AND(O2>=2,L2>M2,N2>=80,N2<150),7, AND(L2<=1.05*M2,O2>=2,N2>=60,Q2>0),8, AND(L2>M2,O2<1,P2>=1.5,N2>=30,Q2>0),9, AND(O2>=1.5,L2>M2,N2>=40,N2<140,Q2>0),10, TRUE,"" )} | V2: =IF(AA2="","",IF(AN2="NaN",0,AN2)) -> 1 | W2: =IF(AA2="","",IF(AO2="NaN",0,AO2)) -> 0.81 | X2: =IF(BB2="NaN",-99,BB2) -> 16 | Y2: 46141 | Z2: 1630 | AA2: ZM | AB2: 95.76 | AC2: 0.0507 | AD2: Information Technology | AE2: 1.5 | AF2: 4.32 | AG2: 6.4 | AH2: 97.58 | AI2: 69.15 | AJ2: 86.92 | AK2: 82.11 | AL2: 82.69 | AM2: 1 | AN2: 1 | AO2: 0.81 | AP2: 6815835 | AQ2: -200443.44 | AR2: 4431087.3 | AS2: 4379189.9 | AT2: 38.55 | AU2: 29.51 | AV2: 7.56 | AW2: 4.05 | AX2: 97.54 | AY2: 71.4 | AZ2: -71.4 | BA2: -77.13 | BB2: 16 | BC2: 28,217 M
A3: =IF(AA3="","",E3&AA3) -> 46141ZS | B3: =E3 + TIME(LEFT(TEXT(F3,"0000"),2),RIGHT(TEXT(F3,"0000"),2),0) -> 46141.688 | C3: =IF(ISNUMBER(SEARCH("[",AA3)),LEFT(AA3,FIND("[",AA3)-1),AA3) -> ZS | D3: =IF(AA3="","",B3&C3) -> 46141.6875ZS | E3: =Y3 -> 46141 | F3: =Z3 -> 1630 | G3: =IF(AA3="","",IF(AG3="<empty>","",AG3)) -> 5.55 | H3: =IF(Z3="","",IF(AJ3="NaN",0,AJ3)) -> 133.54 | I3: =IF(AA3="","",IF(AK3="NaN",0,AK3)) -> 145.07 | J3: =IF(AA3="","",IF(AL3="NaN",0,AL3)) -> 235.24 | K3: =IF(AA3="","",IF(AP3="<empty>",0,AP3)) -> 1339176 | L3: =IF(AA3="","",IF(AR3="NaN",0,AR3)) -> 3140769.1 | M3: =IF(AA3="","",IF(AS3="NaN",0,AS3)) -> 3008291.2 | N3: =IF(AA3="","",IF(AT3="NaN",0,AT3)) -> -81.76 | O3: =IFERROR(K3/L3,0) -> 0.42638474 | P3: {=_xlfn.IFNA(_xlfn.XLOOKUP(C3, C$1:C2, O$1:O2, "", 0, -1), "")} | Q3: =AC3 -> -0.0098 | R3: =IF(E3<Dash!$AQ$5, C3, "") | S3: {=_xlfn.XLOOKUP(C3, R$1:R2, AB$1:AB2, 0, 0, -1)} -> 0 | T3: =IF(OR(AB3=0,S3=0),0,(AB3-S3)*100/S3) -> 0 | U3: {=_xlfn.IFS( AND(T3>12,O3>=2.8,N3>=120),1, AND(O3>=1.5,ABS(Q3)<0.003),2, AND(N3>=60,K3<L3,L3<=M3),3, AND(O3>=2.8,N3>=150),4, AND(L3<=1.05*M3,O3<1),5, AND(N3>=40,K3<L3,L3<=M3),6, AND(O3>=2,L3>M3,N3>=80,N3<150),7, AND(L3<=1.05*M3,O3>=2,N3>=60,Q3>0),8, AND(L3>M3,O3<1,P3>=1.5,N3>=30,Q3>0),9, AND(O3>=1.5,L3>M3,N3>=40,N3<140,Q3>0),10, TRUE,"" )} -> 5 | V3: =IF(AA3="","",IF(AN3="NaN",0,AN3)) -> 0.58 | W3: =IF(AA3="","",IF(AO3="NaN",0,AO3)) -> -0.88 | X3: =IF(BB3="NaN",-99,BB3) -> 20 | Y3: 46141 | Z3: 1630 | AA3: ZS | AB3: 134.73 | AC3: -0.0098 | AD3: Information Technology | AE3: 1 | AF3: 6.56 | AG3: 5.55 | AH3: 336.99 | AI3: 114.625 | AJ3: 133.54 | AK3: 145.07 | AL3: 235.24 | AM3: -5 | AN3: 0.58 | AO3: -0.88 | AP3: 1339176 | AQ3: -100866.15 | AR3: 3140769.1 | AS3: 3008291.2 | AT3: -81.76 | AU3: -8.34 | AV3: 2.84 | AW3: -0.57 | AX3: 211.62 | AY3: 115.13 | AZ3: -115.13 | BA3: -115.13 | BB3: 20 | BC3: 21,663 M

Sheet TO
A1: DateSymbol | B1: DateTime | C1: Sym | D1: DateSymbolTime | E1: Date | F1: Sequence | G1: Market Cap | H1: Export Date | I1: Export Time | J1: Symbol | K1: Beta | L1: Market Cap | M1: Long-term Debt to Capital - Current (LTM) | N1: Price / Earnings Ratio - Current | O1: Price / Book Value Ratio - Current | P1: Return on Equity (ROE) - Current (LTM) | Q1: EPS | R1: Div. Yield - Current | S1: Sector | T1: Free Cash Flow Per Share - Current (LTM)
A2: =IF(J2="","",E2&J2) -> 46139ZM | B2: =E2 + TIME(LEFT(TEXT(F2,"0000"),2),RIGHT(TEXT(F2,"0000"),2),0) -> 46139.688 | C2: =IF(ISNUMBER(SEARCH("[",J2)),LEFT(J2,FIND("[",J2)-1),J2) -> ZM | D2: =IF(J2="","",B2&C2) -> 46139.6875ZM | E2: =H2 -> 46139 | F2: =I2 -> 1630 | G2: =VALUE(SUBSTITUTE(SUBSTITUTE(L2," M",""),",",""))*1000000 -> 26765000000 | H2: 46139 | I2: 1630 | J2: ZM | K2: 1.5 | L2: 26,765 M | M2: 0.3112 | N2: 14.896 | O2: 2.775 | P2: 20.275 | Q2: 6.18 | R2: <empty> | S2: Information Technology | T2: 6.4
A3: =IF(J3="","",E3&J3) -> 46139ZS | B3: =E3 + TIME(LEFT(TEXT(F3,"0000"),2),RIGHT(TEXT(F3,"0000"),2),0) -> 46139.688 | C3: =IF(ISNUMBER(SEARCH("[",J3)),LEFT(J3,FIND("[",J3)-1),J3) -> ZS | D3: =IF(J3="","",B3&C3) -> 46139.6875ZS | E3: =H3 -> 46139 | F3: =I3 -> 1630 | G3: =VALUE(SUBSTITUTE(SUBSTITUTE(L3," M",""),",",""))*1000000 -> 21564000000 | H3: 46139 | I3: 1630 | J3: ZS | K3: 1 | L3: 21,564 M | M3: 44.241 | N3: -465.55 | O3: 14.625 | P3: -3.5563 | Q3: -0.43 | R3: <empty> | S3: Information Technology | T3: 5.55

Sheet RR
A1: Key | B1: Y Ticker | C1: TOS Ticker | D1: Date | E1: Is Latest | F1: Latest Symbol | G1: Last Price | H1: Buy Trade | I1: Sell Trade | J1: Weight | K1: Prev Dt (<7 days) | L1: Prev Wt | M1: Modifier | N1: Entry | O1: Entry Wt | P1: Cont | Q1: Cont Wt | R1: Reverse | S1: BRR | T1: M TOS | U1: Ticker | V1: Name | W1: Outlook | X1: Sell Trade | Y1: Buy Trade | Z1: Last Price | AA1: Market Close | AB1: =_xlfn.MAXIFS(D:D,D:D,"<=" & Dash!AB9,D:D,">=" & Dash!AB10) -> 46141 | AC1: Look in RRT tab for mapping
A2: =D2&B2 -> 46141URA | B2: =_xlfn.XLOOKUP(U2,RRT!A:A,RRT!B:B) -> URA | C2: =_xlfn.XLOOKUP(U2,RRT!A:A,RRT!C:C) -> URA | D2: =AA2 -> 46141 | E2: =IF($AB$1=D2,"Y","") -> Y | F2: =IF(D2=_xlfn.MAXIFS(D:D,C:C,C2),C2,"") -> URA | G2: =Z2 -> 0 | H2: =X2 -> 0 | I2: =Y2 -> 0 | J2: =_xlfn.XLOOKUP(W2,Parm!$BH:$BH,Parm!$BI:$BI) -> 3 | K2: =IF(E2="","",IFERROR(_xlfn.MAXIFS(D$1:D1, B$1:B1, B2, D$1:D1, "<"&D2, D$1:D1, ">"&(D2-7),J$1:J1,"<>"&J2), "")) -> 0 | L2: =IF(OR(K2="",K2=0),"",_xlfn.XLOOKUP(K2&B2,A:A,J:J)) | M2: {=_xlfn.IFS(L2="","",J2<>L2,J2,TRUE,"")} | N2: {=IF(F2="","",_xlfn.IFS(AND(J2<=0,M2<0),"SellAll",J2<=-2,"SellAll",J2=-1,"SellWatch",J2=0,"Neutral",AND(J2>1,OR(M2>1,L2=0)),"BuySome",J2=3,"BuySome",J2=2,"BuySome",J2=1,"BuyWatch",TRUE,"Neutral"))} -> BuySome | O2: =_xlfn.XLOOKUP(N2,Parm!$AN$2:$AN$25,Parm!$AO$2:$AO$25,"") -> 9 | P2: {=IF(OR(F2="",M2=""),"",_xlfn.IFS(AND(_xlfn.NUMBERVALUE(J2)<=0,_xlfn.NUMBERVALUE(M2)<=0),"SellAll",AND(_xlfn.NUMBERVALUE(J2)>0,_xlfn.NUMBERVALUE(M2)<=0),"SellSome",AND(_xlfn.NUMBERVALUE(J2)>0,_xlfn.NUMBERVALUE(M2)>1),"BuyMore",AND(_xlfn.NUMBERVALUE(J2)>0,_xlfn.NUMBERVALUE(M2)>0),"BuySome",TRUE,""))} | Q2: =_xlfn.XLOOKUP(P2,Parm!$AN$2:$AN$25,Parm!$AO$2:$AO$25,"") | R2: =_xlfn.XLOOKUP(U2,RRT!A:A,RRT!D:D) -> N | S2: =IF(H2=0,"",IF(R2="Y",(G2-I2)/(H2-I2),(G2-H2)/(I2-H2))) | T2: {=IF(ISNA(_xlfn.XLOOKUP(C2,MA!B:B,,MA!B:B)),C2,"")} | U2: URA | V2: Global X Uranium ETF | W2: Bullish | X2: 0 | Y2: 0 | Z2: 0 | AA2: 46141
A3: =D3&B3 -> 46141XLY | B3: =_xlfn.XLOOKUP(U3,RRT!A:A,RRT!B:B) -> XLY | C3: =_xlfn.XLOOKUP(U3,RRT!A:A,RRT!C:C) -> XLY | D3: =AA3 -> 46141 | E3: =IF($AB$1=D3,"Y","") -> Y | F3: =IF(D3=_xlfn.MAXIFS(D:D,C:C,C3),C3,"") -> XLY | G3: =Z3 -> 0 | H3: =X3 -> 0 | I3: =Y3 -> 0 | J3: =_xlfn.XLOOKUP(W3,Parm!$BH:$BH,Parm!$BI:$BI) -> 3 | K3: =IF(E3="","",IFERROR(_xlfn.MAXIFS(D$1:D2, B$1:B2, B3, D$1:D2, "<"&D3, D$1:D2, ">"&(D3-7),J$1:J2,"<>"&J3), "")) -> 0 | L3: =IF(OR(K3="",K3=0),"",_xlfn.XLOOKUP(K3&B3,A:A,J:J)) | M3: {=_xlfn.IFS(L3="","",J3<>L3,J3,TRUE,"")} | N3: {=IF(F3="","",_xlfn.IFS(AND(J3<=0,M3<0),"SellAll",J3<=-2,"SellAll",J3=-1,"SellWatch",J3=0,"Neutral",AND(J3>1,OR(M3>1,L3=0)),"BuySome",J3=3,"BuySome",J3=2,"BuySome",J3=1,"BuyWatch",TRUE,"Neutral"))} -> BuySome | O3: =_xlfn.XLOOKUP(N3,Parm!$AN$2:$AN$25,Parm!$AO$2:$AO$25,"") -> 9 | P3: {=IF(OR(F3="",M3=""),"",_xlfn.IFS(AND(_xlfn.NUMBERVALUE(J3)<=0,_xlfn.NUMBERVALUE(M3)<=0),"SellAll",AND(_xlfn.NUMBERVALUE(J3)>0,_xlfn.NUMBERVALUE(M3)<=0),"SellSome",AND(_xlfn.NUMBERVALUE(J3)>0,_xlfn.NUMBERVALUE(M3)>1),"BuyMore",AND(_xlfn.NUMBERVALUE(J3)>0,_xlfn.NUMBERVALUE(M3)>0),"BuySome",TRUE,""))} | Q3: =_xlfn.XLOOKUP(P3,Parm!$AN$2:$AN$25,Parm!$AO$2:$AO$25,"") | R3: =_xlfn.XLOOKUP(U3,RRT!A:A,RRT!D:D) -> N | S3: =IF(H3=0,"",IF(R3="Y",(G3-I3)/(H3-I3),(G3-H3)/(I3-H3))) | T3: {=IF(ISNA(_xlfn.XLOOKUP(C3,MA!B:B,,MA!B:B)),C3,"")} | U3: XLY | V3: Consumer Discretionary Select Sector SPDR Fund | W3: Bullish | X3: 0 | Y3: 0 | Z3: 0 | AA3: 46141

Sheet call
A1: Key | B1: Symbol | C1: Date | D1: Outlook | E1: Outlook Modifier | F1: Prev Date | G1: Prev State | H1: Lastest Symbol | I1: Weight | J1: Modifier | K1: CAll Entry | L1: CAll Entry Wt | M1: CAll Cont | N1: CAll Cont Wt | O1: Miss | P1: TOS Lookup | Q1: MA Lookup | R1: Y Lookup | S1: Imported Date | T1: Symbol | U1: Outlook | V1: Outlook Modifier | Y1: =TODAY()-45 -> 46102
A2: =C2&B2 -> 46141META | B2: =T2 -> META | C2: =S2 -> 46141 | D2: =U2 -> BULLISH | E2: =V2 -> long | F2: =IFERROR(_xlfn.MAXIFS(C:C, B:B, B2, C:C, "<"&C2), "") -> 0 | G2: =IF(F2>0,_xlfn.XLOOKUP(F2&B2,A:A,I:I),"") | H2: =IF(C2<$Y$1,"",IF(C2=_xlfn.MAXIFS(C:C,B:B,B2),B2,"")) -> META | I2: =_xlfn.XLOOKUP(E2,Parm!$BE:$BE,Parm!$BF:$BF) -> 3 | J2: =IF(G2<>"",I2-G2,0) -> 0 | K2: {=IF(H2="","",_xlfn.IFS(AND(I2<=0,J2<0),"SellAll",I2<=-2,"SellAll",I2=-1,"SellWatch",C2<Dash!$AH$3,"Neutral",I2=0,"Neutral",AND(I2>1,OR(J2>1,G2=0)),"BuySome",I2=3,"BuySome",I2=2,"BuySome",I2=1,"BuyWatch",TRUE,"Neutral"))} -> BuySome | L2: =_xlfn.XLOOKUP(K2,Parm!$AN$2:$AN$25,Parm!$AO$2:$AO$25,"") -> 9 | M2: {=IF(H2="","",_xlfn.IFS(AND(I2<=0,J2<0),"SellAll",AND(I2>0,J2<0),"SellSome",C2<Dash!$AH$3,"",AND(I2>0,J2>1),"BuyMore",AND(I2>0,J2>0),"BuySome",TRUE,""))} | N2: =_xlfn.XLOOKUP(M2,Parm!$AN$2:$AN$25,Parm!$AO$2:$AO$25,"") | O2: {=_xlfn.IFS(I2<=0,"",LEFT(B2,1)="$","",AND(ISNA(Q2),C2>$Y$1),B2,TRUE,"")} -> META | P2: =_xlfn.XLOOKUP(B2,TL!C:C,TL!C:C) -> #N/A | Q2: =_xlfn.XLOOKUP(B2,MA!B:B,MA!B:B) -> #N/A | R2: =_xlfn.XLOOKUP(B2,Y!C:C,Y!C:C) -> #N/A | S2: 46141 | T2: META | U2: BULLISH | V2: long
A3: =C3&B3 -> 46141ODFL | B3: =T3 -> ODFL | C3: =S3 -> 46141 | D3: =U3 -> BEARISH | E3: =V3 -> short | F3: =IFERROR(_xlfn.MAXIFS(C:C, B:B, B3, C:C, "<"&C3), "") -> 0 | G3: =IF(F3>0,_xlfn.XLOOKUP(F3&B3,A:A,I:I),"") | H3: =IF(C3<$Y$1,"",IF(C3=_xlfn.MAXIFS(C:C,B:B,B3),B3,"")) -> ODFL | I3: =_xlfn.XLOOKUP(E3,Parm!$BE:$BE,Parm!$BF:$BF) -> -3 | J3: =IF(G3<>"",I3-G3,0) -> 0 | K3: {=IF(H3="","",_xlfn.IFS(AND(I3<=0,J3<0),"SellAll",I3<=-2,"SellAll",I3=-1,"SellWatch",C3<Dash!$AH$3,"Neutral",I3=0,"Neutral",AND(I3>1,OR(J3>1,G3=0)),"BuySome",I3=3,"BuySome",I3=2,"BuySome",I3=1,"BuyWatch",TRUE,"Neutral"))} -> SellAll | L3: =_xlfn.XLOOKUP(K3,Parm!$AN$2:$AN$25,Parm!$AO$2:$AO$25,"") -> -10 | M3: {=IF(H3="","",_xlfn.IFS(AND(I3<=0,J3<0),"SellAll",AND(I3>0,J3<0),"SellSome",C3<Dash!$AH$3,"",AND(I3>0,J3>1),"BuyMore",AND(I3>0,J3>0),"BuySome",TRUE,""))} | N3: =_xlfn.XLOOKUP(M3,Parm!$AN$2:$AN$25,Parm!$AO$2:$AO$25,"") | O3: {=_xlfn.IFS(I3<=0,"",LEFT(B3,1)="$","",AND(ISNA(Q3),C3>$Y$1),B3,TRUE,"")} | P3: =_xlfn.XLOOKUP(B3,TL!C:C,TL!C:C) -> #N/A | Q3: =_xlfn.XLOOKUP(B3,MA!B:B,MA!B:B) -> #N/A | R3: =_xlfn.XLOOKUP(B3,Y!C:C,Y!C:C) -> #N/A | S3: 46141 | T3: ODFL | U3: BEARISH | V3: short
A4: =C4&B4 -> 46141HUM | B4: =T4 -> HUM | C4: =S4 -> 46141 | D4: =U4 -> NEUTRAL | E4: =V4 -> neutral | F4: =IFERROR(_xlfn.MAXIFS(C:C, B:B, B4, C:C, "<"&C4), "") -> 0 | G4: =IF(F4>0,_xlfn.XLOOKUP(F4&B4,A:A,I:I),"") | H4: =IF(C4<$Y$1,"",IF(C4=_xlfn.MAXIFS(C:C,B:B,B4),B4,"")) -> HUM | I4: =_xlfn.XLOOKUP(E4,Parm!$BE:$BE,Parm!$BF:$BF) -> 0 | J4: =IF(G4<>"",I4-G4,0) -> 0 | K4: {=IF(H4="","",_xlfn.IFS(AND(I4<=0,J4<0),"SellAll",I4<=-2,"SellAll",I4=-1,"SellWatch",C4<Dash!$AH$3,"Neutral",I4=0,"Neutral",AND(I4>1,OR(J4>1,G4=0)),"BuySome",I4=3,"BuySome",I4=2,"BuySome",I4=1,"BuyWatch",TRUE,"Neutral"))} -> Neutral | L4: =_xlfn.XLOOKUP(K4,Parm!$AN$2:$AN$25,Parm!$AO$2:$AO$25,"") -> 0 | M4: {=IF(H4="","",_xlfn.IFS(AND(I4<=0,J4<0),"SellAll",AND(I4>0,J4<0),"SellSome",C4<Dash!$AH$3,"",AND(I4>0,J4>1),"BuyMore",AND(I4>0,J4>0),"BuySome",TRUE,""))} | N4: =_xlfn.XLOOKUP(M4,Parm!$AN$2:$AN$25,Parm!$AO$2:$AO$25,"") | O4: {=_xlfn.IFS(I4<=0,"",LEFT(B4,1)="$","",AND(ISNA(Q4),C4>$Y$1),B4,TRUE,"")} | P4: =_xlfn.XLOOKUP(B4,TL!C:C,TL!C:C) -> #N/A | Q4: =_xlfn.XLOOKUP(B4,MA!B:B,MA!B:B) -> #N/A | R4: =_xlfn.XLOOKUP(B4,Y!C:C,Y!C:C) -> #N/A | S4: 46141 | T4: HUM | U4: NEUTRAL | V4: neutral

Sheet F
A1: Key | B1: Symbol | C1: Ignore | D1: Date | E1: Price Paid | F1: Qty | G1: Cur Val | H1: Prev Qty | I1: Prev Val | J1: New leg | K1: Leg ID | L1: Qty Diff | M1: Snapshot P/L | N1: Running P/L | O1: Leg Status | P1: Leg P/L | Q1: Final Status | R1: Final P/L | S1: M TOS | T1: Y Lookup | U1: TOS Lookup | V1: MA Lookup | W1: Export Date | X1: Account Number | Y1: Account Name | Z1: Symbol | AA1: Description | AB1: Quantity | AC1: Last Price | AD1: Last Price Change | AE1: Current Value | AF1: Today's Gain/Loss Dollar | AG1: Today's Gain/Loss Percent | AH1: Total Gain/Loss Dollar | AI1: Total Gain/Loss Percent | AJ1: Percent Of Account | AK1: Cost Basis Total | AL1: Average Cost Basis | AM1: Type | AO1: Today | AP1: =Dash!$AB$2 -> 46142 | AQ1: =_xlfn.MAXIFS(D:D,D:D,"<=" & AP1) -> 46126
A2: =D2&Z2 -> 46126DOW | B2: =Z2 -> DOW | C2: =IF(B2="SPAXX**","Y","") | D2: =W2 -> 46126 | E2: =AC2 -> 39.16 | F2: =AB2 -> 150 | G2: =AE2 -> 5874 | H2: {=_xlfn.XLOOKUP(1, (B$1:B1=B2)*(K$1:K1=K2), F$1:F1, 0, 0, -1)} -> 0 | I2: {=_xlfn.XLOOKUP(1, (B$1:B1=B2)*(K$1:K1=K2), G$1:G1, 0, 0, -1)} -> 0 | J2: =IF(COUNTIFS(B$1:B1, B2, D$1:D1, _xlfn.MAXIFS(D$1:D1,D$1:D1,"<"&D2))>0, 0, 1) -> 1 | K2: {=IF(J2=1, _xlfn.MAXIFS(K$1:K1,B$1:B1,B2)+1, _xlfn.XLOOKUP(B2, B$1:B1, K$1:K1, 0, 0, -1))} -> 1 | L2: =IF(I2="","",F2-H2) -> 150 | M2: =IF(OR(H2=0, K2=""), 0, G2 - (I2/H2 * F2)) -> 0 | N2: =SUMIFS(M$1:M2, B$1:B2, B2, K$1:K2, K2) -> 0 | O2: =IF(COUNTIFS(B:B, B2, D:D, _xlfn.MINIFS(D:D, D:D, ">"&D2))=0, IF(D2=MAX(D:D),"","Closed"), "") | P2: =IF(OR(F2=0, O2="Closed"), N2, "") | Q2: =IF(COUNTIFS(B3:B$94716, B2)=0, "Final", "") -> Final | R2: =IF(Q2="Final", SUMIFS(M$1:M2, B$1:B2, B2), "") -> 0 | S2: =IF(AND(ISNA(V2),O2="Final"),B2,"") | T2: =IF(C2="Y","",_xlfn.XLOOKUP(Z2,Y!C:C,Y!C:C)) -> #N/A | U2: =IF(C2="Y","",_xlfn.XLOOKUP(Z2,TL!C:C,TL!C:C)) -> #N/A | V2: =IF(C2="Y","",_xlfn.XLOOKUP(Z2,MA!B:B,MA!B:B)) -> #N/A | W2: 46126 | X2: 249118149 | Y2: Rollover IRA | Z2: DOW | AA2: DOW INC COM | AB2: 150 | AC2: 39.16 | AD2: -0.95 | AE2: 5874 | AF2: -142.5 | AG2: -0.0237 | AH2: 52.01 | AI2: 0.0089 | AJ2: 0.0341 | AK2: 5821.99 | AL2: 38.81 | AM2: Cash

Sheet CS
A1: Key | B1: Symbol | C1: Ignore | D1: Date | E1: Price Paid | F1: Qty | G1: Cost | H1: Prev Qty | I1: Prev Val | J1: New leg | K1: Leg ID | L1: Qty Diff | M1: Snapshot P/L | N1: Running P/L | O1: Leg Status | P1: Leg P/L | Q1: Final Status | R1: Final P/L | S1: Account | T1: M TOS | U1: Y Lookup | V1: TOS Lookup | W1: MA Lookup | X1: Account | Y1: Imported Date | Z1: Symbol | AA1: Description | AB1: Qty (Quantity) | AC1: Price | AD1: Price Chng $ (Price Change $) | AE1: Price Chng % (Price Change %) | AF1: Mkt Val (Market Value) | AG1: Day Chng $ (Day Change $) | AH1: Day Chng % (Day Change %) | AI1: Cost Basis | AJ1: Gain $ (Gain/Loss $) | AK1: Gain % (Gain/Loss %) | AL1: Reinvest? | AM1: Reinvest Capital Gains? | AN1: Security Type
A2: =D2&B2 -> 46141XTL | B2: =Z2 -> XTL | C2: =IF(OR(B2="--",B2="Cash & Cash Investments",B2="SWPPX",B2="Account Total"),"Y","") | D2: =Y2 -> 46141 | E2: =IF(U2="",0,AI2/AB2) -> #N/A | F2: =IF(AB2="--",0,AB2) -> 75 | G2: =AI2 -> 15868.13 | H2: {=_xlfn.XLOOKUP(1, (B$1:B1=B2)*(K$1:K1=K2), F$1:F1, 0, 0, -1)} -> 0 | I2: {=_xlfn.XLOOKUP(1, (B$1:B1=B2)*(K$1:K1=K2), G$1:G1, 0, 0, -1)} -> 0 | J2: =IF(COUNTIFS(B$1:B1, B2, D$1:D1, _xlfn.MAXIFS(D$1:D1,D$1:D1,"<"&D2))>0, 0, 1) -> 1 | K2: {=IF(J2=1, _xlfn.MAXIFS(K$1:K1,B$1:B1,B2)+1, _xlfn.XLOOKUP(B2, B$1:B1, K$1:K1, 0, 0, -1))} -> 1 | L2: =IF(I2="","",F2-H2) -> 75 | M2: =IF(OR(H2=0, K2=""), 0, G2 - (I2/H2 * F2)) -> 0 | N2: =SUMIFS(M$1:M2, B$1:B2, B2, K$1:K2, K2) -> 0 | O2: =IF(COUNTIFS(B:B, B2, D:D, _xlfn.MINIFS(D:D, D:D, ">"&D2))=0, IF(D2=MAX(D:D),"","Closed"), "") | P2: =IF(OR(F2=0, O2="Closed"), N2, "") | Q2: =IF(COUNTIFS(B3:B$92426, B2)=0, "Final", "") -> Final | R2: =IF(Q2="Final", SUMIFS(M$1:M2, B$1:B2, B2), "") -> 0 | S2: =X2 -> Rollover_IRA ...892 | T2: =IF(AND(Q2="Final",ISNA(W2)),B2,"") -> XTL | U2: =IF(C2="Y","",_xlfn.XLOOKUP(Z2,Y!C:C,Y!C:C)) -> #N/A | V2: =IF(C2="Y","",_xlfn.XLOOKUP(Z2,TL!C:C,TL!C:C)) -> #N/A | W2: =IF(C2="Y","",_xlfn.XLOOKUP(Z2,MA!B:B,MA!B:B)) -> #N/A | X2: Rollover_IRA ...892 | Y2: 46141 | Z2: XTL | AA2: STATE STREET SPDR S&P TELECOM ETF | AB2: 75 | AC2: 214.3 | AD2: 3.8 | AE2: 0.0181 | AF2: 16072.5 | AG2: 227.37 | AH2: 0.0143 | AI2: 15868.13 | AJ2: 204.37 | AK2: 0.0129 | AL2: No | AM2: N/A | AN2: ETFs & Closed End Funds

Sheet etf
A1: Key | B1: Symbol | C1: Date | D1: Outlook | E1: BRR | F1: TRR | G1: Weight | H1: Is Latest? | I1: Latest Symbol | J1: ETF Entry | K1: ETF Entry Wt | L1: ETF Cont | M1: ETF Cont Wt | N1: Date2 | O1: ETF Change | P1: Error | Q1: MA | R1: Imported Date | S1: Sector | T1: Ticker | U1: Date Added | V1: Recent Price | W1: BRR | X1: TRR | Y1: Asset Class | AA1: Include | AB1: =Dash!AH4 -> 46111
A2: 460190 | B2: 0 | C2: 46019 | D2: BULLISH | E2: 0 | F2: 0 | G2: 3 | N2: 46019 | R2: 46019 | S2: BULLISH
A3: 46019BUXX | B3: BUXX | C3: 46019 | D3: BULLISH | E3: 20.32 | F3: 20.41 | G3: 3 | N3: 46019 | R3: 46019 | S3: Income Short Maturity | T3: BUXX | U3: 45224 | V3: 20.36 | W3: 20.32 | X3: 20.41 | Y3: Domestic Fixed Income

Sheet etfchg
A1: Date | B1: Action | C1: Chg | D1: Wt | E1: Date2 | F1: Wt | G1: MA | H1: Imported Date | I1: Desc | J1: Symbol | K1: Outlook | L1: Change | N1: Keep the data only for a week
A2: =IF(H2="","",DATEVALUE(TEXT(H2,"mm/dd/yyyy"))) -> 45996 | B2: =IF(K2="Long",IF(L2="Long","BuySome","SellAll"),IF(L2="Short","SellAll","Neutral")) -> SellAll | C2: {=IF(ISNA(_xlfn.XLOOKUP(J2,#REF!,#REF!)),J2,"")} | D2: =_xlfn.IFNA(_xlfn.XLOOKUP(B2,Parm!$AN$2:$AN$25,Parm!$AO$2:$AO$25),"") -> -10 | E2: =H2 -> 45996 | F2: =IF(AND(K2="Long",L2="Neutral"),-3,_xlfn.XLOOKUP(L2,Parm!$BE$2:$BE$11,Parm!$BF$2:$BF$11)) -> -3 | G2: =IF(OR(J2="Dummy",F2<=0),"",IF(ISNA(_xlfn.XLOOKUP(C2,MA!B:B,MA!B:B)),C2,"")) | H2: 45996 | I2: Don’t Delete | J2: Dummy | K2: Long | L2: Neutral

Sheet II
A1: Key | B1: Symbol | C1: Date | D1: Outlook | E1: Weight | F1: Is Latest? | G1: Latest Symbol | H1: II Entry | I1: II Entry | J1: II Cont | K1: II Cont | L1: Date2 | M1: II Change | N1: M TOS | O1: Imported Date | P1: Outlook | Q1: Ticker | S1: Include | T1: =Dash!$AH$7 -> 46111
A2: =C2&B2 -> 46139WING | B2: =IF(Q2="","",Q2) -> WING | C2: =O2 -> 46139 | D2: =IF(P2="Long","BULLISH",IF(P2="Short","BEARISH",#REF!)) -> BEARISH | E2: =_xlfn.XLOOKUP(D2,Parm!$BE:$BE,Parm!$BF:$BF) -> -3 | F2: =IF(MAX(C:C)=C2,"Y","") -> Y | G2: =IF(C2=_xlfn.MAXIFS(C:C,B:B,B2),B2,"") -> WING | H2: =IF(G2="","",IF(F2="Y",IF(E2>0,"BuyMore","SellAll"),"Neutral")) -> SellAll | I2: =_xlfn.XLOOKUP(H2,Parm!$AN$2:$AN$25,Parm!$AO$2:$AO$25,"") -> -10 | J2: =IF(G2="","",IF(F2="Y",IF(E2>0,"","SellAll"),IF(E2>0,"SellNeutral",""))) -> SellAll | K2: =_xlfn.XLOOKUP(J2,Parm!$AN$2:$AN$25,Parm!$AO$2:$AO$25,"") -> -10 | L2: =C2 -> 46139 | M2: {=IF(F2="Y",IFERROR(INDEX(_xlfn._xlws.FILTER(IIchg!$B140:$B163, (IIchg!$J140:$J163=B2)), 1), ""),"")} | N2: =IF(OR(P2="Longs",P2="Shorts",P2="Stock"),"",IF(ISNA(_xlfn.XLOOKUP(B2,MA!B:B,MA!B:B)),B2,"")) -> WING | O2: 46139 | P2: Short | Q2: WING

Sheet IIchg
A1: Date | B1: Action | C1: Chg | E1: Outlook | F1: Miss | G1: MOS | H1: Imported Date | I1: Desc | J1: Symbol | K1: Outlook | L1: Change | N1: Keep the data only for a week

Sheet psRk
A1: Date | B1: Rank | C1: Ticker | D1: 1WK Ago | E1: 1MN Ago | F1: Date Added | G1: Asset Class | H1: Minimum | I1: Maximum
A2: 46146 | B2: 28 | C2: BNO | D2: 43 | F2: 2026-02-13 00:00:00 | G2: Commodities | H2: 0.01 | I2: 0.04

Sheet ps5
A1: Date | B1: Securities | C1: Day1 | D1: Day2 | E1: Day3 | F1: Day4 | G1: Day5
A2: 46146 | B2: Securities | C2: 01May | D2: 30Apr | E2: 29Apr | F2: 28Apr | G2: 27Apr
A3: 46146 | B3: BNO | C3: 28 | D3: 25 | E3: 26 | F3: 27 | G3: 27

Sheet psTn
A1: Date | B1: Securities | C1: Today | D1: 1 Day Ago | E1: 1 Week Ago | F1: 1 Month Ago | G1: 3 Months Ago
A2: 46146 | B2: Securities | C2: Today | D2: 1DayAgo | E2: 1WeekAgo | F2: 1MonthAgo | G2: 3MonthsAgo
A3: 46146 | B3: BNO | C3: 28 | D3: 25 | E3: 25 | F3: 17

Sheet ssH
A1: Key | B1: Date | C1: Stock | D1: Rank HL | E1: Unranked | F1: Signal | G1: Anlst Best Idea | H1: Rank | I1: Total | J1: Signal Sign | K1: Is Latest | L1: Latest | M1: Removed Date | N1: Miss MA | O1: TOS | P1: MA | Q1: Y | R1: Vlkup | S1: Imported Date | T1: Days On | U1: Ticker | V1: Signal Date | W1: Prior Close of Signal Price | X1: Last Close Price | Y1: % Delta Since Initial Siganl | Z1: Sector | AA1: Analyst | AB1: Anlyst Best Idea Rank | AE1: Today | AF1: =Dash!$AB$2 -> 46142 | AG1: =_xlfn.MAXIFS(B:B,B:B,"<=" & AF1) -> 46140
A2: =B2&C2 -> 46140AS | B2: =S2 -> 46140 | C2: =U2 -> AS | D2: =IF(E2="",H2,0) -> 3 | E2: =IF(G2="KMSignal", 99, IF(G2="Bench", 50, "")) | F2: =Y2 -> 0 | G2: =AB2 -> 3/9 | H2: {=IF(G2="KMSignal", 99, IF(G2="Bench", 50, _xlfn.TEXTSPLIT(G2,"/")))} -> 3 | I2: 9 | J2: {=_xlfn.IFS(F2>0.5,3,F2>0.25,2,F2>0,1,F2<=0,-1)} -> -1 | K2: =IF(B2=MAX(B:B),"Y","") -> Y | L2: =IF(B2=_xlfn.MAXIFS(B:B,C:C,C2),C2,"") -> AS | M2: =IF(AND(L2<>"",K2=""),B2,"") | N2: {=_xlfn.IFS(AND(ISNA(O2),K2="Y"),C2,TRUE,"")} -> AS | O2: =_xlfn.XLOOKUP(C2,TL!C:C,TL!C:C) -> #N/A | P2: =_xlfn.XLOOKUP(C2,MA!B:B,MA!B:B) -> #N/A | Q2: =_xlfn.XLOOKUP(C2,Y!C:C,Y!C:C) -> #N/A | R2: =_xlfn.XLOOKUP(C2,sss!B:B,sss!B:B) -> AS | S2: 46140 | T2: 0 | U2: AS | V2: 2026-04-27 00:00:00 | W2: 35.8 | X2: 35.8 | Y2: 0 | Z2: Retail | AA2: BrianMcGough | AB2: 3/9 | AE2: Day Ago | AF2: =AF1-1 -> 46141 | AG2: =_xlfn.MAXIFS(B:B,B:B,"<=" & AF2) -> 46140
AE3: Wk Ago | AF3: =AF1-7 -> 46135 | AG3: =_xlfn.MAXIFS(B:B,B:B,"<=" & AF3) -> 0
AE4: 3 Wks Ago | AF4: =AF1-7*3 -> 46121 | AG4: =_xlfn.MAXIFS(B:B,B:B,"<=" & AF4) -> 0
AE5: Month Ago | AF5: =EDATE(AF1, -1) -> 46111 | AG5: =_xlfn.MAXIFS(B:B,B:B,"<=" & AF5) -> 0
AE6: 3 Month Ago | AF6: =EDATE(AF1, -3) -> 46052 | AG6: =_xlfn.MAXIFS(B:B,B:B,"<=" & AF6) -> 0

Sheet Trig
A1: Value Column | B1: (1) Column | C1: (2) Brkeout From | D1: (3) Brkeout To | E1: (4) Wt - Bw (1) & (2) | F1: (5) Wt - Bw (2) & (3) | G1: (6) Wt - Abv (3) | I1: Buy | J1: Sell | K1: Sh | L1: ZM | M1: Stock | N1: Rating | O1: 899-SA-Trend-Breaks | Q1: 898-SA-Streak-VeryBad | S1: 897-SW-Vlm-Spike-Price-Dn | U1: 896-SA-TRbelowTN-Trade-Breaks | W1: 895-SA-!TN!TD!Bull-TRR-Rev | Y1: 894-SA-!Bull-TN-TRR | AA1: 893-SA-TRR-blw-TN | AC1: 889-STM-OverBought | AE1: 888-STM-!Bull-BBTh-Crossover-RSI-IVHV | AG1: 887-STM-!Bull--BBTh-Crossover-RSI-IV | AI1: 859-SS-Bull-BBTh-Crossover-RSI-IVHV | AK1: 858-SS-Bull-BBTh-Crossover-RSI-IV | AM1: 857-SS-BBTh-Crossover-RSIOnly | AO1: 798-STM-!Bull-TRR-Rev | AQ1: 796-SW-!Bull-BBTh-Crossover | AS1: 793-STM-!TD!Bull-TRR-Rev | AU1: 792-STM-Bull-TN-TD-TRR-RSI-IV | AW1: 791-STM-!Bull-HighAbvTRR | AY1: 789-SS-!Bull-OverBought | BA1: 788-SS-!Bull-TN-TD-TRR | BC1: 787-SS-Bull-TRR-Rev | BE1: 786-SS-Bull-OverBought | BG1: 785-SS-Trade-Breaks | BI1: 784-SS-Streak-GoingBad | BK1: 783-SW-Vol-Spke-Price-Dn-Past | BM1: 782-SS-3mnHigh | BO1: 781-SS-TRR-CloseToTrade | BQ1: 699-SW-Resistance | BS1: 698-SS-Bull-HighAbvTRR | BU1: 697-STM-Earnings-Date | BW1: 449-B-TN-TD-LRR-UP-MACD | BY1: 448-BS-TN-TD-LRR | CA1: 399-B-TN-TD-LRR-UP-MACD | CC1: 398-B-TN-TD-LRR-UP-DAY | CE1: 397-B-TN-TD-LRR | CG1: 396-BS-LRR-CloseToTrade | CI1: 395-BS-TN-TD-LRR | CK1: 394-BS-TN-LRR | CM1: 299-BS-BB-Streak-HiHi-TN-TD | CO1: 298-BS-BB-HL-HiHi-TN-TD | CQ1: 279-BS-BB-Streak-HiHi | CS1: 278-BS-BB-HL-HiHi | CU1: 277-BS-VS-LT | CW1: 269-BS-Bull | CY1: 268-BS-3M-HiHi | DA1: 267-BS-Trade-CO | DC1: 199-BS-TN-LRR-MACD-UP-DAY | DE1: 198-BS-TN-LRR-UP-MACD | DG1: 197-BS-TN-LRR-UP-DAY | DI1: 196-BS-TN-LRR | DK1: 189-BR-BB-LoHi | DM1: 188-BR-TNabvTD-UP-MACD-DAY | DO1: 187-BR-NoTN-NoTD-UP-MACD-DAY | DQ1: 186-BR-Trend-CO | DS1: 99-BS-Min | DU1: 98-BW-TD-LRR-RSI | DW1: 97-BW-TD-RSI-IV | DY1: 96-BW-RSI-IVHV-Min | EA1: 95-BW-LowBelwLRR | EC1: 94-BW-UP-MACD | EE1: 93-BW-LRRabvTD | EG1: 92-BS-RSI-MACD-Vlme-IVHV-IVBRR | EI1: 92-BS-RSI-MACD-Vlme-IVHV-IVBRR | EK1: 92-BS-RSI-MACD-Vlme-IVHV-IVBRR | EM1: 52-BS-BRR | EO1: 51-BS-TRADE-TREND | ES1: Rating
I2: 1 | J2: 1 | K2: Count | O2: {=SUMPRODUCT(--(O4:O118<>""),P4:P118)} -> 40 | Q2: {=SUMPRODUCT(--(Q4:Q118<>""),R4:R118)} -> 60 | S2: {=SUMPRODUCT(--(S4:S118<>""),T4:T118)} -> 10 | U2: {=SUMPRODUCT(--(U4:U118<>""),V4:V118)} -> 40 | W2: {=SUMPRODUCT(--(W4:W118<>""),X4:X118)} -> 80 | Y2: {=SUMPRODUCT(--(Y4:Y118<>""),Z4:Z118)} -> 40 | AA2: {=SUMPRODUCT(--(AA4:AA118<>""),AB4:AB118)} -> 50 | AC2: {=SUMPRODUCT(--(AC4:AC118<>""),AD4:AD118)} -> 70 | AE2: {=SUMPRODUCT(--(AE4:AE118<>""),AF4:AF118)} -> 60 | AG2: {=SUMPRODUCT(--(AG4:AG118<>""),AH4:AH118)} -> 50 | AI2: {=SUMPRODUCT(--(AI4:AI118<>""),AJ4:AJ118)} -> 60 | AK2: {=SUMPRODUCT(--(AK4:AK118<>""),AL4:AL118)} -> 50 | AM2: {=SUMPRODUCT(--(AM4:AM118<>""),AN4:AN118)} -> 20 | AO2: {=SUMPRODUCT(--(AO4:AO118<>""),AP4:AP118)} -> 90 | AQ2: {=SUMPRODUCT(--(AQ4:AQ118<>""),AR4:AR118)} -> 30 | AS2: {=SUMPRODUCT(--(AS4:AS118<>""),AT4:AT118)} -> 80 | AU2: {=SUMPRODUCT(--(AU4:AU118<>""),AV4:AV118)} -> 80 | AW2: {=SUMPRODUCT(--(AW4:AW118<>""),AX4:AX118)} -> 20 | AY2: {=SUMPRODUCT(--(AY4:AY118<>""),AZ4:AZ118)} -> 70 | BA2: {=SUMPRODUCT(--(BA4:BA118<>""),BB4:BB118)} -> 50 | BC2: {=SUMPRODUCT(--(BC4:BC118<>""),BD4:BD118)} -> 80 | BE2: {=SUMPRODUCT(--(BE4:BE118<>""),BF4:BF118)} -> 70 | BG2: {=SUMPRODUCT(--(BG4:BG118<>""),BH4:BH118)} -> 50 | BI2: {=SUMPRODUCT(--(BI4:BI118<>""),BJ4:BJ118)} -> 60 | BK2: {=SUMPRODUCT(--(BK4:BK118<>""),BL4:BL118)} -> 10 | BM2: {=SUMPRODUCT(--(BM4:BM118<>""),BN4:BN118)} -> 40 | BO2: {=SUMPRODUCT(--(BO4:BO118<>""),BP4:BP118)} -> 20 | BQ2: {=SUMPRODUCT(--(BQ4:BQ118<>""),BR4:BR118)} -> 10 | BS2: {=SUMPRODUCT(--(BS4:BS118<>""),BT4:BT118)} -> 20 | BU2: {=SUMPRODUCT(--(BU4:BU118<>""),BV4:BV118)} -> 10 | BW2: {=SUMPRODUCT(--(BW4:BW118<>""),BX4:BX118)} -> 73 | BY2: {=SUMPRODUCT(--(BY4:BY118<>""),BZ4:BZ118)} -> 70 | CA2: {=SUMPRODUCT(--(CA4:CA118<>""),CB4:CB118)} -> 74 | CC2: {=SUMPRODUCT(--(CC4:CC118<>""),CD4:CD118)} -> 74 | CE2: {=SUMPRODUCT(--(CE4:CE118<>""),CF4:CF118)} -> 91 | CG2: {=SUMPRODUCT(--(CG4:CG118<>""),CH4:CH118)} -> 50 | CI2: {=SUMPRODUCT(--(CI4:CI118<>""),CJ4:CJ118)} -> 60 | CK2: {=SUMPRODUCT(--(CK4:CK118<>""),CL4:CL118)} -> 70 | CM2: {=SUMPRODUCT(--(CM4:CM118<>""),CN4:CN118)} -> 85 | CO2: {=SUMPRODUCT(--(CO4:CO118<>""),CP4:CP118)} -> 113 | CQ2: {=SUMPRODUCT(--(CQ4:CQ118<>""),CR4:CR118)} -> 65 | CS2: {=SUMPRODUCT(--(CS4:CS118<>""),CT4:CT118)} -> 93 | CU2: {=SUMPRODUCT(--(CU4:CU118<>""),CV4:CV118)} -> 51 | CW2: {=SUMPRODUCT(--(CW4:CW118<>""),CX4:CX118)} -> 151 | CY2: {=SUMPRODUCT(--(CY4:CY118<>""),CZ4:CZ118)} -> 123 | DA2: {=SUMPRODUCT(--(DA4:DA118<>""),DB4:DB118)} -> 82 | DC2: {=SUMPRODUCT(--(DC4:DC118<>""),DD4:DD118)} -> 84 | DE2: {=SUMPRODUCT(--(DE4:DE118<>""),DF4:DF118)} -> 74 | DG2: {=SUMPRODUCT(--(DG4:DG118<>""),DH4:DH118)} -> 94 | DI2: {=SUMPRODUCT(--(DI4:DI118<>""),DJ4:DJ118)} -> 54 | DK2: {=SUMPRODUCT(--(DK4:DK118<>""),DL4:DL118)} -> 104 | DM2: {=SUMPRODUCT(--(DM4:DM118<>""),DN4:DN118)} -> 93 | DO2: {=SUMPRODUCT(--(DO4:DO118<>""),DP4:DP118)} -> 94 | DQ2: {=SUMPRODUCT(--(DQ4:DQ118<>""),DR4:DR118)} -> 102 | DS2: {=SUMPRODUCT(--(DS4:DS118<>""),DT4:DT118)} -> 106 | DU2: {=SUMPRODUCT(--(DU4:DU118<>""),DV4:DV118)} -> 80 | DW2: {=SUMPRODUCT(--(DW4:DW118<>""),DX4:DX118)} -> 80 | DY2: {=SUMPRODUCT(--(DY4:DY118<>""),DZ4:DZ118)} -> 100 | EA2: {=SUMPRODUCT(--(EA4:EA118<>""),EB4:EB118)} -> 50 | EC2: {=SUMPRODUCT(--(EC4:EC118<>""),ED4:ED118)} -> 75 | EE2: {=SUMPRODUCT(--(EE4:EE118<>""),EF4:EF118)} -> 50 | EG2: {=SUMPRODUCT(--(EG4:EG118<>""),EH4:EH118)} -> 20 | EI2: {=SUMPRODUCT(--(EI4:EI118<>""),EJ4:EJ118)} -> 20 | EK2: {=SUMPRODUCT(--(EK4:EK118<>""),EL4:EL118)} -> 10 | EM2: {=SUMPRODUCT(--(EM4:EM118<>""),EN4:EN118)} -> 10 | EO2: {=SUMPRODUCT(--(EO4:EO118<>""),EP4:EP118)} -> 20 | ES2: =SUM(ES4:ES118)*3 -> 84
I3: 1 | J3: 1 | K3: STK | L3: =L1 -> ZM | M3: =MATCH(L3,MA!B:B,0) -> 2 | N3: =SUM(N4:N118) -> 52 | P3: {=Trig!O$2-SUMPRODUCT(--($M$4:$M$118<=Trig!O$4:O$118), ((Trig!P$4:P$118)))} -> 20 | R3: {=Trig!Q$2-SUMPRODUCT(--($M$4:$M$118<=Trig!Q$4:Q$118), ((Trig!R$4:R$118)))} -> 40 | T3: {=Trig!S$2-SUMPRODUCT(--($M$4:$M$118<=Trig!S$4:S$118), ((Trig!T$4:T$118)))} -> 10 | V3: {=Trig!U$2-SUMPRODUCT(--($M$4:$M$118<=Trig!U$4:U$118), ((Trig!V$4:V$118)))} -> 30 | X3: {=Trig!W$2-SUMPRODUCT(--($M$4:$M$118<=Trig!W$4:W$118), ((Trig!X$4:X$118)))} -> 40 | Z3: {=Trig!Y$2-SUMPRODUCT(--($M$4:$M$118<=Trig!Y$4:Y$118), ((Trig!Z$4:Z$118)))} -> 20 | AB3: {=Trig!AA$2-SUMPRODUCT(--($M$4:$M$118<=Trig!AA$4:AA$118), ((Trig!AB$4:AB$118)))} -> 20 | AD3: {=Trig!AC$2-SUMPRODUCT(--($M$4:$M$118<=Trig!AC$4:AC$118), ((Trig!AD$4:AD$118)))} -> 50 | AF3: {=Trig!AE$2-SUMPRODUCT(--($M$4:$M$118<=Trig!AE$4:AE$118), ((Trig!AF$4:AF$118)))} -> 40 | AH3: {=Trig!AG$2-SUMPRODUCT(--($M$4:$M$118<=Trig!AG$4:AG$118), ((Trig!AH$4:AH$118)))} -> 30 | AJ3: {=Trig!AI$2-SUMPRODUCT(--($M$4:$M$118<=Trig!AI$4:AI$118), ((Trig!AJ$4:AJ$118)))} -> 50 | AL3: {=Trig!AK$2-SUMPRODUCT(--($M$4:$M$118<=Trig!AK$4:AK$118), ((Trig!AL$4:AL$118)))} -> 40 | AN3: {=Trig!AM$2-SUMPRODUCT(--($M$4:$M$118<=Trig!AM$4:AM$118), ((Trig!AN$4:AN$118)))} -> 10 | AP3: {=Trig!AO$2-SUMPRODUCT(--($M$4:$M$118<=Trig!AO$4:AO$118), ((Trig!AP$4:AP$118)))} -> 50 | AR3: {=Trig!AQ$2-SUMPRODUCT(--($M$4:$M$118<=Trig!AQ$4:AQ$118), ((Trig!AR$4:AR$118)))} -> 0 | AT3: {=Trig!AS$2-SUMPRODUCT(--($M$4:$M$118<=Trig!AS$4:AS$118), ((Trig!AT$4:AT$118)))} -> 50 | AV3: {=Trig!AU$2-SUMPRODUCT(--($M$4:$M$118<=Trig!AU$4:AU$118), ((Trig!AV$4:AV$118)))} -> 60 | AX3: {=Trig!AW$2-SUMPRODUCT(--($M$4:$M$118<=Trig!AW$4:AW$118), ((Trig!AX$4:AX$118)))} -> 0 | AZ3: {=Trig!AY$2-SUMPRODUCT(--($M$4:$M$118<=Trig!AY$4:AY$118), ((Trig!AZ$4:AZ$118)))} -> 40 | BB3: {=Trig!BA$2-SUMPRODUCT(--($M$4:$M$118<=Trig!BA$4:BA$118), ((Trig!BB$4:BB$118)))} -> 30 | BD3: {=Trig!BC$2-SUMPRODUCT(--($M$4:$M$118<=Trig!BC$4:BC$118), ((Trig!BD$4:BD$118)))} -> 50 | BF3: {=Trig!BE$2-SUMPRODUCT(--($M$4:$M$118<=Trig!BE$4:BE$118), ((Trig!BF$4:BF$118)))} -> 50 | BH3: {=Trig!BG$2-SUMPRODUCT(--($M$4:$M$118<=Trig!BG$4:BG$118), ((Trig!BH$4:BH$118)))} -> 30 | BJ3: {=Trig!BI$2-SUMPRODUCT(--($M$4:$M$118<=Trig!BI$4:BI$118), ((Trig!BJ$4:BJ$118)))} -> 50 | BL3: {=Trig!BK$2-SUMPRODUCT(--($M$4:$M$118<=Trig!BK$4:BK$118), ((Trig!BL$4:BL$118)))} -> 10 | BN3: {=Trig!BM$2-SUMPRODUCT(--($M$4:$M$118<=Trig!BM$4:BM$118), ((Trig!BN$4:BN$118)))} -> 30 | BP3: {=Trig!BO$2-SUMPRODUCT(--($M$4:$M$118<=Trig!BO$4:BO$118), ((Trig!BP$4:BP$118)))} -> 10 | BR3: {=Trig!BQ$2-SUMPRODUCT(--($M$4:$M$118<=Trig!BQ$4:BQ$118), ((Trig!BR$4:BR$118)))} -> 10 | BT3: {=Trig!BS$2-SUMPRODUCT(--($M$4:$M$118<=Trig!BS$4:BS$118), ((Trig!BT$4:BT$118)))} -> 10 | BV3: {=Trig!BU$2-SUMPRODUCT(--($M$4:$M$118<=Trig!BU$4:BU$118), ((Trig!BV$4:BV$118)))} -> 10 | BX3: {=Trig!BW$2-SUMPRODUCT(--($M$4:$M$118>=Trig!BW$4:BW$118), ((Trig!BX$4:BX$118)))} -> 31 | BZ3: {=Trig!BY$2-SUMPRODUCT(--($M$4:$M$118>=Trig!BY$4:BY$118), ((Trig!BZ$4:BZ$118)))} -> 30 | CB3: {=Trig!CA$2-SUMPRODUCT(--($M$4:$M$118>=Trig!CA$4:CA$118), ((Trig!CB$4:CB$118)))} -> 41 | CD3: {=Trig!CC$2-SUMPRODUCT(--($M$4:$M$118>=Trig!CC$4:CC$118), ((Trig!CD$4:CD$118)))} -> 31 | CF3: {=Trig!CE$2-SUMPRODUCT(--($M$4:$M$118>=Trig!CE$4:CE$118), ((Trig!CF$4:CF$118)))} -> 41 | CH3: {=Trig!CG$2-SUMPRODUCT(--($M$4:$M$118>=Trig!CG$4:CG$118), ((Trig!CH$4:CH$118)))} -> 30 | CJ3: {=Trig!CI$2-SUMPRODUCT(--($M$4:$M$118>=Trig!CI$4:CI$118), ((Trig!CJ$4:CJ$118)))} -> 30 | CL3: {=Trig!CK$2-SUMPRODUCT(--($M$4:$M$118>=Trig!CK$4:CK$118), ((Trig!CL$4:CL$118)))} -> 30 | CN3: {=Trig!CM$2-SUMPRODUCT(--($M$4:$M$118>=Trig!CM$4:CM$118), ((Trig!CN$4:CN$118)))} -> 41 | CP3: {=Trig!CO$2-SUMPRODUCT(--($M$4:$M$118>=Trig!CO$4:CO$118), ((Trig!CP$4:CP$118)))} -> 21 | CR3: {=Trig!CQ$2-SUMPRODUCT(--($M$4:$M$118>=Trig!CQ$4:CQ$118), ((Trig!CR$4:CR$118)))} -> 31 | CT3: {=Trig!CS$2-SUMPRODUCT(--($M$4:$M$118>=Trig!CS$4:CS$118), ((Trig!CT$4:CT$118)))} -> 11 | CV3: {=Trig!CU$2-SUMPRODUCT(--($M$4:$M$118>=Trig!CU$4:CU$118), ((Trig!CV$4:CV$118)))} -> 21 | CX3: {=Trig!CW$2-SUMPRODUCT(--($M$4:$M$118>=Trig!CW$4:CW$118), ((Trig!CX$4:CX$118)))} -> 51 | CZ3: {=Trig!CY$2-SUMPRODUCT(--($M$4:$M$118>=Trig!CY$4:CY$118), ((Trig!CZ$4:CZ$118)))} -> 41 | DB3: {=Trig!DA$2-SUMPRODUCT(--($M$4:$M$118>=Trig!DA$4:DA$118), ((Trig!DB$4:DB$118)))} -> 21 | DD3: {=Trig!DC$2-SUMPRODUCT(--($M$4:$M$118>=Trig!DC$4:DC$118), ((Trig!DD$4:DD$118)))} -> 31 | DF3: {=Trig!DE$2-SUMPRODUCT(--($M$4:$M$118>=Trig!DE$4:DE$118), ((Trig!DF$4:DF$118)))} -> 31 | DH3: {=Trig!DG$2-SUMPRODUCT(--($M$4:$M$118>=Trig!DG$4:DG$118), ((Trig!DH$4:DH$118)))} -> 21 | DJ3: {=Trig!DI$2-SUMPRODUCT(--($M$4:$M$118>=Trig!DI$4:DI$118), ((Trig!DJ$4:DJ$118)))} -> 31 | DL3: {=Trig!DK$2-SUMPRODUCT(--($M$4:$M$118>=Trig!DK$4:DK$118), ((Trig!DL$4:DL$118)))} -> 51 | DN3: {=Trig!DM$2-SUMPRODUCT(--($M$4:$M$118>=Trig!DM$4:DM$118), ((Trig!DN$4:DN$118)))} -> 51 | DP3: {=Trig!DO$2-SUMPRODUCT(--($M$4:$M$118>=Trig!DO$4:DO$118), ((Trig!DP$4:DP$118)))} -> 41 | DR3: {=Trig!DQ$2-SUMPRODUCT(--($M$4:$M$118>=Trig!DQ$4:DQ$118), ((Trig!DR$4:DR$118)))} -> 42 | DT3: {=Trig!DS$2-SUMPRODUCT(--($M$4:$M$118>=Trig!DS$4:DS$118), ((Trig!DT$4:DT$118)))} -> 41 | DV3: {=Trig!DU$2-SUMPRODUCT(--($M$4:$M$118>=Trig!DU$4:DU$118), ((Trig!DV$4:DV$118)))} -> 30 | DX3: {=Trig!DW$2-SUMPRODUCT(--($M$4:$M$118>=Trig!DW$4:DW$118), ((Trig!DX$4:DX$118)))} -> 30 | DZ3: {=Trig!DY$2-SUMPRODUCT(--($M$4:$M$118>=Trig!DY$4:DY$118), ((Trig!DZ$4:DZ$118)))} -> 70 | EB3: {=Trig!EA$2-SUMPRODUCT(--($M$4:$M$118>=Trig!EA$4:EA$118), ((Trig!EB$4:EB$118)))} -> 20 | ED3: {=Trig!EC$2-SUMPRODUCT(--($M$4:$M$118>=Trig!EC$4:EC$118), ((Trig!ED$4:ED$118)))} -> 42 | EF3: {=Trig!EE$2-SUMPRODUCT(--($M$4:$M$118>=Trig!EE$4:EE$118), ((Trig!EF$4:EF$118)))} -> 10 | EH3: {=Trig!EG$2-SUMPRODUCT(--($M$4:$M$118>=Trig!EG$4:EG$118), ((Trig!EH$4:EH$118)))} -> 0 | EJ3: {=Trig!EI$2-SUMPRODUCT(--($M$4:$M$118>=Trig!EI$4:EI$118), ((Trig!EJ$4:EJ$118)))} -> 0 | EL3: {=Trig!EK$2-SUMPRODUCT(--($M$4:$M$118>=Trig!EK$4:EK$118), ((Trig!EL$4:EL$118)))} -> 0 | EN3: {=Trig!EM$2-SUMPRODUCT(--($M$4:$M$118>=Trig!EM$4:EM$118), ((Trig!EN$4:EN$118)))} -> 10 | EP3: {=Trig!EO$2-SUMPRODUCT(--($M$4:$M$118>=Trig!EO$4:EO$118), ((Trig!EP$4:EP$118)))} -> 10 | ES3: {=SUMPRODUCT(--($M$4:$M$118>=0), $M$4:$M$118, ((Trig!ES$4:ES$118)))} -> 52
K4: MA | L4: Begin | M4: {=TRANSPOSE(INDIRECT("MA!JR" & M3 & ":OB" & M3))} -> -1
I5: {=IF( SUM(--NOT(ISBLANK(BW5:EP5) ) ),1, "" )} -> 1 | J5: {=IF( SUM(--NOT(ISBLANK(O5:BV5) ) ),1, "" )} -> 1 | K5: MA | L5: MACDH Direction | M5: 2 | N5: =IF(ES5="", "", IF(M5>0,M5*ES5,0)) -> 2 | O5: -1 | P5: 10 | Q5: -1 | R5: 10 | U5: -1 | V5: 10 | AO5: 0 | AP5: 10 | BC5: -1 | BD5: 10 | BG5: -1 | BH5: 10 | BI5: -1 | BJ5: 10 | CM5: 1 | CN5: 10 | CO5: 1 | CP5: 10 | CQ5: 1 | CR5: 10 | CS5: 1 | CT5: 10 | CU5: 1 | CV5: 10 | CW5: 1 | CX5: 10 | CY5: 1 | CZ5: 10 | DK5: 1 | DL5: 10 | DS5: 1 | DT5: 10 | EE5: 1 | EF5: 10 | ES5: 1
I6: {=IF( SUM(--NOT(ISBLANK(BW6:EP6) ) ),1, "" )} | J6: {=IF( SUM(--NOT(ISBLANK(O6:BV6) ) ),1, "" )} -> 1 | K6: MA | L6: MACD Direction | M6: -1 | N6: =IF(ES6="", "", IF(M6>0,M6*ES6,0)) -> 0 | O6: -1 | P6: 10 | Q6: -1 | R6: 10 | U6: -1 | V6: 10 | BG6: -1 | BH6: 10 | BI6: -1 | BJ6: 10 | ES6: 1
I7: {=IF( SUM(--NOT(ISBLANK(BW7:EP7) ) ),1, "" )} -> 1 | J7: {=IF( SUM(--NOT(ISBLANK(O7:BV7) ) ),1, "" )} | K7: MA | L7: BB Direction | M7: 1 | N7: =IF(ES7="", "", IF(M7>0,M7*ES7,0)) -> 1 | CW7: 1 | CX7: 10 | DK7: 1 | DL7: 10 | DS7: 1 | DT7: 10 | EA7: 0 | EB7: 10 | ES7: 1
A8: BB_Threshold_Crossover | H8: {=IF(AND(A8="",B8=""),"",INDIRECT(ADDRESS($M$3,MATCH(IF(A8="",B8,A8),MA!$A$1:$NP$1,0),1,1,"MA")))} -> 1 | I8: {=IF( SUM(--NOT(ISBLANK(BW8:EP8) ) ),1, "" )} | J8: {=IF( SUM(--NOT(ISBLANK(O8:BV8) ) ),1, "" )} -> 1 | K8: MA | L8: BBThresh Crossover | M8: -1 | N8: =IF(ES8="", "", IF(M8>0,M8*ES8,0)) -> 0 | AE8: -1 | AF8: 10 | AG8: -1 | AH8: 10 | AI8: -1 | AJ8: 10 | AK8: -1 | AL8: 10 | AM8: -1 | AN8: 10 | AQ8: -1 | AR8: 10 | ES8: 1
B9: BBThresh_CO_Days | C9: 4 | D9: 7 | E9: 1 | F9: 2 | G9: 3 | H9: {=IF(AND(A9="",B9=""),"",INDIRECT(ADDRESS($M$3,MATCH(IF(A9="",B9,A9),MA!$A$1:$NP$1,0),1,1,"MA")))} -> 13 | I9: {=IF( SUM(--NOT(ISBLANK(BW9:EP9) ) ),1, "" )} | J9: {=IF( SUM(--NOT(ISBLANK(O9:BV9) ) ),1, "" )} | K9: MA | L9: BBThresh CO Days | M9: 1 | N9: =IF(ES9="", "", IF(M9>0,M9*ES9,0))
A10: BBThresh_CO_Days | B10: BBThresh_CO_Days2 | C10: 2 | D10: 5 | E10: 1 | F10: 2 | G10: 3 | H10: {=IF(AND(A10="",B10=""),"",INDIRECT(ADDRESS($M$3,MATCH(IF(A10="",B10,A10),MA!$A$1:$NP$1,0),1,1,"MA")))} -> 13 | I10: {=IF( SUM(--NOT(ISBLANK(BW10:EP10) ) ),1, "" )} | J10: {=IF( SUM(--NOT(ISBLANK(O10:BV10) ) ),1, "" )} -> 1 | K10: MA | L10: BBThresh CO Days2 | M10: 1 | N10: =IF(ES10="", "", IF(M10>0,M10*ES10,0)) | AQ10: 1 | AR10: 10
I11: {=IF( SUM(--NOT(ISBLANK(BW11:EP11) ) ),1, "" )} -> 1 | J11: {=IF( SUM(--NOT(ISBLANK(O11:BV11) ) ),1, "" )} -> 1 | K11: MA | L11: Trade Cross Over | M11: 1 | N11: =IF(ES11="", "", IF(M11>0,M11*ES11,0)) | U11: -1 | V11: 10 | BG11: -1 | BH11: 10 | DA11: 1 | DB11: 10
B12: Trade_sd | C12: 1 | D12: 5 | E12: 1 | F12: 2 | G12: 3 | H12: {=IF(AND(A12="",B12=""),"",INDIRECT(ADDRESS($M$3,MATCH(IF(A12="",B12,A12),MA!$A$1:$NP$1,0),1,1,"MA")))} -> 4.337963 | I12: {=IF( SUM(--NOT(ISBLANK(BW12:EP12) ) ),1, "" )} -> 1 | J12: {=IF( SUM(--NOT(ISBLANK(O12:BV12) ) ),1, "" )} -> 1 | K12: MA | L12: Trade-Rule | M12: 1 | N12: =IF(ES12="", "", IF(M12>0,M12*ES12,0)) -> 1 | O12: -1 | P12: 10 | Q12: -2 | R12: 10 | W12: -2 | X12: 10 | Y12: 0 | Z12: 10 | AA12: 0 | AB12: 10 | AS12: -1 | AT12: 10 | BW12: 0 | BX12: 10 | BY12: 0 | BZ12: 10 | CA12: 0 | CB12: 10 | CC12: 0 | CD12: 10 | CE12: 0 | CF12: 10 | CI12: 0 | CJ12: 10 | CK12: -1 | CL12: 10 | CM12: 0 | CN12: 10 | CO12: 0 | CP12: 10 | CW12: 2 | CX12: 10 | CY12: 2 | CZ12: 10 | DU12: 0 | DV12: 10 | DW12: 0 | DX12: 10 | DY12: -1 | DZ12: 10 | EA12: -1 | EB12: 10 | EC12: -1 | ED12: 10 | EE12: 0 | EF12: 10 | EO12: 0 | EP12: 10 | ES12: 1
H13: {=IF(AND(A13="",B13=""),"",INDIRECT(ADDRESS($M$3,MATCH(IF(A13="",B13,A13),MA!$A$1:$NP$1,0),1,1,"MA")))} | I13: {=IF( SUM(--NOT(ISBLANK(BW13:EP13) ) ),1, "" )} -> 1 | J13: {=IF( SUM(--NOT(ISBLANK(O13:BV13) ) ),1, "" )} -> 1 | K13: MA | L13: !Trade Rule | M13: 3 | N13: =IF(ES13="", "", IF(M13>0,M13*ES13,0)) | AU13: 0 | AV13: 10 | BA13: 0 | BB13: 10 | CK13: 1 | CL13: 10 | DA13: -1 | DB13: 10 | DC13: 0 | DD13: 10 | DE13: 0 | DF13: 10 | DG13: 0 | DH13: 10 | DI13: 0 | DJ13: 10 | DO13: -1 | DP13: 10
H14: {=IF(AND(A14="",B14=""),"",INDIRECT(ADDRESS($M$3,MATCH(IF(A14="",B14,A14),MA!$A$1:$NP$1,0),1,1,"MA")))} | I14: {=IF( SUM(--NOT(ISBLANK(BW14:EP14) ) ),1, "" )} -> 1 | J14: {=IF( SUM(--NOT(ISBLANK(O14:BV14) ) ),1, "" )} -> 1 | K14: MA | L14: Trend Cross Over | M14: -3 | N14: =IF(ES14="", "", IF(M14>0,M14*ES14,0)) | O14: -1 | P14: 10 | DQ14: 1 | DR14: 10
B15: Trend_sd | C15: 3 | D15: 12 | E15: 1 | F15: 2 | G15: 3 | H15: {=IF(AND(A14="",B15=""),"",INDIRECT(ADDRESS($M$3,MATCH(IF(A14="",B15,A14),MA!$A$1:$NP$1,0),1,1,"MA")))} -> 1.9837963 | I15: {=IF( SUM(--NOT(ISBLANK(BW15:EP15) ) ),1, "" )} -> 1 | J15: {=IF( SUM(--NOT(ISBLANK(O15:BV15) ) ),1, "" )} -> 1 | K15: MA | L15: Trend-Rule | M15: -3 | N15: =IF(ES15="", "", IF(M15>0,M15*ES15,0)) -> 0 | W15: -1 | X15: 10 | AA15: 0 | AB15: 10 | BW15: 2 | BX15: 10 | BY15: 2 | BZ15: 10 | CA15: 2 | CB15: 10 | CC15: 2 | CD15: 10 | CE15: 2 | CF15: 10 | CG15: 2 | CH15: 10 | CI15: 2 | CJ15: 10 | CK15: 2 | CL15: 10 | CM15: 3 | CN15: 10 | CO15: 3 | CP15: 10 | CU15: 2 | CV15: 10 | CW15: 3 | CX15: 10 | CY15: 1 | CZ15: 10 | DC15: 2 | DD15: 10 | DE15: 2 | DF15: 10 | DG15: 2 | DH15: 10 | DI15: 2 | DJ15: 10 | DU15: 2 | DV15: 10 | DW15: 2 | DX15: 10 | DY15: 2 | DZ15: 10 | EA15: 2 | EB15: 10 | EC15: 2 | ED15: 10 | EE15: 2 | EF15: 10 | EO15: 1 | EP15: 10 | ES15: 1
H16: {=IF(AND(A16="",B16=""),"",INDIRECT(ADDRESS($M$3,MATCH(IF(A16="",B16,A16),MA!$A$1:$NP$1,0),1,1,"MA")))} | I16: {=IF( SUM(--NOT(ISBLANK(BW16:EP16) ) ),1, "" )} -> 1 | J16: {=IF( SUM(--NOT(ISBLANK(O16:BV16) ) ),1, "" )} -> 1 | K16: MA | L16: !Trend Rule | M16: 1 | N16: =IF(ES16="", "", IF(M16>0,M16*ES16,0)) | AS16: -1 | AT16: 10 | DO16: 0 | DP16: 10
H17: {=IF(AND(A17="",B17=""),"",INDIRECT(ADDRESS($M$3,MATCH(IF(A17="",B17,A17),MA!$A$1:$NP$1,0),1,1,"MA")))} | I17: {=IF( SUM(--NOT(ISBLANK(BW17:EP17) ) ),1, "" )} | J17: {=IF( SUM(--NOT(ISBLANK(O17:BV17) ) ),1, "" )} | K17: MA | L17: Trend Trade Dep Rule | M17: 1 | N17: =IF(ES17="", "", IF(M17>0,M17*ES17,0))
H18: {=IF(AND(A18="",B18=""),"",INDIRECT(ADDRESS($M$3,MATCH(IF(A18="",B18,A18),MA!$A$1:$NP$1,0),1,1,"MA")))} | I18: {=IF( SUM(--NOT(ISBLANK(BW18:EP18) ) ),1, "" )} | J18: {=IF( SUM(--NOT(ISBLANK(O18:BV18) ) ),1, "" )} -> 1 | K18: MA | L18: Trade Trend Relation | M18: 1 | N18: =IF(ES18="", "", IF(M18>0,M18*ES18,0)) | U18: -1 | V18: 10
H19: {=IF(AND(A19="",B19=""),"",INDIRECT(ADDRESS($M$3,MATCH(IF(A19="",B19,A19),MA!$A$1:$NP$1,0),1,1,"MA")))} | I19: {=IF( SUM(--NOT(ISBLANK(BW19:EP19) ) ),1, "" )} -> 1 | J19: {=IF( SUM(--NOT(ISBLANK(O19:BV19) ) ),1, "" )} -> 1 | K19: MA | L19: !Trade Trend Relation | M19: -1 | N19: =IF(ES19="", "", IF(M19>0,M19*ES19,0)) | BG19: -1 | BH19: 10 | DM19: 0 | DN19: 10
B20: Trade_Trend_Sd | C20: 3 | D20: 12 | E20: 1 | F20: 2 | G20: 3 | H20: {=IF(AND(A20="",B20=""),"",INDIRECT(ADDRESS($M$3,MATCH(IF(A20="",B20,A20),MA!$A$1:$NP$1,0),1,1,"MA")))} -> -2.3541667 | I20: {=IF( SUM(--NOT(ISBLANK(BW20:EP20) ) ),1, "" )} | J20: {=IF( SUM(--NOT(ISBLANK(O20:BV20) ) ),1, "" )} | K20: MA | L20: Trade Trend SD Rule | M20: 0 | N20: =IF(ES20="", "", IF(M20>0,M20*ES20,0))
A21: BRR% | B21: BRR% Rule | C21: 60 | D21: 75 | E21: 3 | F21: 2 | G21: 1 | H21: {=IF(AND(A21="",B21=""),"",INDIRECT(ADDRESS($M$3,MATCH(IF(A21="",B21,A21),MA!$A$1:$NP$1,0),1,1,"MA")))} | I21: {=IF( SUM(--NOT(ISBLANK(BW21:EP21) ) ),1, "" )} -> 1 | J21: {=IF( SUM(--NOT(ISBLANK(O21:BV21) ) ),1, "" )} | K21: MA | L21: BRR% Rule | M21: 1 | N21: =IF(ES21="", "", IF(M21>0,M21*ES21,0)) -> 1 | DA21: 3 | DB21: 10 | DK21: 3 | DL21: 10 | DM21: 3 | DN21: 10 | DO21: 3 | DP21: 10 | DQ21: 3 | DR21: 1 | DS21: 3 | DT21: 10 | EC21: 3 | ED21: 10 | ES21: 1
A22: BRR% | B22: BRR% LRR | C22: 35 | D22: 75 | E22: 3 | F22: 2 | G22: 1 | H22: {=IF(AND(A22="",B22=""),"",INDIRECT(ADDRESS($M$3,MATCH(IF(A22="",B22,A22),MA!$A$1:$NP$1,0),1,1,"MA")))} | I22: {=IF( SUM(--NOT(ISBLANK(BW22:EP22) ) ),1, "" )} -> 1 | J22: {=IF( SUM(--NOT(ISBLANK(O22:BV22) ) ),1, "" )} -> 1 | K22: MA | L22: BRR% LRR | M22: 1 | N22: =IF(ES22="", "", IF(M22>0,M22*ES22,0)) | W22: 2 | X22: 10 | AA22: 2 | AB22: 10 | AO22: 2 | AP22: 10 | AS22: 2 | AT22: 10 | AY22: 1 | AZ22: 10 | BY22: 3 | BZ22: 10 | CE22: 3 | CF22: 10 | CG22: 3 | CH22: 10 | CI22: 3 | CJ22: 10 | CK22: 3 | CL22: 10 | DU22: 3 | DV22: 10
A23: BRR% | B23: BRR% R2 | C23: 25 | D23: 75 | E23: 3 | F23: 2 | G23: 1 | H23: {=IF(AND(A23="",B23=""),"",INDIRECT(ADDRESS($M$3,MATCH(IF(A23="",B23,A23),MA!$A$1:$NP$1,0),1,1,"MA")))} | K23: MA | L23: BRR% R2 | M23: 1 | EM23: 3 | EN23: 10
A24: BRR% | B24: BRR% LRR2 | C24: 50 | D24: 75 | E24: 3 | F24: 2 | G24: 1 | H24: {=IF(AND(A24="",B24=""),"",INDIRECT(ADDRESS($M$3,MATCH(IF(A24="",B24,A24),MA!$A$1:$NP$1,0),1,1,"MA")))} | I24: {=IF( SUM(--NOT(ISBLANK(BW24:EP24) ) ),1, "" )} -> 1 | J24: {=IF( SUM(--NOT(ISBLANK(O24:BV24) ) ),1, "" )} | K24: MA | L24: BRR% LRR2 | M24: 1 | DI24: 3 | DJ24: 10
A25: BRR% | B25: BRR% TRR | C25: 50 | D25: 83 | E25: 1 | F25: 2 | G25: 3 | H25: {=IF(AND(A25="",B25=""),"",INDIRECT(ADDRESS($M$3,MATCH(IF(A25="",B25,A25),MA!$A$1:$NP$1,0),1,1,"MA")))} | I25: {=IF( SUM(--NOT(ISBLANK(BW25:EP25) ) ),1, "" )} -> 1 | J25: {=IF( SUM(--NOT(ISBLANK(O25:BV25) ) ),1, "" )} | K25: MA | L25: BRR% TRR | M25: 1 | N25: =IF(ES25="", "", IF(M25>0,M25*ES25,0)) | CW25: 2 | CX25: 10 | CY25: 2 | CZ25: 10
A26: BRR% | B26: BRR% Puts | C26: 55 | D26: 80 | E26: -1 | F26: -2 | G26: -3 | H26: {=IF(AND(A26="",B26=""),"",INDIRECT(ADDRESS($M$3,MATCH(IF(A26="",B26,A26),MA!$A$1:$NP$1,0),1,1,"MA")))} | I26: {=IF( SUM(--NOT(ISBLANK(BW26:EP26) ) ),1, "" )} -> 1 | J26: {=IF( SUM(--NOT(ISBLANK(O26:BV26) ) ),1, "" )} | K26: MA | L26: BRR% Puts | M26: 1 | N26: =IF(ES26="", "", IF(M26>0,M26*ES26,0)) | DC26: -1 | DD26: 10 | DE26: -1 | DF26: 10 | DG26: -1 | DH26: 10
A27: BRR% | B27: BRR% TRR Puts | C27: 45 | D27: 83 | E27: -1 | F27: -2 | G27: -3 | H27: {=IF(AND(A27="",B27=""),"",INDIRECT(ADDRESS($M$3,MATCH(IF(A27="",B27,A27),MA!$A$1:$NP$1,0),1,1,"MA")))} | I27: {=IF( SUM(--NOT(ISBLANK(BW27:EP27) ) ),1, "" )} -> 1 | J27: {=IF( SUM(--NOT(ISBLANK(O27:BV27) ) ),1, "" )} -> 1 | K27: MA | L27: BRR% TRR Puts | M27: -3 | N27: =IF(ES27="", "", IF(M27>0,M27*ES27,0)) | Y27: -3 | Z27: 10 | AC27: -3 | AD27: 10 | AU27: -3 | AV27: 10 | BA27: -3 | BB27: 10 | BC27: -2 | BD27: 10 | BE27: -3 | BF27: 10 | BO27: -3 | BP27: 10 | BW27: -1 | BX27: 10 | CA27: -1 | CB27: 10 | CC27: -1 | CD27: 10
H28: {=IF(AND(A28="",B28=""),"",INDIRECT(ADDRESS($M$3,MATCH(IF(A28="",B28,A28),MA!$A$1:$NP$1,0),1,1,"MA")))} | I28: {=IF( SUM(--NOT(ISBLANK(BW28:EP28) ) ),1, "" )} | J28: {=IF( SUM(--NOT(ISBLANK(O28:BV28) ) ),1, "" )} | K28: MA | L28: BRR% Dir Rule | M28: 1 | N28: =IF(ES28="", "", IF(M28>0,M28*ES28,0))
B29: High TRR | C29: 0 | D29: 2 | E29: 1 | F29: 2 | G29: 3 | H29: {=IF(AND(A29="",B29=""),"",INDIRECT(ADDRESS($M$3,MATCH(IF(A29="",B29,A29),MA!$A$1:$NP$1,0),1,1,"MA")))} -> -22.340278 | I29: {=IF( SUM(--NOT(ISBLANK(BW29:EP29) ) ),1, "" )} | J29: {=IF( SUM(--NOT(ISBLANK(O29:BV29) ) ),1, "" )} -> 1 | K29: MA | L29: High above TRR | M29: -2 | N29: =IF(ES29="", "", IF(M29>0,M29*ES29,0)) | AW29: 1 | AX29: 10 | BS29: 1 | BT29: 10
B30: Low LRR | C30: 0 | D30: 2 | E30: 3 | F30: 2 | G30: 1 | H30: {=IF(AND(A30="",B30=""),"",INDIRECT(ADDRESS($M$3,MATCH(IF(A30="",B30,A30),MA!$A$1:$NP$1,0),1,1,"MA")))} -> 21.069444 | I30: {=IF( SUM(--NOT(ISBLANK(BW30:EP30) ) ),1, "" )} -> 1 | J30: {=IF( SUM(--NOT(ISBLANK(O30:BV30) ) ),1, "" )} | K30: MA | L30: Low below LRR | M30: 1 | N30: =IF(ES30="", "", IF(M30>0,M30*ES30,0)) | EA30: 3 | EB30: 10
H31: {=IF(AND(A31="",B31=""),"",INDIRECT(ADDRESS($M$3,MATCH(IF(A31="",B31,A31),MA!$A$1:$NP$1,0),1,1,"MA")))} | I31: {=IF( SUM(--NOT(ISBLANK(BW31:EP31) ) ),1, "" )} | J31: {=IF( SUM(--NOT(ISBLANK(O31:BV31) ) ),1, "" )} -> 1 | K31: MA | L31: Trend below TRR | M31: -3 | N31: =IF(ES31="", "", IF(M31>0,M31*ES31,0)) | AA31: -1 | AB31: 10
H32: {=IF(AND(A32="",B32=""),"",INDIRECT(ADDRESS($M$3,MATCH(IF(A32="",B32,A32),MA!$A$1:$NP$1,0),1,1,"MA")))} | I32: {=IF( SUM(--NOT(ISBLANK(BW32:EP32) ) ),1, "" )} -> 1 | J32: {=IF( SUM(--NOT(ISBLANK(O32:BV32) ) ),1, "" )} -> 1 | K32: MA | L32: LRR above Trade | M32: 1 | N32: =IF(ES32="", "", IF(M32>0,M32*ES32,0)) | BA32: 0 | BB32: 10 | BW32: 1 | BX32: 10 | BY32: 1 | BZ32: 10 | DU32: 1 | DV32: 10 | DW32: 1 | DX32: 10 | EE32: 1 | EF32: 10
A33: Sd TRR | B33: TRR_Idx | C33: -0.25 | D33: 1 | E33: -1 | F33: 0 | G33: 1 | H33: {=IF(AND(A33="",B33=""),"",INDIRECT(ADDRESS($M$3,MATCH(IF(A33="",B33,A33),MA!$A$1:$NP$1,0),1,1,"MA")))} -> 22.340278 | I33: {=IF( SUM(--NOT(ISBLANK(BW33:EP33) ) ),1, "" )} | J33: {=IF( SUM(--NOT(ISBLANK(O33:BV33) ) ),1, "" )} | K33: MA | L33: TRR_Idx | M33: 2
A34: Sd MRR | B34: MRR_Idx | C34: -0.25 | D34: 0.25 | E34: -1 | F34: 0 | G34: 1 | H34: {=IF(AND(A34="",B34=""),"",INDIRECT(ADDRESS($M$3,MATCH(IF(A34="",B34,A34),MA!$A$1:$NP$1,0),1,1,"MA")))} -> 22.166667 | I34: {=IF( SUM(--NOT(ISBLANK(BW34:EP34) ) ),1, "" )} | J34: {=IF( SUM(--NOT(ISBLANK(O34:BV34) ) ),1, "" )} | K34: MA | L34: MRR_Idx | M34: 2
A35: Sd LRR | B35: LRR_Idx | C35: -0.25 | D35: 1 | E35: -1 | F35: 0 | G35: 1 | H35: {=IF(AND(A35="",B35=""),"",INDIRECT(ADDRESS($M$3,MATCH(IF(A35="",B35,A35),MA!$A$1:$NP$1,0),1,1,"MA")))} -> 21.069444 | I35: {=IF( SUM(--NOT(ISBLANK(BW35:EP35) ) ),1, "" )} | J35: {=IF( SUM(--NOT(ISBLANK(O35:BV35) ) ),1, "" )} | K35: MA | L35: LRR_Idx | M35: -2
A36: HistoricalVolatility | B36: HVAbsolute | C36: 0.12 | D36: 0.4 | E36: 2 | F36: 3 | G36: 1 | H36: {=IF(AND(A36="",B36=""),"",INDIRECT(ADDRESS($M$3,MATCH(IF(A36="",B36,A36),MA!$A$1:$NP$1,0),1,1,"MA")))} -> #N/A | I36: {=IF( SUM(--NOT(ISBLANK(BW36:EP36) ) ),1, "" )} | J36: {=IF( SUM(--NOT(ISBLANK(O36:BV36) ) ),1, "" )} | K36: MA | L36: HVAbsolute | M36: 3
A37: ImpVolatility | B37: IVAbsolute | C37: 0.2 | D37: 0.4 | E37: 3 | F37: 2 | G37: 1 | H37: {=IF(AND(A37="",B37=""),"",INDIRECT(ADDRESS($M$3,MATCH(IF(A37="",B37,A37),MA!$A$1:$NP$1,0),1,1,"MA")))} -> 0.59 | I37: {=IF( SUM(--NOT(ISBLANK(BW37:EP37) ) ),1, "" )} | J37: {=IF( SUM(--NOT(ISBLANK(O37:BV37) ) ),1, "" )} | K37: MA | L37: IVAbsolute | M37: 3
A38: IVPercentile | B38: IVPercentile | C38: 25 | D38: 70 | E38: 3 | F38: 2 | G38: 1 | H38: {=IF(AND(A38="",B38=""),"",INDIRECT(ADDRESS($M$3,MATCH(IF(A38="",B38,A38),MA!$A$1:$NP$1,0),1,1,"MA")))} -> 96.4 | I38: {=IF( SUM(--NOT(ISBLANK(BW38:EP38) ) ),1, "" )} -> 1 | J38: {=IF( SUM(--NOT(ISBLANK(O38:BV38) ) ),1, "" )} | K38: MA | L38: IVPercentile | M38: -3 | N38: =IF(ES38="", "", IF(M38>0,M38*ES38,0)) -> 0 | DY38: 3 | DZ38: 10 | EC38: 2 | ED38: 1 | ES38: 1
A39: IVPercentile | B39: IVPercentile Puts | C39: 35 | D39: 90 | E39: -1 | F39: -2 | G39: -3 | H39: {=IF(AND(A39="",B39=""),"",INDIRECT(ADDRESS($M$3,MATCH(IF(A39="",B39,A39),MA!$A$1:$NP$1,0),1,1,"MA")))} -> 96.4 | I39: {=IF( SUM(--NOT(ISBLANK(BW39:EP39) ) ),1, "" )} -> 1 | J39: {=IF( SUM(--NOT(ISBLANK(O39:BV39) ) ),1, "" )} -> 1 | K39: MA | L39: IVPercentile Puts | M39: 1 | N39: =IF(ES39="", "", IF(M39>0,M39*ES39,0)) | AC39: -3 | AD39: 10 | AE39: -3 | AF39: 10 | AG39: -3 | AH39: 10 | AI39: -3 | AJ39: 10 | AK39: -3 | AL39: 10 | AU39: -3 | AV39: 10 | AY39: -2 | AZ39: 10 | BE39: -3 | BF39: 10 | DU39: -1 | DV39: 10 | DW39: -1 | DX39: 10
A40: HVPercentile | B40: HVPercentile | C40: 25 | D40: 70 | E40: 3 | F40: 2 | G40: 1 | H40: {=IF(AND(A40="",B40=""),"",INDIRECT(ADDRESS($M$3,MATCH(IF(A40="",B40,A40),MA!$A$1:$NP$1,0),1,1,"MA")))} -> 74.1 | I40: {=IF( SUM(--NOT(ISBLANK(BW40:EP40) ) ),1, "" )} -> 1 | J40: {=IF( SUM(--NOT(ISBLANK(O40:BV40) ) ),1, "" )} | K40: MA | L40: HVPercentile | M40: 2 | N40: =IF(ES40="", "", IF(M40>0,M40*ES40,0)) -> 2 | DY40: 3 | DZ40: 10 | EC40: 2 | ED40: 1 | ES40: 1
A41: HVPercentile | B41: HVPercentile Puts | C41: 35 | D41: 90 | E41: -1 | F41: -2 | G41: -3 | H41: {=IF(AND(A41="",B41=""),"",INDIRECT(ADDRESS($M$3,MATCH(IF(A41="",B41,A41),MA!$A$1:$NP$1,0),1,1,"MA")))} -> 74.1 | I41: {=IF( SUM(--NOT(ISBLANK(BW41:EP41) ) ),1, "" )} -> 1 | J41: {=IF( SUM(--NOT(ISBLANK(O41:BV41) ) ),1, "" )} -> 1 | K41: MA | L41: HVPercentile Puts | M41: 1 | N41: =IF(ES41="", "", IF(M41>0,M41*ES41,0)) | AC41: -3 | AD41: 10 | AE41: -3 | AF41: 10 | AG41: -3 | AH41: 10 | AI41: -3 | AJ41: 10 | AK41: -3 | AL41: 10 | AU41: -3 | AV41: 10 | AY41: -2 | AZ41: 10 | BE41: -3 | BF41: 10 | DU41: -1 | DV41: 10 | DW41: -1 | DX41: 10
B42: IVHV | C42: 100 | D42: 125 | E42: 3 | F42: 2 | G42: 1 | H42: {=IF(AND(A42="",B42=""),"",INDIRECT(ADDRESS($M$3,MATCH(IF(A42="",B42,A42),MA!$A$1:$NP$1,0),1,1,"MA")))} -> 128.26087 | I42: {=IF( SUM(--NOT(ISBLANK(BW42:EP42) ) ),1, "" )} -> 1 | J42: {=IF( SUM(--NOT(ISBLANK(O42:BV42) ) ),1, "" )} | K42: MA | L42: IVHV Rule (modified) | M42: 2 | N42: =IF(ES42="", "", IF(M42>0,M42*ES42,0)) -> 2 | BW42: 3 | BX42: 1 | CA42: 3 | CB42: 1 | CC42: 3 | CD42: 1 | CE42: 3 | CF42: 1 | CM42: 3 | CN42: 1 | CO42: 3 | CP42: 1 | CQ42: 3 | CR42: 1 | CS42: 3 | CT42: 1 | CU42: 3 | CV42: 1 | CW42: 3 | CX42: 1 | CY42: 3 | CZ42: 1 | DA42: 3 | DB42: 1 | DC42: 3 | DD42: 1 | DE42: 3 | DF42: 1 | DG42: 3 | DH42: 1 | DI42: 3 | DJ42: 1 | DK42: 3 | DL42: 1 | DM42: 3 | DN42: 1 | DO42: 3 | DP42: 1 | DQ42: 3 | DR42: 1 | DS42: 3 | DT42: 1 | DW42: 3 | DX42: 10 | DY42: 3 | DZ42: 10 | EC42: 3 | ED42: 1 | EI42: 2 | EJ42: 10 | ES42: 1
A43: IVHV | B43: IVHV Puts | C43: 100 | D43: 125 | E43: -1 | F43: -2 | G43: -3 | H43: {=IF(AND(A43="",B43=""),"",INDIRECT(ADDRESS($M$3,MATCH(IF(A43="",B43,A43),MA!$A$1:$NP$1,0),1,1,"MA")))} -> 128.26087 | I43: {=IF( SUM(--NOT(ISBLANK(BW43:EP43) ) ),1, "" )} | J43: {=IF( SUM(--NOT(ISBLANK(O43:BV43) ) ),1, "" )} -> 1 | K43: MA | L43: IVHV Puts (modified) | M43: 3 | N43: =IF(ES43="", "", IF(M43>0,M43*ES43,0)) -> 3 | AC43: -2 | AD43: 10 | AE43: -2 | AF43: 10 | AI43: -2 | AJ43: 10 | AU43: -2 | AV43: 10 | ES43: 1
K44: MA | L44: IVRule | M44: 2 | BW44: 0 | BX44: 1 | CA44: 0 | CB44: 1 | CC44: 0 | CD44: 1 | CE44: 0 | CF44: 10 | CM44: 0 | CN44: 1 | CO44: 0 | CP44: 1 | CQ44: 0 | CR44: 1 | CS44: 0 | CT44: 1 | CU44: 0 | CV44: 10 | CW44: 0 | CX44: 10 | CY44: 0 | CZ44: 1 | DA44: 0 | DB44: 10 | DC44: 0 | DD44: 1 | DE44: 0 | DF44: 1 | DG44: 0 | DH44: 1 | DI44: 0 | DJ44: 1 | DK44: 0 | DL44: 1 | DM44: 0 | DN44: 1 | DO44: 0 | DP44: 1 | DQ44: 0 | DR44: 10 | DS44: 0 | DT44: 1 | EI44: 0 | EJ44: 10
B45: RSI | C45: 45 | D45: 70 | E45: 3 | F45: 2 | G45: 1 | H45: {=IF(AND(A45="",B45=""),"",INDIRECT(ADDRESS($M$3,MATCH(IF(A45="",B45,A45),MA!$A$1:$NP$1,0),1,1,"MA")))} -> 69.17 | I45: {=IF( SUM(--NOT(ISBLANK(BW45:EP45) ) ),1, "" )} -> 1 | J45: {=IF( SUM(--NOT(ISBLANK(O45:BV45) ) ),1, "" )} -> 1 | K45: MA | L45: RSI Rule | M45: 2 | N45: =IF(ES45="", "", IF(M45>0,M45*ES45,0)) -> 2 | BM45: 1 | BN45: 10 | BW45: 2 | BX45: 1 | BY45: 2 | BZ45: 10 | CA45: 2 | CB45: 1 | CC45: 2 | CD45: 1 | CE45: 2 | CF45: 10 | CI45: 2 | CJ45: 10 | CK45: 2 | CL45: 10 | DC45: 2 | DD45: 1 | DE45: 2 | DF45: 1 | DG45: 2 | DH45: 1 | DI45: 2 | DJ45: 1 | DS45: 2 | DT45: 10 | EC45: 2 | ED45: 1 | EG45: 2 | EH45: 10 | EK45: 2 | EL45: 10 | ES45: 1
A46: RSI | B46: RSI Top | C46: 65 | D46: 80 | E46: 1 | F46: 2 | G46: 3 | H46: {=IF(AND(A46="",B46=""),"",INDIRECT(ADDRESS($M$3,MATCH(IF(A46="",B46,A46),MA!$A$1:$NP$1,0),1,1,"MA")))} -> 69.17 | I46: {=IF( SUM(--NOT(ISBLANK(BW46:EP46) ) ),1, "" )} | J46: {=IF( SUM(--NOT(ISBLANK(O46:BV46) ) ),1, "" )} | K46: MA | L46: RSI Top | M46: 2 | N46: =IF(ES46="", "", IF(M46>0,M46*ES46,0))
A47: RSI | B47: RSI Puts | C47: 60 | D47: 75 | E47: -1 | F47: -2 | G47: -3 | H47: {=IF(AND(A47="",B47=""),"",INDIRECT(ADDRESS($M$3,MATCH(IF(A47="",B47,A47),MA!$A$1:$NP$1,0),1,1,"MA")))} -> 69.17 | I47: {=IF( SUM(--NOT(ISBLANK(BW47:EP47) ) ),1, "" )} -> 1 | J47: {=IF( SUM(--NOT(ISBLANK(O47:BV47) ) ),1, "" )} -> 1 | K47: MA | L47: RSI Puts | M47: -2 | N47: =IF(ES47="", "", IF(M47>0,M47*ES47,0)) | AC47: -3 | AD47: 10 | AE47: -3 | AF47: 10 | AG47: -3 | AH47: 10 | AI47: -3 | AJ47: 10 | AK47: -3 | AL47: 10 | AM47: -3 | AN47: 10 | AU47: -3 | AV47: 10 | AY47: -3 | AZ47: 10 | BE47: -3 | BF47: 10 | CM47: -2 | CN47: 10 | CO47: -2 | CP47: 10 | CQ47: -2 | CR47: 10 | CS47: -2 | CT47: 10 | CW47: -2 | CX47: 10 | CY47: -2 | CZ47: 10 | DA47: -2 | DB47: 10 | DK47: -2 | DL47: 1 | DM47: -2 | DN47: 10 | DO47: -2 | DP47: 1 | DQ47: -2 | DR47: 10 | DU47: -1 | DV47: 10 | DW47: -1 | DX47: 10 | DY47: -1 | DZ47: 10
B48: 3mnLow_sd | C48: 3 | D48: 5 | E48: 1 | F48: 2 | G48: 3 | H48: {=IF(AND(A48="",B48=""),"",INDIRECT(ADDRESS($M$3,MATCH(IF(A48="",B48,A48),MA!$A$1:$NP$1,0),1,1,"MA")))} -> 5.6388889 | I48: {=IF( SUM(--NOT(ISBLANK(BW48:EP48) ) ),1, "" )} -> 1 | J48: {=IF( SUM(--NOT(ISBLANK(O48:BV48) ) ),1, "" )} | K48: MA | L48: 3m-Low-Rule | M48: 3 | N48: =IF(ES48="", "", IF(M48>0,M48*ES48,0)) -> 3 | CM48: 3 | CN48: 1 | CO48: 3 | CP48: 10 | CQ48: 3 | CR48: 1 | CS48: 3 | CT48: 10 | CW48: 3 | CX48: 10 | CY48: 3 | CZ48: 10 | ES48: 1
B49: 3mnLowDays | C49: 20 | D49: 35 | E49: 1 | F49: 2 | G49: 3 | H49: {=IF(AND(A49="",B49=""),"",INDIRECT(ADDRESS($M$3,MATCH(IF(A49="",B49,A49),MA!$A$1:$NP$1,0),1,1,"MA")))} -> 40 | I49: {=IF( SUM(--NOT(ISBLANK(BW49:EP49) ) ),1, "" )} | J49: {=IF( SUM(--NOT(ISBLANK(O49:BV49) ) ),1, "" )} | K49: MA | L49: 3m-Low-Days Rule | M49: 1 | N49: =IF(ES49="", "", IF(M49>0,M49*ES49,0))
B50: 3mnHigh_sd | C50: 2 | D50: 5 | E50: 3 | F50: 2 | G50: 1 | H50: {=IF(AND(A50="",B50=""),"",INDIRECT(ADDRESS($M$3,MATCH(IF(A50="",B50,A50),MA!$A$1:$NP$1,0),1,1,"MA")))} -> -0.41203704 | I50: {=IF( SUM(--NOT(ISBLANK(BW50:EP50) ) ),1, "" )} | J50: {=IF( SUM(--NOT(ISBLANK(O50:BV50) ) ),1, "" )} -> 1 | K50: MA | L50: 3mn-High-Rule | M50: -1 | N50: =IF(ES50="", "", IF(M50>0,M50*ES50,0)) | BM50: -3 | BN50: 10
B51: 3mnHighDays | C51: 6 | D51: 15 | E51: 3 | F51: 2 | G51: 1 | H51: {=IF(AND(A51="",B51=""),"",INDIRECT(ADDRESS($M$3,MATCH(IF(A51="",B51,A51),MA!$A$1:$NP$1,0),1,1,"MA")))} -> 54 | I51: {=IF( SUM(--NOT(ISBLANK(BW51:EP51) ) ),1, "" )} | J51: {=IF( SUM(--NOT(ISBLANK(O51:BV51) ) ),1, "" )} -> 1 | K51: MA | L51: 3mn-High-Dyas Rule | M51: -2 | N51: =IF(ES51="", "", IF(M51>0,M51*ES51,0)) | BM51: 2 | BN51: 10
H52: {=IF(AND(A52="",B52=""),"",INDIRECT(ADDRESS($M$3,MATCH(IF(A52="",B52,A52),MA!$A$1:$NP$1,0),1,1,"MA")))} | I52: {=IF( SUM(--NOT(ISBLANK(BW52:EP52) ) ),1, "" )} | J52: {=IF( SUM(--NOT(ISBLANK(O52:BV52) ) ),1, "" )} | K52: MA | L52: 3mn Long Rule | M52: -1 | N52: =IF(ES52="", "", IF(M52>0,M52*ES52,0))
B53: Perf3M_sd | C53: 4 | D53: 12 | E53: 1 | F53: 2 | G53: 3 | H53: {=IF(AND(A53="",B53=""),"",INDIRECT(ADDRESS($M$3,MATCH(IF(A53="",B53,A53),MA!$A$1:$NP$1,0),1,1,"MA")))} -> 1.9837963 | I53: {=IF( SUM(--NOT(ISBLANK(BW53:EP53) ) ),1, "" )} | J53: {=IF( SUM(--NOT(ISBLANK(O53:BV53) ) ),1, "" )} | K53: MA | L53: Perf3mn SD Rule | M53: 1 | N53: =IF(ES53="", "", IF(M53>0,M53*ES53,0)) -> 1 | ES53: 1
B54: Perf2M_sd | C54: 3 | D54: 8 | E54: 1 | F54: 2 | G54: 3 | H54: {=IF(AND(A54="",B54=""),"",INDIRECT(ADDRESS($M$3,MATCH(IF(A54="",B54,A54),MA!$A$1:$NP$1,0),1,1,"MA")))} -> 6.5413833 | I54: {=IF( SUM(--NOT(ISBLANK(BW54:EP54) ) ),1, "" )} | J54: {=IF( SUM(--NOT(ISBLANK(O54:BV54) ) ),1, "" )} | K54: MA | L54: Perf2M SD Rule | M54: 3 | N54: =IF(ES54="", "", IF(M54>0,M54*ES54,0)) -> 3 | ES54: 1
B55: Perf3W_sd | C55: 2 | D55: 3 | E55: 1 | F55: 2 | G55: 3 | H55: {=IF(AND(A55="",B55=""),"",INDIRECT(ADDRESS($M$3,MATCH(IF(A55="",B55,A55),MA!$A$1:$NP$1,0),1,1,"MA")))} -> 4.337963 | I55: {=IF( SUM(--NOT(ISBLANK(BW55:EP55) ) ),1, "" )} | J55: {=IF( SUM(--NOT(ISBLANK(O55:BV55) ) ),1, "" )} -> 1 | K55: MA | L55: Perf3wk SD Rule | M55: 1 | N55: =IF(ES55="", "", IF(M55>0,M55*ES55,0)) -> 1 | BI55: -2 | BJ55: 10 | ES55: 1
B56: Perf2Wk_sd | C56: 1 | D56: 2 | E56: 1 | F56: 2 | G56: 3 | H56: {=IF(AND(A56="",B56=""),"",INDIRECT(ADDRESS($M$3,MATCH(IF(A56="",B56,A56),MA!$A$1:$NP$1,0),1,1,"MA")))} -> 1.6758 | I56: {=IF( SUM(--NOT(ISBLANK(BW56:EP56) ) ),1, "" )} -> 1 | J56: {=IF( SUM(--NOT(ISBLANK(O56:BV56) ) ),1, "" )} | K56: MA | L56: Perf2wk SD Rule | M56: -3 | N56: =IF(ES56="", "", IF(M56>0,M56*ES56,0)) -> 0 | DO56: 3 | DP56: 10 | DQ56: 3 | DR56: 10 | ES56: 1
A57: Perf3D_sd | B57: Perf3D_sd | C57: 0.5 | D57: 1 | E57: 1 | F57: 2 | G57: 3 | H57: {=IF(AND(A57="",B57=""),"",INDIRECT(ADDRESS($M$3,MATCH(IF(A57="",B57,A57),MA!$A$1:$NP$1,0),1,1,"MA")))} -> 0.89775 | I57: {=IF( SUM(--NOT(ISBLANK(BW57:EP57) ) ),1, "" )} -> 1 | J57: {=IF( SUM(--NOT(ISBLANK(O57:BV57) ) ),1, "" )} -> 1 | K57: MA | L57: Perf3D SD Rule | M57: 3 | N57: =IF(ES57="", "", IF(M57>0,M57*ES57,0)) -> 3 | Q57: -2 | R57: 10 | W57: 1 | X57: 10 | AO57: 1 | AP57: 10 | AS57: 1 | AT57: 10 | BC57: -1 | BD57: 10 | BI57: -2 | BJ57: 10 | CC57: 2 | CD57: 10 | DC57: 2 | DD57: 10 | DG57: 2 | DH57: 10 | DM57: 2 | DN57: 10 | DO57: 2 | DP57: 10 | DQ57: 2 | DR57: 10 | DS57: 1 | DT57: 10 | ES57: 1
A58: Perf1D_sd | B58: Perf1D_sd | C58: 1 | D58: 2 | E58: 1 | F58: 2 | G58: 3 | H58: {=IF(AND(A58="",B58=""),"",INDIRECT(ADDRESS($M$3,MATCH(IF(A58="",B58,A58),MA!$A$1:$NP$1,0),1,1,"MA")))} -> 1.0694444 | I58: {=IF( SUM(--NOT(ISBLANK(BW58:EP58) ) ),1, "" )} -> 1 | J58: {=IF( SUM(--NOT(ISBLANK(O58:BV58) ) ),1, "" )} -> 1 | K58: MA | L58: Perf1D SD Rule | M58: 1 | N58: =IF(ES58="", "", IF(M58>0,M58*ES58,0)) -> 1 | W58: -1 | X58: 10 | AO58: -1 | AP58: 10 | AS58: -1 | AT58: 10 | BC58: -1 | BD58: 10 | BG58: 0 | BH58: 10 | BW58: 0 | BX58: 10 | CA58: 0 | CB58: 10 | CC58: 0 | CD58: 10 | DA58: 1 | DB58: 10 | DC58: 0 | DD58: 10 | DE58: 0 | DF58: 10 | DG58: 0 | DH58: 10 | DM58: 1 | DN58: 1 | DO58: 1 | DP58: 10 | DQ58: 1 | DR58: 10 | EC58: 0 | ED58: 10 | ES58: 1
I59: {=IF( SUM(--NOT(ISBLANK(BW59:EP59) ) ),1, "" )} | J59: {=IF( SUM(--NOT(ISBLANK(O59:BV59) ) ),1, "" )} -> 1 | K59: MA | L59: !Perf1D SD Rule | M59: 3 | N59: =IF(ES59="", "", IF(M59>0,M59*ES59,0)) -> 3 | Y59: -1 | Z59: 10 | AA59: -1 | AB59: 10 | AO59: 0 | AP59: 10 | AU59: -1 | AV59: 10 | BA59: -1 | BB59: 10 | BM59: -1 | BN59: 10 | ES59: 1
A60: Perf3D_sd | B60: Perf3D_sd_1off | C60: 5 | D60: 7 | E60: 3 | F60: 2 | G60: 1 | H60: {=IF(AND(A60="",B60=""),"",INDIRECT(ADDRESS($M$3,MATCH(IF(A60="",B60,A60),MA!$A$1:$NP$1,0),1,1,"MA")))} -> 0.89775 | I60: {=IF( SUM(--NOT(ISBLANK(BW60:EP60) ) ),1, "" )} -> 1 | J60: {=IF( SUM(--NOT(ISBLANK(O60:BV60) ) ),1, "" )} | K60: MA | L60: Perf3D 1Off Rule | M60: 1 | N60: =IF(ES60="", "", IF(M60>0,M60*ES60,0)) -> 1 | BW60: 3 | BX60: 10 | BY60: 3 | BZ60: 10 | CA60: 3 | CB60: 10 | CC60: 3 | CD60: 10 | CE60: 3 | CF60: 10 | CG60: 3 | CH60: 10 | CI60: 3 | CJ60: 10 | CK60: 3 | CL60: 10 | CM60: 3 | CN60: 10 | CO60: 3 | CP60: 10 | CQ60: 3 | CR60: 10 | CS60: 3 | CT60: 10 | CU60: 3 | CV60: 10 | CW60: 3 | CX60: 10 | CY60: 3 | CZ60: 10 | DA60: 3 | DB60: 10 | DC60: 3 | DD60: 10 | DE60: 3 | DF60: 10 | DG60: 3 | DH60: 10 | DI60: 3 | DJ60: 10 | DK60: 3 | DL60: 10 | DM60: 3 | DN60: 10 | DO60: 3 | DP60: 10 | DQ60: 3 | DR60: 10 | DS60: 3 | DT60: 10 | DY60: 3 | DZ60: 10 | EC60: 3 | ED60: 10 | ES60: 1
H61: {=IF(AND(A61="",B61=""),"",INDIRECT(ADDRESS($M$3,MATCH(IF(A61="",B61,A61),MA!$A$1:$NP$1,0),1,1,"MA")))} | I61: {=IF( SUM(--NOT(ISBLANK(BW61:EP61) ) ),1, "" )} -> 1 | J61: {=IF( SUM(--NOT(ISBLANK(O61:BV61) ) ),1, "" )} | K61: MA | L61: Perf SD Rule | M61: 3 | N61: =IF(ES61="", "", IF(M61>0,M61*ES61,0)) | CW61: 2 | CX61: 10 | CY61: 3 | CZ61: 10
H62: {=IF(AND(A62="",B62=""),"",INDIRECT(ADDRESS($M$3,MATCH(IF(A62="",B62,A62),MA!$A$1:$NP$1,0),1,1,"MA")))} | I62: {=IF( SUM(--NOT(ISBLANK(BW62:EP62) ) ),1, "" )} | J62: {=IF( SUM(--NOT(ISBLANK(O62:BV62) ) ),1, "" )} | K62: MA | L62: !Perf SD Rule | M62: -3 | N62: =IF(ES62="", "", IF(M62>0,M62*ES62,0))
H63: {=IF(AND(A63="",B63=""),"",INDIRECT(ADDRESS($M$3,MATCH(IF(A63="",B63,A63),MA!$A$1:$NP$1,0),1,1,"MA")))} | I63: {=IF( SUM(--NOT(ISBLANK(BW63:EP63) ) ),1, "" )} | J63: {=IF( SUM(--NOT(ISBLANK(O63:BV63) ) ),1, "" )} | K63: MA | L63: !Perf3D Rule | M63: 1 | N63: =IF(ES63="", "", IF(M63>0,M63*ES63,0))
B64: BBHighLow_SD | C64: 2 | D64: 8 | E64: 1 | F64: 2 | G64: 3 | H64: {=IF(AND(A64="",B64=""),"",INDIRECT(ADDRESS($M$3,MATCH(IF(A64="",B64,A64),MA!$A$1:$NP$1,0),1,1,"MA")))} -> -0.17361111 | I64: {=IF( SUM(--NOT(ISBLANK(BW64:EP64) ) ),1, "" )} -> 1 | J64: {=IF( SUM(--NOT(ISBLANK(O64:BV64) ) ),1, "" )} | K64: MA | L64: BBHighLow_SD Rule | M64: 3 | N64: =IF(ES64="", "", IF(M64>0,M64*ES64,0)) -> 3 | CO64: 3 | CP64: 10 | CS64: 3 | CT64: 10 | DG64: 2 | DH64: 10 | DK64: 2 | DL64: 10 | ES64: 1
B65: BBHighLowDays | C65: 4 | D65: 9 | E65: 1 | F65: 2 | G65: 3 | H65: {=IF(AND(A65="",B65=""),"",INDIRECT(ADDRESS($M$3,MATCH(IF(A65="",B65,A65),MA!$A$1:$NP$1,0),1,1,"MA")))} -> 1 | I65: {=IF( SUM(--NOT(ISBLANK(BW65:EP65) ) ),1, "" )} -> 1 | J65: {=IF( SUM(--NOT(ISBLANK(O65:BV65) ) ),1, "" )} -> 1 | K65: MA | L65: BBHighLow Days Rule | M65: 3 | N65: =IF(ES65="", "", IF(M65>0,M65*ES65,0)) | BC65: 1 | BD65: 10 | CO65: 3 | CP65: 10 | CS65: 3 | CT65: 10 | DG65: 2 | DH65: 10 | DK65: 2 | DL65: 10
B66: BB_Streak | C66: 3 | D66: 6 | E66: 1 | F66: 2 | G66: 3 | H66: {=IF(AND(A66="",B66=""),"",INDIRECT(ADDRESS($M$3,MATCH(IF(A66="",B66,A66),MA!$A$1:$NP$1,0),1,1,"MA")))} -> 8 | I66: {=IF( SUM(--NOT(ISBLANK(BW66:EP66) ) ),1, "" )} -> 1 | J66: {=IF( SUM(--NOT(ISBLANK(O66:BV66) ) ),1, "" )} -> 1 | K66: MA | L66: BBStreak Rule | M66: 2 | N66: =IF(ES66="", "", IF(M66>0,M66*ES66,0)) -> 2 | Q66: -3 | R66: 10 | BI66: -2 | BJ66: 10 | CM66: 3 | CN66: 10 | CQ66: 3 | CR66: 10 | ES66: 1
B67: BBStreakRule1 | C67: 3 | D67: 6 | E67: 3 | F67: 2 | G67: 1 | H67: {=IF(AND(A67="",B67=""),"",INDIRECT(ADDRESS($M$3,MATCH(IF(A67="",B67,A67),MA!$A$1:$NP$1,0),1,1,"MA")))} -> 1 | I67: {=IF( SUM(--NOT(ISBLANK(BW67:EP67) ) ),1, "" )} -> 1 | J67: {=IF( SUM(--NOT(ISBLANK(O67:BV67) ) ),1, "" )} | K67: MA | L67: BBStreak Rule1 | M67: 2 | N67: =IF(ES67="", "", IF(M67>0,M67*ES67,0)) -> 2 | CO67: -2 | CP67: 10 | CS67: -2 | CT67: 10 | CY67: -2 | CZ67: 10 | ES67: 1
A68: BB_Streak | B68: BBStreak Rule2 | C68: 4 | D68: 6 | E68: -1 | F68: -2 | G68: -3 | H68: {=IF(AND(A68="",B68=""),"",INDIRECT(ADDRESS($M$3,MATCH(IF(A68="",B68,A68),MA!$A$1:$NP$1,0),1,1,"MA")))} -> 8 | I68: {=IF( SUM(--NOT(ISBLANK(BW68:EP68) ) ),1, "" )} -> 1 | J68: {=IF( SUM(--NOT(ISBLANK(O68:BV68) ) ),1, "" )} -> 1 | K68: MA | L68: BBStreak Rule2 | M68: -3 | N68: =IF(ES68="", "", IF(M68>0,M68*ES68,0)) | W68: 0 | X68: 10 | AO68: 0 | AP68: 10 | AS68: 0 | AT68: 10 | BC68: 0 | BD68: 10 | DK68: 3 | DL68: 10
B69: BB_Streak_Days | C69: 4 | D69: 10 | E69: 3 | F69: 2 | G69: 1 | H69: {=IF(AND(A69="",B69=""),"",INDIRECT(ADDRESS($M$3,MATCH(IF(A69="",B69,A69),MA!$A$1:$NP$1,0),1,1,"MA")))} -> 1 | I69: {=IF( SUM(--NOT(ISBLANK(BW69:EP69) ) ),1, "" )} -> 1 | J69: {=IF( SUM(--NOT(ISBLANK(O69:BV69) ) ),1, "" )} | K69: MA | L69: BBStreak Days Rule | M69: -2 | N69: =IF(ES69="", "", IF(M69>0,M69*ES69,0)) | CM69: 3 | CN69: 10 | CQ69: 3 | CR69: 10 | DK69: 2 | DL69: 10
A70: BB_Streak_Days | B70: BBStreak Days Rule2 | C70: 4 | D70: 8 | E70: 1 | F70: 2 | G70: 3 | H70: {=IF(AND(A70="",B70=""),"",INDIRECT(ADDRESS($M$3,MATCH(IF(A70="",B70,A70),MA!$A$1:$NP$1,0),1,1,"MA")))} -> 1 | I70: {=IF( SUM(--NOT(ISBLANK(BW70:EP70) ) ),1, "" )} | J70: {=IF( SUM(--NOT(ISBLANK(O70:BV70) ) ),1, "" )} -> 1 | K70: MA | L70: BBStreak Days Up Rule | M70: -3 | N70: =IF(ES70="", "", IF(M70>0,M70*ES70,0)) | Q70: 1 | R70: 10
A71: BB_Streak_Days | B71: BBStreak Days Rule3 | C71: 2 | D71: 4 | E71: 3 | F71: 2 | G71: 1 | H71: {=IF(AND(A71="",B71=""),"",INDIRECT(ADDRESS($M$3,MATCH(IF(A71="",B71,A71),MA!$A$1:$NP$1,0),1,1,"MA")))} -> 1 | I71: {=IF( SUM(--NOT(ISBLANK(BW71:EP71) ) ),1, "" )} | J71: {=IF( SUM(--NOT(ISBLANK(O71:BV71) ) ),1, "" )} -> 1 | K71: MA | L71: BBStreak Days Rule2 | M71: 1 | N71: =IF(ES71="", "", IF(M71>0,M71*ES71,0)) | AO71: 2 | AP71: 10 | BC71: 1 | BD71: 10
A72: BB_Streak_Days | B72: BBStreak Days Rule4 | C72: 2 | D72: 4 | E72: 1 | F72: 2 | G72: 3 | H72: {=IF(AND(A72="",B72=""),"",INDIRECT(ADDRESS($M$3,MATCH(IF(A72="",B72,A72),MA!$A$1:$NP$1,0),1,1,"MA")))} -> 1 | I72: {=IF( SUM(--NOT(ISBLANK(BW72:EP72) ) ),1, "" )} | J72: {=IF( SUM(--NOT(ISBLANK(O72:BV72) ) ),1, "" )} -> 1 | K72: MA | L72: BBStreak Days Up Rule2 | M72: 3 | N72: =IF(ES72="", "", IF(M72>0,M72*ES72,0)) | W72: 2 | X72: 10 | AO72: 2 | AP72: 10 | AS72: 2 | AT72: 10 | BI72: 1 | BJ72: 10
H73: {=IF(AND(A73="",B73=""),"",INDIRECT(ADDRESS($M$3,MATCH(IF(A73="",B73,A73),MA!$A$1:$NP$1,0),1,1,"MA")))} | I73: {=IF( SUM(--NOT(ISBLANK(BW73:EP73) ) ),1, "" )} | J73: {=IF( SUM(--NOT(ISBLANK(O73:BV73) ) ),1, "" )} | K73: MA | L73: BB Bull Rule | M73: 0 | N73: =IF(ES73="", "", IF(M73>0,M73*ES73,0))
H74: {=IF(AND(A74="",B74=""),"",INDIRECT(ADDRESS($M$3,MATCH(IF(A74="",B74,A74),MA!$A$1:$NP$1,0),1,1,"MA")))} | I74: {=IF( SUM(--NOT(ISBLANK(BW74:EP74) ) ),1, "" )} | J74: {=IF( SUM(--NOT(ISBLANK(O74:BV74) ) ),1, "" )} | K74: MA | L74: BB Bull Puts | M74: 0 | N74: =IF(ES74="", "", IF(M74>0,M74*ES74,0))
B75: BBHighDays | C75: 10 | D75: 30 | E75: 1 | F75: 2 | G75: 3 | H75: {=IF(AND(A75="",B75=""),"",INDIRECT(ADDRESS($M$3,MATCH(IF(A75="",B75,A75),MA!$A$1:$NP$1,0),1,1,"MA")))} -> 6 | I75: {=IF( SUM(--NOT(ISBLANK(BW75:EP75) ) ),1, "" )} | J75: {=IF( SUM(--NOT(ISBLANK(O75:BV75) ) ),1, "" )} | K75: MA | L75: BBHighDays | M75: 2 | N75: =IF(ES75="", "", IF(M75>0,M75*ES75,0))
B76: BBLowDays | C76: 5 | D76: 10 | E76: 1 | F76: 2 | G76: 3 | H76: {=IF(AND(A76="",B76=""),"",INDIRECT(ADDRESS($M$3,MATCH(IF(A76="",B76,A76),MA!$A$1:$NP$1,0),1,1,"MA")))} -> 14 | I76: {=IF( SUM(--NOT(ISBLANK(BW76:EP76) ) ),1, "" )} | J76: {=IF( SUM(--NOT(ISBLANK(O76:BV76) ) ),1, "" )} | K76: MA | L76: BBLowDays | M76: 3 | N76: =IF(ES76="", "", IF(M76>0,M76*ES76,0))
B77: MACD_BRR | C77: 0.2 | D77: 0.9 | E77: 1 | F77: 2 | G77: 3 | H77: {=IF(AND(A77="",B77=""),"",INDIRECT(ADDRESS($M$3,MATCH(IF(A77="",B77,A77),MA!$A$1:$NP$1,0),1,1,"MA")))} -> 1 | I77: {=IF( SUM(--NOT(ISBLANK(BW77:EP77) ) ),1, "" )} | J77: {=IF( SUM(--NOT(ISBLANK(O77:BV77) ) ),1, "" )} | K77: MA | L77: MACD Rule | M77: 3 | N77: =IF(ES77="", "", IF(M77>0,M77*ES77,0))
B78: MACDH_BRR | C78: 0.2 | D78: 0.9 | E78: 1 | F78: 2 | G78: 3 | H78: {=IF(AND(A78="",B78=""),"",INDIRECT(ADDRESS($M$3,MATCH(IF(A78="",B78,A78),MA!$A$1:$NP$1,0),1,1,"MA")))} -> 0.81 | I78: {=IF( SUM(--NOT(ISBLANK(BW78:EP78) ) ),1, "" )} | J78: {=IF( SUM(--NOT(ISBLANK(O78:BV78) ) ),1, "" )} | K78: MA | L78: MACDH Rule | M78: 3 | N78: =IF(ES78="", "", IF(M78>0,M78*ES78,0))
H79: {=IF(AND(A79="",B79=""),"",INDIRECT(ADDRESS($M$3,MATCH(IF(A79="",B79,A79),MA!$A$1:$NP$1,0),1,1,"MA")))} | I79: {=IF( SUM(--NOT(ISBLANK(BW79:EP79) ) ),1, "" )} | J79: {=IF( SUM(--NOT(ISBLANK(O79:BV79) ) ),1, "" )} | K79: MA | L79: MACD and H Rule | M79: -3 | N79: =IF(ES79="", "", IF(M79>0,M79*ES79,0))
A80: MACD_BRR | B80: MACD_BRR Puts | C80: 0.5 | D80: 0.98 | E80: -1 | F80: -2 | G80: -3 | H80: {=IF(AND(A80="",B80=""),"",INDIRECT(ADDRESS($M$3,MATCH(IF(A80="",B80,A80),MA!$A$1:$NP$1,0),1,1,"MA")))} -> 1 | I80: {=IF( SUM(--NOT(ISBLANK(BW80:EP80) ) ),1, "" )} -> 1 | J80: {=IF( SUM(--NOT(ISBLANK(O80:BV80) ) ),1, "" )} -> 1 | K80: MA | L80: MACD_BRR Puts | M80: -3 | N80: =IF(ES80="", "", IF(M80>0,M80*ES80,0)) | AC80: -3 | AD80: 10 | AY80: -3 | AZ80: 10 | BE80: -3 | BF80: 10 | CE80: -2 | CF80: 10 | DM80: -2 | DN80: 10 | DS80: -2 | DT80: 10
A81: MACDH_BRR | B81: MACDH_BRR Puts | C81: 0.5 | D81: 0.98 | E81: -1 | F81: -2 | G81: -3 | H81: {=IF(AND(A81="",B81=""),"",INDIRECT(ADDRESS($M$3,MATCH(IF(A81="",B81,A81),MA!$A$1:$NP$1,0),1,1,"MA")))} -> 0.81 | I81: {=IF( SUM(--NOT(ISBLANK(BW81:EP81) ) ),1, "" )} -> 1 | J81: {=IF( SUM(--NOT(ISBLANK(O81:BV81) ) ),1, "" )} -> 1 | K81: MA | L81: MACDH_BRR Puts | M81: 0 | N81: =IF(ES81="", "", IF(M81>0,M81*ES81,0)) | AC81: -3 | AD81: 10 | AY81: -3 | AZ81: 10 | BE81: -3 | BF81: 10 | CA81: -2 | CB81: 1 | CC81: -2 | CD81: 1 | CE81: -2 | CF81: 10 | CM81: -2 | CN81: 1 | CO81: -2 | CP81: 1 | CQ81: -2 | CR81: 1 | CS81: -2 | CT81: 1 | CW81: -2 | CX81: 10 | CY81: -2 | CZ81: 1 | DA81: -2 | DB81: 1 | DC81: -2 | DD81: 1 | DE81: -2 | DF81: 1 | DG81: -2 | DH81: 1 | DI81: -2 | DJ81: 1 | DK81: -2 | DL81: 1 | DM81: -2 | DN81: 10 | DO81: -2 | DP81: 1 | DQ81: -2 | DR81: 10 | DS81: -2 | DT81: 10 | DY81: -1 | DZ81: 10 | EC81: -2 | ED81: 1
H82: {=IF(AND(A82="",B82=""),"",INDIRECT(ADDRESS($M$3,MATCH(IF(A82="",B82,A82),MA!$A$1:$NP$1,0),1,1,"MA")))} | I82: {=IF( SUM(--NOT(ISBLANK(BW82:EP82) ) ),1, "" )} | J82: {=IF( SUM(--NOT(ISBLANK(O82:BV82) ) ),1, "" )} | K82: MA | L82: MACD and H Rule Puts | M82: 0 | N82: =IF(ES82="", "", IF(M82>0,M82*ES82,0))
A83: A_MACDays_Streak | B83: MACDH Days | C83: 1 | D83: 3 | E83: 1 | F83: 2 | G83: 3 | H83: {=IF(AND(A83="",B83=""),"",INDIRECT(ADDRESS($M$3,MATCH(IF(A83="",B83,A83),MA!$A$1:$NP$1,0),1,1,"MA")))} -> 1 | I83: {=IF( SUM(--NOT(ISBLANK(BW83:EP83) ) ),1, "" )} -> 1 | J83: {=IF( SUM(--NOT(ISBLANK(O83:BV83) ) ),1, "" )} | K83: MA | L83: MACDH Days | M83: 0 | N83: =IF(ES83="", "", IF(M83>0,M83*ES83,0)) | CA83: 2 | CB83: 10 | DC83: 2 | DD83: 10 | DE83: 2 | DF83: 10 | DK83: 3 | DL83: 10 | DM83: 3 | DN83: 10 | DO83: 3 | DP83: 10 | DQ83: 2 | DR83: 10 | DY83: 2 | DZ83: 10 | EC83: 2 | ED83: 10
A84: A_MACDays_Streak | B84: MACDH Days2 | C84: 1 | D84: 3 | E84: 3 | F84: 2 | G84: 1 | H84: {=IF(AND(A84="",B84=""),"",INDIRECT(ADDRESS($M$3,MATCH(IF(A84="",B84,A84),MA!$A$1:$NP$1,0),1,1,"MA")))} -> 1 | I84: {=IF( SUM(--NOT(ISBLANK(BW84:EP84) ) ),1, "" )} | J84: {=IF( SUM(--NOT(ISBLANK(O84:BV84) ) ),1, "" )} | K84: MA | L84: MACDH Days2 | M84: 0 | N84: =IF(ES84="", "", IF(M84>0,M84*ES84,0))
B85: Overbought | H85: {=IF(AND(A85="",B85=""),"",INDIRECT(ADDRESS($M$3,MATCH(IF(A85="",B85,A85),MA!$A$1:$NP$1,0),1,1,"MA")))} -> 0 | I85: {=IF( SUM(--NOT(ISBLANK(BW85:EP85) ) ),1, "" )} | J85: {=IF( SUM(--NOT(ISBLANK(O85:BV85) ) ),1, "" )} | K85: MA | L85: Overbought | M85: 2 | N85: =IF(ES85="", "", IF(M85>0,M85*ES85,0))
H86: {=IF(AND(A86="",B86=""),"",INDIRECT(ADDRESS($M$3,MATCH(IF(A86="",B86,A86),MA!$A$1:$NP$1,0),1,1,"MA")))} | I86: {=IF( SUM(--NOT(ISBLANK(BW86:EP86) ) ),1, "" )} -> 1 | J86: {=IF( SUM(--NOT(ISBLANK(O86:BV86) ) ),1, "" )} | K86: MA | L86: !Overbought | M86: 0 | N86: =IF(ES86="", "", IF(M86>0,M86*ES86,0)) | CM86: 0 | CN86: 1 | CO86: 0 | CP86: 10 | CQ86: 0 | CR86: 1 | CS86: 0 | CT86: 10 | CW86: 0 | CX86: 10 | CY86: 0 | CZ86: 10
B87: 3mn_stk_outlook_sd | C87: 3 | D87: 6 | E87: 1 | F87: 2 | G87: 3 | H87: {=IF(AND(A87="",B87=""),"",INDIRECT(ADDRESS($M$3,MATCH(IF(A87="",B87,A87),MA!$A$1:$NP$1,0),1,1,"MA")))} -> 5.6388889 | I87: {=IF( SUM(--NOT(ISBLANK(BW87:EP87) ) ),1, "" )} | J87: {=IF( SUM(--NOT(ISBLANK(O87:BV87) ) ),1, "" )} | K87: MA | L87: 3mn Outlook | M87: 2 | N87: =IF(ES87="", "", IF(M87>0,M87*ES87,0))
B88: 3mnHighLowDays | C88: 6 | D88: 12 | E88: 1 | F88: 2 | G88: 3 | H88: {=IF(AND(A88="",B88=""),"",INDIRECT(ADDRESS($M$3,MATCH(IF(A88="",B88,A88),MA!$A$1:$NP$1,0),1,1,"MA")))} -> 40 | I88: {=IF( SUM(--NOT(ISBLANK(BW88:EP88) ) ),1, "" )} | J88: {=IF( SUM(--NOT(ISBLANK(O88:BV88) ) ),1, "" )} | K88: MA | L88: 3mn Outlook Days | M88: 0 | N88: =IF(ES88="", "", IF(M88>0,M88*ES88,0))
B89: 3w_stk_outlook_sd | C89: 2 | D89: 4 | E89: 1 | F89: 2 | G89: 3 | H89: {=IF(AND(A89="",B89=""),"",INDIRECT(ADDRESS($M$3,MATCH(IF(A89="",B89,A89),MA!$A$1:$NP$1,0),1,1,"MA")))} -> 4.3125 | I89: {=IF( SUM(--NOT(ISBLANK(BW89:EP89) ) ),1, "" )} | J89: {=IF( SUM(--NOT(ISBLANK(O89:BV89) ) ),1, "" )} | K89: MA | L89: 3wk Outlook | M89: 3 | N89: =IF(ES89="", "", IF(M89>0,M89*ES89,0))
B90: 3wkHighLowDays | C90: 4 | D90: 8 | E90: 1 | F90: 2 | G90: 3 | H90: {=IF(AND(A90="",B90=""),"",INDIRECT(ADDRESS($M$3,MATCH(IF(A90="",B90,A90),MA!$A$1:$NP$1,0),1,1,"MA")))} -> 13 | I90: {=IF( SUM(--NOT(ISBLANK(BW90:EP90) ) ),1, "" )} | J90: {=IF( SUM(--NOT(ISBLANK(O90:BV90) ) ),1, "" )} | K90: MA | L90: 3wk Outlook Days | M90: -1 | N90: =IF(ES90="", "", IF(M90>0,M90*ES90,0))
H91: {=IF(AND(A91="",B91=""),"",INDIRECT(ADDRESS($M$3,MATCH(IF(A91="",B91,A91),MA!$A$1:$NP$1,0),1,1,"MA")))} | I91: {=IF( SUM(--NOT(ISBLANK(BW91:EP91) ) ),1, "" )} | J91: {=IF( SUM(--NOT(ISBLANK(O91:BV91) ) ),1, "" )} | K91: MA | L91: !3wk Outlook | M91: 0 | N91: =IF(ES91="", "", IF(M91>0,M91*ES91,0))
H92: {=IF(AND(A92="",B92=""),"",INDIRECT(ADDRESS($M$3,MATCH(IF(A92="",B92,A92),MA!$A$1:$NP$1,0),1,1,"MA")))} | I92: {=IF( SUM(--NOT(ISBLANK(BW92:EP92) ) ),1, "" )} | J92: {=IF( SUM(--NOT(ISBLANK(O92:BV92) ) ),1, "" )} | K92: MA | L92: !3wk Outlook Days | M92: 0 | N92: =IF(ES92="", "", IF(M92>0,M92*ES92,0))
H93: {=IF(AND(A93="",B93=""),"",INDIRECT(ADDRESS($M$3,MATCH(IF(A93="",B93,A93),MA!$A$1:$NP$1,0),1,1,"MA")))} | I93: {=IF( SUM(--NOT(ISBLANK(BW93:EP93) ) ),1, "" )} -> 1 | J93: {=IF( SUM(--NOT(ISBLANK(O93:BV93) ) ),1, "" )} | K93: MA | L93: Bull Rule | M93: 0 | N93: =IF(ES93="", "", IF(M93>0,M93*ES93,0)) | CW93: 3 | CX93: 10
H94: {=IF(AND(A94="",B94=""),"",INDIRECT(ADDRESS($M$3,MATCH(IF(A94="",B94,A94),MA!$A$1:$NP$1,0),1,1,"MA")))} | I94: {=IF( SUM(--NOT(ISBLANK(BW94:EP94) ) ),1, "" )} | J94: {=IF( SUM(--NOT(ISBLANK(O94:BV94) ) ),1, "" )} | K94: MA | L94: !Bull Rule | M94: 0.5 | N94: =IF(ES94="", "", IF(M94>0,M94*ES94,0))
H95: {=IF(AND(A95="",B95=""),"",INDIRECT(ADDRESS($M$3,MATCH(IF(A95="",B95,A95),MA!$A$1:$NP$1,0),1,1,"MA")))} | I95: {=IF( SUM(--NOT(ISBLANK(BW95:EP95) ) ),1, "" )} | J95: {=IF( SUM(--NOT(ISBLANK(O95:BV95) ) ),1, "" )} -> 1 | K95: MA | L95: PerfOrBull Rule | M95: 1 | N95: =IF(ES95="", "", IF(M95>0,M95*ES95,0)) | W95: 2 | X95: 10 | Y95: 2 | Z95: 10 | AE95: 2 | AF95: 10 | AG95: 2 | AH95: 10 | AO95: 2 | AP95: 10 | AQ95: 2 | AR95: 10 | AS95: 2 | AT95: 10 | AU95: 2 | AV95: 10 | AW95: 2 | AX95: 10 | AY95: 2 | AZ95: 10 | BA95: 2 | BB95: 10
H96: {=IF(AND(A96="",B96=""),"",INDIRECT(ADDRESS($M$3,MATCH(IF(A96="",B96,A96),MA!$A$1:$NP$1,0),1,1,"MA")))} | I96: {=IF( SUM(--NOT(ISBLANK(BW96:EP96) ) ),1, "" )} | J96: {=IF( SUM(--NOT(ISBLANK(O96:BV96) ) ),1, "" )} -> 1 | K96: MA | L96: !PerfOrBull Rule | M96: -1 | N96: =IF(ES96="", "", IF(M96>0,M96*ES96,0)) | AI96: -3 | AJ96: 10 | AK96: -3 | AL96: 10 | BC96: -3 | BD96: 10 | BE96: -3 | BF96: 10 | BS96: -3 | BT96: 10
B97: 50 DMA | C97: 2 | D97: 4 | E97: 1 | F97: 2 | G97: 3 | H97: {=IF(AND(A97="",B97=""),"",INDIRECT(ADDRESS($M$3,MATCH(IF(A97="",B97,A97),MA!$A$1:$NP$1,0),1,1,"MA")))} -> 82.11 | I97: {=IF( SUM(--NOT(ISBLANK(BW97:EP97) ) ),1, "" )} -> 1 | J97: {=IF( SUM(--NOT(ISBLANK(O97:BV97) ) ),1, "" )} | K97: MA | L97: 50-DMA-Rule | M97: 2 | N97: =IF(ES97="", "", IF(M97>0,M97*ES97,0)) -> 2 | CW97: 1 | CX97: 10 | CY97: 1 | CZ97: 10 | DS97: 1 | DT97: 1 | ES97: 1
H98: {=IF(AND(A98="",B98=""),"",INDIRECT(ADDRESS($M$3,MATCH(IF(A98="",B98,A98),MA!$A$1:$NP$1,0),1,1,"MA")))} | I98: {=IF( SUM(--NOT(ISBLANK(BW98:EP98) ) ),1, "" )} -> 1 | J98: {=IF( SUM(--NOT(ISBLANK(O98:BV98) ) ),1, "" )} | K98: MA | L98: 50-DMA-Crossover | M98: 2 | N98: =IF(ES98="", "", IF(M98>0,M98*ES98,0)) | DS98: 0 | DT98: 1
B99: 200 DMA | C99: 2 | D99: 4 | E99: 1 | F99: 2 | G99: 3 | H99: {=IF(AND(A99="",B99=""),"",INDIRECT(ADDRESS($M$3,MATCH(IF(A99="",B99,A99),MA!$A$1:$NP$1,0),1,1,"MA")))} -> 82.69 | I99: {=IF( SUM(--NOT(ISBLANK(BW99:EP99) ) ),1, "" )} -> 1 | J99: {=IF( SUM(--NOT(ISBLANK(O99:BV99) ) ),1, "" )} | K99: MA | L99: 200-DMA-Rule | M99: 1 | N99: =IF(ES99="", "", IF(M99>0,M99*ES99,0)) -> 1 | DS99: 1 | DT99: 1 | ES99: 1
H100: {=IF(AND(A100="",B100=""),"",INDIRECT(ADDRESS($M$3,MATCH(IF(A100="",B100,A100),MA!$A$1:$NP$1,0),1,1,"MA")))} | I100: {=IF( SUM(--NOT(ISBLANK(BW100:EP100) ) ),1, "" )} -> 1 | J100: {=IF( SUM(--NOT(ISBLANK(O100:BV100) ) ),1, "" )} | K100: MA | L100: 200-DMA-Crossover | M100: 0 | N100: =IF(ES100="", "", IF(M100>0,M100*ES100,0)) | DS100: 0 | DT100: 1
...

Sheet MA
A1: Key | B1: Symbol | C1: Y Symbol | D1: Close | E1: Company Name | F1: Last | G1: Last Net Chng | H1: Last %Change | I1: High | J1: Low | K1: RR LRR | L1: RR TRR | M1: TOS Daily Export Date | N1: TOS Weekly Export Date | O1: TOS Latest Export Date | P1: TOS Other Export Date | Q1: Y Mkt Close Export | R1: Y Latest Exp Date | S1: Use Latest | T1: II Date | U1: ETF Date | V1: SSH Date | W1: FH Date | X1: CS Date | Y1: RR Date | Z1: Sort Symbol | AA1: StandardDeviation | AB1: Median SD | AC1: SDorMedian | AD1: SD% | AE1: A_TrendValue | AF1: A_TradeValue | AG1: Trend_sd | AH1: Trade_sd | AI1: Trade_Trend_Sd | AJ1: A_BBHighLow | AK1: BBHighLow_A | AL1: BBHighLow | AM1: BBHighLowDays | AN1: BB_Direction1 | AO1: BBHighLow_SD | AP1: A_BBHighLowDays | AQ1: BBHighDays | AR1: BBLowDays | AS1: A_BB_Streak | AT1: BB_Streak_1 | AU1: BB_Streak_2 | AV1: BB_Streak_cur | AW1: BB_Threshold_Crossover | AX1: BBThresh_CO_Days | AY1: BB_Streak | AZ1: BB_Streak_Days | BA1: A_3mnLow | BB1: 3mnLow_sd | BC1: 3mnLowDays | BD1: A_3mnHigh | BE1: 3mnHigh_sd | BF1: 3mnHighDays | BG1: 3mn_min_BRR% | BH1: A_3mnHighLow | BI1: 3mnHighLow | BJ1: 3mn_stk_outlook_sd | BK1: 3mnHighLowDays | BL1: A_3wkHighLow | BM1: 3wkHighLow | BN1: 3w_stk_outlook_sd | BO1: 3wkHighLowDays | BP1: Perf3M | BQ1: Perf3M_sd | BR1: A_Perf2M | BS1: Perf2M_sd | BT1: Perf3W | BU1: Perf3W_sd | BV1: A_Perf2Wk | BW1: Perf2Wk_sd | BX1: A_Perf3D | BY1: Perf3D_sd | BZ1: Perf3D_Value | CA1: Perf1D_sd | CB1: Perf | CC1: 52Low | CD1: 52High | CE1: 52-Wk High % | CF1: 20 DMA | CG1: 50 DMA | CH1: 200 DMA | CI1: A_MACD_BRR | CJ1: MACD_BRR | CK1: A_MACDH_D_BRR | CL1: MACDH_BRR | CM1: A_MACDays_Streak | CN1: D_Last | CO1: D_%Change | CP1: D_Net Chng | CQ1: D_Open | CR1: D_High | CS1: D_Low | CT1: D_RSI | CU1: D_IV | CV1: D_HV | CW1: HVPercentile | CX1: IVPercentile | CY1: L_Last | CZ1: L_Net Chng | DA1: L_%Change | DB1: L_Open | DC1: L_High | DD1: L_Low | DE1: L_RSI | DF1: L_ImpVolatility | DG1: Y_Last Price | DH1: Y_Change | DI1: Y_Change(%) | DJ1: Y_Open | DK1: Y_High | DL1: Y_Low | DM1: Last | DN1: Net Chng | DO1: %Change | DP1: Open | DQ1: High | DR1: Low | DS1: RSI | DT1: ImpVolatility | DU1: BB_Bot_Prev | DV1: BB_Top_Prev | DW1: BB BRR% | DX1: RR_Bottom | DY1: RR_Top | DZ1: RR BRR% | EA1: ETF_Bottom | EB1: ETF_Top | EC1: RR_Bottom | ED1: RR_Top | EE1: BRR% | EF1: Prev Close | EG1: Open | EH1: High | EI1: Low | EJ1: Open | EK1: High | EL1: Low | EM1: Chg SD | EN1: Price Direction | EO1: High TRR | EP1: Low LRR | EQ1: Trnd TRR | ER1: Trd LRR | ES1: Sd TRR | ET1: Sd MRR | EU1: Sd LRR | EV1: BB_Bot_15d | EW1: BB_Bot_7d | EX1: BB_Bot_3d | EY1: BB_Bot_Slope | EZ1: BB_Top_15d | FA1: BB_Top_7d | FB1: BB_Top_3d | FC1: BB_Tot_Slope | FD1: BB_Slope | FE1: BB Bull | FF1: A_VolumeSpike | FG1: VolumeSpike | FH1: VS Spike | FI1: VS Volume Spike | FJ1: VS Price Change | FK1: VS Price Change SD | FL1: VS Volatility | FM1: VS Days | FN1: D_Vlt_Caution | FO1: D_Vlt_RuleCode | FP1: D_Vlt_RuleDesc | FQ1: D_Vlt_RuleAction | FR1: IVHV | FS1: L_Vlm | FT1: W_Vlm | FU1: Volume | FV1: VolumeRateOfChange | FW1: W_Avg Vlm (10day) | FX1: Vlm 10 Factor | FY1: Vlm 10 day % | FZ1: W_Avg Vlm (3m) | GA1: Vlm 3 M Factor | GB1: Vlm 3m % | GC1: Vlm Score | GD1: Vlm Desc | GE1: W_Vlm_RuleCode | GF1: Vlm_RuleDesc | GG1: Vlm_Action | GH1: Volatility regime | GI1: Volatility regime | GJ1: Price zone | GK1: Price zone | GL1: Trend context | GM1: Trend context | GN1: Momentum | GO1: Momentum | GP1: Long Trend Total | GQ1: Long Trend Score | GR1: Long Trend Descr | GS1: ST Signal Scenario | GT1: ST_Signal Score | GU1: ST_Signal Desc | GV1: Final Signal Scenario | GW1: Final_Signal | GX1: Beta | GY1: Market Cap | GZ1: Long-term Debt to Capital - Current (LTM) | HA1: Price / Earnings Ratio - Current | HB1: Price / Book Value Ratio - Current | HC1: Return on Equity (ROE) - Current (LTM) | HD1: EPS | HE1: Div. Yield - Current | HF1: Sector | HG1: Free Cash Flow Per Share - Current (LTM) | HH1: Asset Class | HI1: Sctr!Sector | HJ1: Sector | HK1: Sub Asset Class | HL1: Industry | HM1: Growth - Sector Based | HN1: Growth - Econ Based | HO1: Growth | HP1: Scale | HQ1: Solvency | HR1: Value? | HS1: Quality? | HT1: Dividend? | HU1: Momentum Score | HV1: Momentum | HW1: Sensitivity | HX1: Growth - M OL | HY1: Scale - M OL | HZ1: Solvency - M OL | IA1: Value? - M OL | IB1: Quality? - M OL | IC1: Dividend? - M OL | ID1: Momentum - M OL | IE1: Sensitivity - M OL | IF1: Asset Class - M OL | IG1: Equity Sector - M OL | IH1: M+ves - Equity Style | II1: M-ves - Equity Style | IJ1: Growth - Q OL | IK1: Scale - Q OL | IL1: Solvency - Q OL | IM1: Value? - Q OL | IN1: Quality? - Q OL | IO1: Dividend? - Q OL | IP1: Momentum - Q OL | IQ1: Sensitivity - Q OL | IR1: Asset Class - Q OL | IS1: Equity Sector - Q OL | IT1: Q+ves - Equity Style | IU1: Q-ves - Equity Style | IV1: SP500 Volatility | IW1: Nasdaq Volatility | IX1: Dow Volatility | IY1: RusSell Volatility | IZ1: FCF | JA1: Ticker | JB1: EarningsDays | JC1: Short Ratio | JD1: Float | JE1: Shares Out | JF1: Begin | JG1: MACDH Direction | JH1: MACD Direction | JI1: BB Direction | JJ1: BB Threshold | JK1: BBThresh CO Days | JL1: BBThresh_CO_Days2 | JM1: Trade Cross Over | JN1: Trade-Rule | JO1: !Trade Rule | JP1: Trend Cross Over | JQ1: Trend-Rule | JR1: !Trend Rule | JS1: Trend Trade Dep Rule | JT1: TrTn Relation | JU1: !TrTn Relation | JV1: Trade Trend SD Rule | JW1: BRR% Rule | JX1: BRR% LRR | JY1: BRR% R2 | JZ1: BRR% LRR2 | KA1: BRR% TRR | KB1: BRR% Puts | KC1: BRR% TRR Puts | KD1: BRR% Dir | KE1: High TRR | KF1: Low LRR | KG1: Trend below TRR | KH1: LRR above Trade | KI1: TRR_Idx | KJ1: MRR_Idx | KK1: LRR_Idx | KL1: HVAbsolute | KM1: IVAbsolute | KN1: IVPercentile | KO1: IVPercentile Puts | KP1: HVPercentile | KQ1: HVPercentile Puts | KR1: IVHV | KS1: IVHV Puts | KT1: IVRule | KU1: RSI Rule | KV1: RSI Top | KW1: RSI Puts | KX1: 3m-Low-Rule | KY1: 3m-Low-Days Rule | KZ1: 3mn-High-Rule | LA1: 3mn-High-Days Rule | LB1: 3m-Long | LC1: Perf3mn SD Rule | LD1: Perf2M SD Rule | LE1: Perf3WK SD Rule | LF1: Perf2WK SD Rule | LG1: Perf3D SD Rule | LH1: Perf1D SD Rule | LI1: !Perf1D_sd | LJ1: Perf3D_sd_1off | LK1: Perf SD Rule | LL1: !Perf SD Rule | LM1: !Perf3D Rule | LN1: BBHighLow_SD Rule | LO1: BBHighLow Days Rule | LP1: BBStreak Rule | LQ1: BBStreakRule1 | LR1: BBStreak Rule2 | LS1: BBStreak Days Rule | LT1: BBStreak Days Rule2 | LU1: BBStreak Days Rule3 | LV1: BBStreak Days Rule4 | LW1: BB Bull Rule | LX1: BB Bull Puts | LY1: BBHighDays | LZ1: BBLowDays | MA1: MACD Rule | MB1: MACDH Rule | MC1: MACD and H Rule | MD1: MACD_BRR Puts | ME1: MACDH_BRR Puts | MF1: MACD and H Rule Puts | MG1: MACDH Days | MH1: MACDH Days2 | MI1: Overbought | MJ1: !Overbought | MK1: 3mn Outlook | ML1: 3mn Outlook Days | MM1: 3wk Outlook | MN1: 3wk Outlook Days | MO1: !3wk ol | MP1: !3wk ol days | MQ1: BULL | MR1: !BULL | MS1: PerfOrBull | MT1: !PerfOrBull | MU1: 50-DMA-Rule | MV1: 50-DMA-Crossover | MW1: 200-DMA-Rule | MX1: 200-DMA-Crossover | MY1: 52-Wk Low Rule | MZ1: 52-Wk High Rule | NA1: BRRTrade | NB1: TRRTrade | NC1: Up Resistance | ND1: Down Resistance | NE1: Earnings | NF1: VS Price | NG1: VS Volume Spike | NH1: VS Volatility | NI1: VS Days | NJ1: VS LT Outlook Rule | NK1: Current Price SD Rule | NL1: Current Volume Rule | NM1: Current Volatility Rule | NN1: Short Term Oulook (If LT Bullish) | NO1: Short Term Oulook (If LT Bearish) | NP1: End | NQ1: =Trig!O1 -> 899-SA-Trend-Breaks | NR1: =Trig!Q1 -> 898-SA-Streak-VeryBad | NS1: =Trig!S1 -> 897-SW-Vlm-Spike-Price-Dn | NT1: =Trig!U1 -> 896-SA-TRbelowTN-Trade-Breaks | NU1: =Trig!W1 -> 895-SA-!TN!TD!Bull-TRR-Rev | NV1: =Trig!Y1 -> 894-SA-!Bull-TN-TRR | NW1: =Trig!AA1 -> 893-SA-TRR-blw-TN | NX1: =Trig!AC1 -> 889-STM-OverBought | NY1: =Trig!AE1 -> 888-STM-!Bull-BBTh-Crossover-RSI-IVHV | NZ1: =Trig!AG1 -> 887-STM-!Bull--BBTh-Crossover-RSI-IV | OA1: =Trig!AI1 -> 859-SS-Bull-BBTh-Crossover-RSI-IVHV | OB1: =Trig!AK1 -> 858-SS-Bull-BBTh-Crossover-RSI-IV | OC1: =Trig!AM1 -> 857-SS-BBTh-Crossover-RSIOnly | OD1: =Trig!AO1 -> 798-STM-!Bull-TRR-Rev | OE1: =Trig!AQ1 -> 796-SW-!Bull-BBTh-Crossover | OF1: =Trig!AS1 -> 793-STM-!TD!Bull-TRR-Rev | OG1: =Trig!AU1 -> 792-STM-Bull-TN-TD-TRR-RSI-IV | OH1: =Trig!AW1 -> 791-STM-!Bull-HighAbvTRR | OI1: =Trig!AY1 -> 789-SS-!Bull-OverBought | OJ1: =Trig!BA1 -> 788-SS-!Bull-TN-TD-TRR | OK1: =Trig!BC1 -> 787-SS-Bull-TRR-Rev | OL1: =Trig!BE1 -> 786-SS-Bull-OverBought | OM1: =Trig!BG1 -> 785-SS-Trade-Breaks | ON1: =Trig!BI1 -> 784-SS-Streak-GoingBad | OO1: =Trig!BK1 -> 783-SW-Vol-Spke-Price-Dn-Past | OP1: =Trig!BM1 -> 782-SS-3mnHigh | OQ1: =Trig!BO1 -> 781-SS-TRR-CloseToTrade | OR1: =Trig!BQ1 -> 699-SW-Resistance | OS1: =Trig!BS1 -> 698-SS-Bull-HighAbvTRR | OT1: =Trig!BU1 -> 697-STM-Earnings-Date | OU1: =Trig!BW1 -> 449-B-TN-TD-LRR-UP-MACD | OV1: =Trig!BY1 -> 448-BS-TN-TD-LRR | OW1: =Trig!CA1 -> 399-B-TN-TD-LRR-UP-MACD | OX1: =Trig!CC1 -> 398-B-TN-TD-LRR-UP-DAY | OY1: =Trig!CE1 -> 397-B-TN-TD-LRR | OZ1: =Trig!CG1 -> 396-BS-LRR-CloseToTrade | PA1: =Trig!CI1 -> 395-BS-TN-TD-LRR | PB1: =Trig!CK1 -> 394-BS-TN-LRR | PC1: =Trig!CM1 -> 299-BS-BB-Streak-HiHi-TN-TD | PD1: =Trig!CO1 -> 298-BS-BB-HL-HiHi-TN-TD | PE1: =Trig!CQ1 -> 279-BS-BB-Streak-HiHi | PF1: =Trig!CS1 -> 278-BS-BB-HL-HiHi | PG1: =Trig!CU1 -> 277-BS-VS-LT | PH1: =Trig!CW1 -> 269-BS-Bull | PI1: =Trig!CY1 -> 268-BS-3M-HiHi | PJ1: =Trig!DA1 -> 267-BS-Trade-CO | PK1: =Trig!DC1 -> 199-BS-TN-LRR-MACD-UP-DAY | PL1: =Trig!DE1 -> 198-BS-TN-LRR-UP-MACD | PM1: =Trig!DG1 -> 197-BS-TN-LRR-UP-DAY | PN1: =Trig!DI1 -> 196-BS-TN-LRR | PO1: =Trig!DK1 -> 189-BR-BB-LoHi | PP1: =Trig!DM1 -> 188-BR-TNabvTD-UP-MACD-DAY | PQ1: =Trig!DO1 -> 187-BR-NoTN-NoTD-UP-MACD-DAY | PR1: =Trig!DQ1 -> 186-BR-Trend-CO | PS1: =Trig!DS1 -> 99-BS-Min | PT1: =Trig!DU1 -> 98-BW-TD-LRR-RSI | PU1: =Trig!DW1 -> 97-BW-TD-RSI-IV | PV1: =Trig!DY1 -> 96-BW-RSI-IVHV-Min | PW1: =Trig!EA1 -> 95-BW-LowBelwLRR | PX1: =Trig!EC1 -> 94-BW-UP-MACD | PY1: =Trig!EE1 -> 93-BW-LRRabvTD | PZ1: =Trig!EG1 -> 92-BS-RSI-MACD-Vlme-IVHV-IVBRR | QA1: =Trig!EI1 -> 92-BS-RSI-MACD-Vlme-IVHV-IVBRR | QB1: =Trig!EK1 -> 92-BS-RSI-MACD-Vlme-IVHV-IVBRR | QC1: =Trig!EM1 -> 52-BS-BRR | QD1: =Trig!EO1 -> 51-BS-TRADE-TREND | QE1: Tn Td Rule | QF1: Tn Td Rule Action | QG1: Tn Td Rule Desc | QH1: A_BB_Bot_Slope | QI1: A_BB_Top_Slope | QJ1: BBRngStrkRule | QK1: BBRngStrkRule Action | QL1: BBRngStrkRule Desc | QM1: BullRiskRng-Action | QN1: !BullRiskRng-Action | QO1: RiskRng Longs Action | QP1: RRBullBear | QQ1: RRDesc | QR1: Td Tn BB Risk Range Rule Action | QS1: Td Tn BB Risk Range Rule Action | QT1: Td Tn BB Risk Range Rule Action Seq | QU1: PS Rk | QV1: PS Outlook | QW1: PSRk Chg | QX1: ETF | QY1: II | QZ1: II Chg | RA1: II Final | RB1: CAll | RC1: CAll Modifier | RD1: RR | RE1: Sg Rk | RF1: KM | RG1: SgRk Chg | RH1: Sg Strength | RI1: SgS Chg | RJ1: Sig OL | RK1: Sig Rating | RL1: HE Outlook | RM1: SSS Entry | RN1: PS Date | RO1: ETF Date | RP1: II Date | RQ1: CAll Date | RR1: RR Date | RS1: PS Entry | RT1: ETF Entry | RU1: II Entry | RV1: CAll Entry | RW1: RR Entry | RX1: HE Entry | RY1: SSS Date | RZ1: SS Entry Only | SA1: HE Entry | SB1: PS Cont | SC1: ETF Cont | SD1: II Cont | SE1: CAll Cont | SF1: RR Cont | SG1: HE Cont | SH1: SS Entry Only | SI1: SSS Cont | SJ1: Trig Matched Rule1 | SK1: Trig M Rule2 | SL1: Trig M Rule3 | SM1: Trig M Rule4 | SN1: Trig M Rule5 | SO1: Trig M Rule6 | SP1: Trig M Rule7 | SQ1: Trig M Rule8 | SR1: Trig M Rule9 | SS1: Trig M Rule10 | ST1: Trig M Rule11 | SU1: Blanks | SV1: Negatives | SW1: Positives | SX1: Neg Rank | SY1: Pos Rank | SZ1: Trig Rule | TA1: HE Entry | TB1: HE Cont | TC1: SS Entry | TD1: SS Cont | TE1: Trig | TF1: Blanks | TG1: Negatives | TH1: Positives | TI1: Neg Rank | TJ1: Pos Rank | TK1: Entry | TL1: HE Cont | TM1: SS Cont | TN1: Trig | TO1: Blanks | TP1: Negatives | TQ1: Positives | TR1: Neg Rank | TS1: Pos Rank | TT1: Cont | TU1: OverAll | TV1: OverAll Group | TW1: Action Type | TX1: ^L1 | TY1: ^L2 | TZ1: ^L3 | UA1: #Actionable | UB1: Index | UC1: Neg Outlook | UD1: Pos Outlook | UE1: Fidelity | UF1: CS | UG1: Stocks$ | UH1: RH | UI1: Long$ | UJ1: Short$ | UK1: My | UL1: Amt Type | UM1: Unit$ | UN1: Min$ | UO1: Max$ | UP1: TnTdMax$ | UQ1: Remaining | UR1: Final Action | US1: Amount | UT1: Amount | UU1: Final Action | UV1: Amount | UW1: Amount | UX1: PVV Rule | UY1: #Tickers to include | UZ1: #Act | VA1: #F1 Seq | VB1: #Fidelity | VC1: #CS | VD1: ^Sell | VE1: ^Buy | VF1: OA Group | VG1: ^L3 | VH1: My | VI1: Fidelity | VJ1: CS | VK1: Remaining | VL1: PVV Rule | VM1: Tn Stdv | VN1: Td Stdv | VO1: Tn Td Stdv Diff | VP1: HE Outlook | VQ1: Tr Td Outlook | VR1: BRR% | VS1: Sector Ticker | VT1: HE OL - Sector | VU1: Tn Td Rule | VV1: BRR% - Sector | VW1: Asset Class - M OL | VX1: Equity Sector - M OL | VY1: M+ves - Equity Style | VZ1: M-ves - Equity Style | WA1: Asset Class - Q OL | WB1: Equity Sector - Q OL | WC1: Q+ves - Equity Style | WD1: Q-ves - Equity Style | WE1: ST_Signal Desc | WF1: ST_Signal Action | WG1: D_Vlt_Caution | WH1: D_Vlt_RuleDesc | WI1: Vlm_RuleDesc | WJ1: Vlm_RuleAction | WK1: Vlm Desc | WL1: Volatility regime | WM1: Tn Td Rule Desc | WN1: BBRngStrkRule Desc | WO1: RRBullBear | WP1: RRDesc | WQ1: Opposite Outlook | WR1: Outlook | WS1: Portfolio | WT1: Ticker | WU1: Td Tn BB Risk Range Rule Action | WV1: Amount | WW1: Final Action | WX1: Amount | WY1: HE Entry | WZ1: HE Cont | XA1: SS Entry | XB1: SS Cont | XC1: Trig | XD1: Entry | XE1: Cont | XF1: OverAll | XG1: Matched Rule1 | XH1: M Rule2 | XI1: M Rule3 | XJ1: M Rule4 | XK1: M Rule5 | XL1: M Rule6 | XM1: M Rule7 | XN1: M Rule8 | XO1: M Rule9 | XP1: M Rule10 | XQ1: M Rule11
